[
  {
    "league_id": "APTACHICAGO",
    "source_league": "APTACHICAGO",
    "match_id": "nndz-WWk2NnhycndnZz09_Line1",
    "url": "https://aptachicago.tenniscores.com/print_match.php?sch=nndz-WWk2NnhycndnZz09&print&",
    "Home Team": "Lake Forest 14",
    "Away Team": "Skokie 14",
    "Scores": "6-0, 6-3",
    "Line": "Line 1",
    "Away Player 1": "John Croghan",
    "Away Player 2": "Declan Kavanaugh",
    "Away Player 1 ID": "nndz-WkNPd3g3Yjhodz09",
    "Away Player 2 ID": "nndz-WkNHNXdicndqQT09",
    "Home Player 1": "Jason Perlioni",
    "Home Player 2": "Hunter Gordy",
    "Home Player 1 ID": "nndz-WkNHeHdyL3hoZz09",
    "Home Player 2 ID": "nndz-WkNHeHdyYjRnQT09",
    "Winner": "away",
    "Date": "14-Sep-25"
  },
  {
    "league_id": "APTACHICAGO",
    "source_league": "APTACHICAGO",
    "match_id": "nndz-WWk2NnhycndnZz09_Line2",
    "url": "https://aptachicago.tenniscores.com/print_match.php?sch=nndz-WWk2NnhycndnZz09&print&",
    "Home Team": "Lake Forest 14",
    "Away Team": "Skokie 14",
    "Scores": "6-7, 4-6",
    "Line": "Line 2",
    "Away Player 1": "Sam Barden",
    "Away Player 2": "Erik Falk",
    "Away Player 1 ID": "nndz-WkMrK3didnhodz09",
    "Away Player 2 ID": "nndz-WkNDOXlMendoUT09",
    "Home Player 1": "Alex Kane",
    "Home Player 2": "Mike Hall",
    "Home Player 1 ID": "nndz-WkM2OHg3cnhqQT09",
    "Home Player 2 ID": "nndz-WkNHeHhiNzZnZz09",
    "Winner": "home",
    "Date": "14-Sep-25"
  },
  {
    "league_id": "APTACHICAGO",
    "source_league": "APTACHICAGO",
    "match_id": "nndz-WWk2NnhycndnZz09_Line3",
    "url": "https://aptachicago.tenniscores.com/print_match.php?sch=nndz-WWk2NnhycndnZz09&print&",
    "Home Team": "Lake Forest 14",
    "Away Team": "Skokie 14",
    "Scores": "7-5, 0-6, 3-6",
    "Line": "Line 3",
    "Away Player 1": "Fritz Duda",
    "Away Player 2": "Tom Ahlering",
    "Away Player 1 ID": "nndz-WkNDd3lMbi9nQT09",
    "Away Player 2 ID": "nndz-WkNDNnhycjRqUT09",
    "Home Player 1": "Steve  Cervieri",
    "Home Player 2": "Glenn Heidbreder",
    "Home Player 1 ID": "nndz-WkMrK3hienhnQT09",
    "Home Player 2 ID": "nndz-WkNPd3g3L3hoZz09",
    "Winner": "home",
    "Date": "14-Sep-25"
  },
  {
    "league_id": "APTACHICAGO",
    "source_league": "APTACHICAGO",
    "match_id": "nndz-WWk2NnhycndnZz09_Line4",
    "url": "https://aptachicago.tenniscores.com/print_match.php?sch=nndz-WWk2NnhycndnZz09&print&",
    "Home Team": "Lake Forest 14",
    "Away Team": "Skokie 14",
    "Scores": "5-7, 6-1, 6-2",
    "Line": "Line 4",
    "Away Player 1": "Timothy Cwick",
    "Away Player 2": "Brandon Organ",
    "Away Player 1 ID": "nndz-WlNlN3lMcjRodz09",
    "Away Player 2 ID": "nndz-WkNDNnhyM3hqUT09",
    "Home Player 1": "Andrew Pfahl",
    "Home Player 2": "Chris DeLuca",
    "Home Player 1 ID": "nndz-WkNPd3liL3hnQT09",
    "Home Player 2 ID": "nndz-WkNPd3lMcjZnQT09",
    "Winner": "away",
    "Date": "14-Sep-25"
  },
  {
    "league_id": "APTACHICAGO",
    "source_league": "APTACHICAGO",
    "match_id": "nndz-WWk2NnhydjZnUT09_Line1",
    "url": "https://aptachicago.tenniscores.com/print_match.php?sch=nndz-WWk2NnhydjZnUT09&print&",
    "Home Team": "Westmoreland 14",
    "Away Team": "Evanston 14",
    "Scores": "4-6, 6-3, 6-4",
    "Line": "Line 1",
    "Away Player 1": "Hank Adams",
    "Away Player 2": "Chad Goven",
    "Away Player 1 ID": "nndz-WkM2NHhiajRnUT09",
    "Away Player 2 ID": "nndz-WkNDd3hyN3doUT09",
    "Home Player 1": "Matt Laughton",
    "Home Player 2": "Erik Scheier",
    "Home Player 1 ID": "nndz-WkNPd3g3bjloZz09",
    "Home Player 2 ID": "nndz-WkNPd3g3MytqUT09",
    "Winner": "away",
    "Date": "14-Sep-25"
  },
  {
    "league_id": "APTACHICAGO",
    "source_league": "APTACHICAGO",
    "match_id": "nndz-WWk2NnhydjZnUT09_Line2",
    "url": "https://aptachicago.tenniscores.com/print_match.php?sch=nndz-WWk2NnhydjZnUT09&print&",
    "Home Team": "Westmoreland 14",
    "Away Team": "Evanston 14",
    "Scores": "2-6, 2-6",
    "Line": "Line 2",
    "Away Player 1": "Mark Barbato",
    "Away Player 2": "Jeff Kremin",
    "Away Player 1 ID": "nndz-WkNDNnhyci9oZz09",
    "Away Player 2 ID": "nndz-WkNPd3libjlodz09",
    "Home Player 1": "Jay J Leonard",
    "Home Player 2": "Yale Dieckmann",
    "Home Player 1 ID": "nndz-WkNPd3g3M3hoZz09",
    "Home Player 2 ID": "nndz-WkNDNnhyZjVoUT09",
    "Winner": "home",
    "Date": "14-Sep-25"
  },
  {
    "league_id": "APTACHICAGO",
    "source_league": "APTACHICAGO",
    "match_id": "nndz-WWk2NnhydjZnUT09_Line3",
    "url": "https://aptachicago.tenniscores.com/print_match.php?sch=nndz-WWk2NnhydjZnUT09&print&",
    "Home Team": "Westmoreland 14",
    "Away Team": "Evanston 14",
    "Scores": "0-6, 5-7",
    "Line": "Line 3",
    "Away Player 1": "Dan Braasch",
    "Away Player 2": "Jeff Kremin",
    "Away Player 1 ID": "nndz-WkNDOXdMbjlqUT09",
    "Away Player 2 ID": "nndz-WkNPd3libjlodz09",
    "Home Player 1": "Cory Lester",
    "Home Player 2": "Cholly Smith",
    "Home Player 1 ID": "nndz-WkNHeHc3bitqUT09",
    "Home Player 2 ID": "nndz-WkNPd3hycitoZz09",
    "Winner": "home",
    "Date": "14-Sep-25"
  },
  {
    "league_id": "APTACHICAGO",
    "source_league": "APTACHICAGO",
    "match_id": "nndz-WWk2NnhydjZnUT09_Line4",
    "url": "https://aptachicago.tenniscores.com/print_match.php?sch=nndz-WWk2NnhydjZnUT09&print&",
    "Home Team": "Westmoreland 14",
    "Away Team": "Evanston 14",
    "Scores": "6-4, 7-6",
    "Line": "Line 4",
    "Away Player 1": "Tony DePalo",
    "Away Player 2": "Matt Smith",
    "Away Player 1 ID": "nndz-WkNHeHdiZi9nZz09",
    "Away Player 2 ID": "nndz-WkNHeHhyejRnZz09",
    "Home Player 1": "Tony Fata",
    "Home Player 2": "Dan Waters",
    "Home Player 1 ID": "nndz-WkNPd3hyLzRnQT09",
    "Home Player 2 ID": "nndz-WkNDOXdiajRnQT09",
    "Winner": "away",
    "Date": "14-Sep-25"
  },
  {
    "league_id": "APTACHICAGO",
    "source_league": "APTACHICAGO",
    "match_id": "nndz-WWk2NnhydjloZz09_Line2",
    "url": "https://aptachicago.tenniscores.com/print_match.php?sch=nndz-WWk2NnhydjloZz09&print&",
    "Home Team": "Winnetka I 14",
    "Away Team": "Winnetka II 14",
    "Scores": "2-6, 6-7",
    "Line": "Line 2",
    "Away Player 1": "Tom Chowaniac",
    "Away Player 2": "Bill Schumacher",
    "Away Player 1 ID": "nndz-WkNHNXhyeitoZz09",
    "Away Player 2 ID": "nndz-WkNDd3lMN3dqQT09",
    "Home Player 1": "Will Kim",
    "Home Player 2": "Joel Holland",
    "Home Player 1 ID": "nndz-WlNlNnhiMzhoUT09",
    "Home Player 2 ID": "nndz-WkM2L3dyejdnUT09",
    "Winner": "home",
    "Date": "14-Sep-25"
  },
  {
    "league_id": "APTACHICAGO",
    "source_league": "APTACHICAGO",
    "match_id": "nndz-WWk2NnhydjloZz09_Line4",
    "url": "https://aptachicago.tenniscores.com/print_match.php?sch=nndz-WWk2NnhydjloZz09&print&",
    "Home Team": "Winnetka I 14",
    "Away Team": "Winnetka II 14",
    "Scores": "6-2, 6-2",
    "Line": "Line 4",
    "Away Player 1": "Brad Birchmeier",
    "Away Player 2": "Glenn Pankau",
    "Away Player 1 ID": "nndz-WkNPd3hyZjZndz09",
    "Away Player 2 ID": "nndz-WkNPd3hyNytnUT09",
    "Home Player 1": "Rick Boerke",
    "Home Player 2": "Jim Obrien",
    "Home Player 1 ID": "nndz-WkNPd3g3Ny9nZz09",
    "Home Player 2 ID": "nndz-WkNPd3hMYitndz09",
    "Winner": "away",
    "Date": "14-Sep-25"
  },
  {
    "league_id": "APTACHICAGO",
    "source_league": "APTACHICAGO",
    "match_id": "nndz-WWk2NnhycndnQT09_Line1",
    "url": "https://aptachicago.tenniscores.com/print_match.php?sch=nndz-WWk2NnhycndnQT09&print&",
    "Home Team": "Lake Bluff 14",
    "Away Team": "Tennaqua 14",
    "Scores": "4-6, 2-6",
    "Line": "Line 1",
    "Away Player 1": "Stan Vajdic",
    "Away Player 2": "Mark Buranosky",
    "Away Player 1 ID": "nndz-WkNPd3g3djRqQT09",
    "Away Player 2 ID": "nndz-WkNPd3g3ZjVqQT09",
    "Home Player 1": "Randy Creighton",
    "Home Player 2": "Paul Stevens",
    "Home Player 1 ID": "nndz-WkNDNnhyMy9odz09",
    "Home Player 2 ID": "nndz-WkNPd3libitqUT09",
    "Winner": "home",
    "Date": "14-Sep-25"
  },
  {
    "league_id": "APTACHICAGO",
    "source_league": "APTACHICAGO",
    "match_id": "nndz-WWk2NnhycndnQT09_Line4",
    "url": "https://aptachicago.tenniscores.com/print_match.php?sch=nndz-WWk2NnhycndnQT09&print&",
    "Home Team": "Lake Bluff 14",
    "Away Team": "Tennaqua 14",
    "Scores": "6-4, 6-1",
    "Line": "Line 4",
    "Away Player 1": "Luke Vajdic",
    "Away Player 2": "Scott  Roler",
    "Away Player 1 ID": "nndz-WkNHeHdiZjRnUT09",
    "Away Player 2 ID": "nndz-WkM2L3c3djZodz09",
    "Home Player 1": "Tony Kriss",
    "Home Player 2": "Chris Serbin",
    "Home Player 1 ID": "nndz-WkNPd3hyLzlodz09",
    "Home Player 2 ID": "nndz-WkNPd3hyZjdnQT09",
    "Winner": "away",
    "Date": "14-Sep-25"
  },
  {
    "league_id": "APTACHICAGO",
    "source_league": "APTACHICAGO",
    "match_id": "nndz-WWk2Nnhycndndz09_Line1",
    "url": "https://aptachicago.tenniscores.com/print_match.php?sch=nndz-WWk2Nnhycndndz09&print&",
    "Home Team": "Lake Bluff 17",
    "Away Team": "Winnetka 17",
    "Scores": "5-7, 2-6",
    "Line": "Line 1",
    "Away Player 1": "Marc Gale",
    "Away Player 2": "Jesse Zuehl",
    "Away Player 1 ID": "nndz-WkNHd3diYi9odz09",
    "Away Player 2 ID": "nndz-WkMrK3diZjZqUT09",
    "Home Player 1": "Stephan Cobalt",
    "Home Player 2": "Sam Alper",
    "Home Player 1 ID": "nndz-WkMrK3dyM3hnQT09",
    "Home Player 2 ID": "nndz-WkNHeHdMai9oZz09",
    "Winner": "home",
    "Date": "17-Sep-25"
  },
  {
    "league_id": "APTACHICAGO",
    "source_league": "APTACHICAGO",
    "match_id": "nndz-WWk2Nnhycndndz09_Line2",
    "url": "https://aptachicago.tenniscores.com/print_match.php?sch=nndz-WWk2Nnhycndndz09&print&",
    "Home Team": "Lake Bluff 17",
    "Away Team": "Winnetka 17",
    "Scores": "7-6, 3-6, 6-2",
    "Line": "Line 2",
    "Away Player 1": "Larry  Schmit",
    "Away Player 2": "Dave Napier",
    "Away Player 1 ID": "nndz-WkM2L3hMdjZoUT09",
    "Away Player 2 ID": "nndz-WkNHd3diYi9nZz09",
    "Home Player 1": "Zack Stiltz",
    "Home Player 2": "Alex Ross",
    "Home Player 1 ID": "nndz-WkM2OHg3djdoQT09",
    "Home Player 2 ID": "nndz-WkNDNnlMYjZqQT09",
    "Winner": "away",
    "Date": "17-Sep-25"
  },
  {
    "league_id": "APTACHICAGO",
    "source_league": "APTACHICAGO",
    "match_id": "nndz-WWk2Nnhycndndz09_Line3",
    "url": "https://aptachicago.tenniscores.com/print_match.php?sch=nndz-WWk2Nnhycndndz09&print&",
    "Home Team": "Lake Bluff 17",
    "Away Team": "Winnetka 17",
    "Scores": "4-6, 6-4, 6-7",
    "Line": "Line 3",
    "Away Player 1": "Tom Collier",
    "Away Player 2": "Guillermo Trias",
    "Away Player 1 ID": "nndz-WkMreHdMejVoUT09",
    "Away Player 2 ID": "nndz-WkM2L3g3bjdnZz09",
    "Home Player 1": "Matt Valente",
    "Home Player 2": "Alex Gregor",
    "Home Player 1 ID": "nndz-WkNHeHdMaitnQT09",
    "Home Player 2 ID": "nndz-WkM2L3g3Nzlodz09",
    "Winner": "home",
    "Date": "17-Sep-25"
  },
  {
    "league_id": "APTACHICAGO",
    "source_league": "APTACHICAGO",
    "match_id": "nndz-WWk2Nnhycndndz09_Line4",
    "url": "https://aptachicago.tenniscores.com/print_match.php?sch=nndz-WWk2Nnhycndndz09&print&",
    "Home Team": "Lake Bluff 17",
    "Away Team": "Winnetka 17",
    "Scores": "5-7, 5-7",
    "Line": "Line 4",
    "Away Player 1": "Andrew Moen",
    "Away Player 2": "Patrick Parmentier",
    "Away Player 1 ID": "nndz-WkM2L3c3endndz09",
    "Away Player 2 ID": "nndz-WkNHd3diLy9qQT09",
    "Home Player 1": "David Lewicki",
    "Home Player 2": "Kevin Corcoran",
    "Home Player 1 ID": "nndz-WkNHeHdMZjRqUT09",
    "Home Player 2 ID": "nndz-WkM2OHlibndnQT09",
    "Winner": "home",
    "Date": "17-Sep-25"
  },
  {
    "league_id": "APTACHICAGO",
    "source_league": "APTACHICAGO",
    "match_id": "nndz-WWk2NnhydjZoQT09_Line1",
    "url": "https://aptachicago.tenniscores.com/print_match.php?sch=nndz-WWk2NnhydjZoQT09&print&",
    "Home Team": "Valley Lo 17",
    "Away Team": "Sunset Ridge 17",
    "Scores": "6-3, 2-6, 3-6",
    "Line": "Line 1",
    "Away Player 1": "Keith Beach",
    "Away Player 2": "Ben Cohen",
    "Away Player 1 ID": "nndz-WkNHNXdMejlndz09",
    "Away Player 2 ID": "nndz-WkM2L3hMdjRoUT09",
    "Home Player 1": "Noah Finkel",
    "Home Player 2": "Scott Nelson",
    "Home Player 1 ID": "nndz-WkNPd3hycjloQT09",
    "Home Player 2 ID": "nndz-WkNPd3g3MytoUT09",
    "Winner": "home",
    "Date": "17-Sep-25"
  },
  {
    "league_id": "APTACHICAGO",
    "source_league": "APTACHICAGO",
    "match_id": "nndz-WWk2NnhydjZoQT09_Line2",
    "url": "https://aptachicago.tenniscores.com/print_match.php?sch=nndz-WWk2NnhydjZoQT09&print&",
    "Home Team": "Valley Lo 17",
    "Away Team": "Sunset Ridge 17",
    "Scores": "6-7, 7-6, 6-3",
    "Line": "Line 2",
    "Away Player 1": "Blake  Overlock",
    "Away Player 2": "Kurt Sarbaugh",
    "Away Player 1 ID": "nndz-WkNPd3lMejdqUT09",
    "Away Player 2 ID": "nndz-WkNHNXdMejlqUT09",
    "Home Player 1": "Duane Garrett",
    "Home Player 2": "Tim Schulte",
    "Home Player 1 ID": "nndz-WkNPd3g3bjdqQT09",
    "Home Player 2 ID": "nndz-WkNPd3g3ZitnZz09",
    "Winner": "away",
    "Date": "17-Sep-25"
  },
  {
    "league_id": "APTACHICAGO",
    "source_league": "APTACHICAGO",
    "match_id": "nndz-WWk2NnhydjZoQT09_Line3",
    "url": "https://aptachicago.tenniscores.com/print_match.php?sch=nndz-WWk2NnhydjZoQT09&print&",
    "Home Team": "Valley Lo 17",
    "Away Team": "Sunset Ridge 17",
    "Scores": "1-6, 3-6",
    "Line": "Line 3",
    "Away Player 1": "Matthew L. Johnson",
    "Away Player 2": "Rod Nuyens",
    "Away Player 1 ID": "nndz-WkNDNnhyM3doZz09",
    "Away Player 2 ID": "nndz-WkNHNXdyZjVqQT09",
    "Home Player 1": "John Barrett",
    "Home Player 2": "Stefan Brabeck",
    "Home Player 1 ID": "nndz-WkM2L3hiMytnUT09",
    "Home Player 2 ID": "nndz-WkM2L3hiM3hqUT09",
    "Winner": "home",
    "Date": "17-Sep-25"
  },
  {
    "league_id": "APTACHICAGO",
    "source_league": "APTACHICAGO",
    "match_id": "nndz-WWk2NnhydjZoQT09_Line4",
    "url": "https://aptachicago.tenniscores.com/print_match.php?sch=nndz-WWk2NnhydjZoQT09&print&",
    "Home Team": "Valley Lo 17",
    "Away Team": "Sunset Ridge 17",
    "Scores": "6-1, 4-6, 1-6",
    "Line": "Line 4",
    "Away Player 1": "Rick Juneau",
    "Away Player 2": "Patrick Hughes",
    "Away Player 1 ID": "nndz-WkNPd3lMdjRnZz09",
    "Away Player 2 ID": "nndz-WkNPd3liYjhnQT09",
    "Home Player 1": "Brett Hendricks",
    "Home Player 2": "Alan League",
    "Home Player 1 ID": "nndz-WkNHeHdMYi9odz09",
    "Home Player 2 ID": "nndz-WkNPd3liZjVoQT09",
    "Winner": "home",
    "Date": "17-Sep-25"
  },
  {
    "league_id": "APTACHICAGO",
    "source_league": "APTACHICAGO",
    "match_id": "nndz-WWk2NnhydjRoZz09_Line1",
    "url": "https://aptachicago.tenniscores.com/print_match.php?sch=nndz-WWk2NnhydjRoZz09&print&",
    "Home Team": "Prairie Club I 17",
    "Away Team": "Prairie Club II 17",
    "Scores": "6-4, 6-1",
    "Line": "Line 1",
    "Away Player 1": "Kevin Casey",
    "Away Player 2": "Jeff Hyla",
    "Away Player 1 ID": "nndz-WkM2L3dyZjhoZz09",
    "Away Player 2 ID": "nndz-WkM2L3dyejhqQT09",
    "Home Player 1": "Bob Rosinski",
    "Home Player 2": "David Samuels",
    "Home Player 1 ID": "nndz-WkNPd3lMajdnQT09",
    "Home Player 2 ID": "nndz-WkNPd3lMN3hqQT09",
    "Winner": "away",
    "Date": "17-Sep-25"
  },
  {
    "league_id": "APTACHICAGO",
    "source_league": "APTACHICAGO",
    "match_id": "nndz-WWk2NnhydjRoZz09_Line3",
    "url": "https://aptachicago.tenniscores.com/print_match.php?sch=nndz-WWk2NnhydjRoZz09&print&",
    "Home Team": "Prairie Club I 17",
    "Away Team": "Prairie Club II 17",
    "Scores": "6-2, 6-2",
    "Line": "Line 3",
    "Away Player 1": "Matt Salmon",
    "Away Player 2": "Mitch Greenwald",
    "Away Player 1 ID": "nndz-WkM2L3dyeitoUT09",
    "Away Player 2 ID": "nndz-WkNHeHdMbjVnUT09",
    "Home Player 1": "Rick Fradin",
    "Home Player 2": "Brian Nourbash",
    "Home Player 1 ID": "nndz-WkNPd3lMejZnUT09",
    "Home Player 2 ID": "nndz-WkNPd3lMejZoUT09",
    "Winner": "away",
    "Date": "17-Sep-25"
  },
  {
    "league_id": "APTACHICAGO",
    "source_league": "APTACHICAGO",
    "match_id": "nndz-WWk2NnhydjRoZz09_Line4",
    "url": "https://aptachicago.tenniscores.com/print_match.php?sch=nndz-WWk2NnhydjRoZz09&print&",
    "Home Team": "Prairie Club I 17",
    "Away Team": "Prairie Club II 17",
    "Scores": "6-4, 6-4",
    "Line": "Line 4",
    "Away Player 1": "Vince Milito",
    "Away Player 2": "Tim Merrigan",
    "Away Player 1 ID": "nndz-WkNPd3liNzRoQT09",
    "Away Player 2 ID": "nndz-WkNPd3liejVoUT09",
    "Home Player 1": "Dan Polaneczky",
    "Home Player 2": "Richard Yoo",
    "Home Player 1 ID": "nndz-WkM2NXlMbjdodz09",
    "Home Player 2 ID": "nndz-WkNPd3liejlndz09",
    "Winner": "away",
    "Date": "17-Sep-25"
  },
  {
    "league_id": "APTACHICAGO",
    "source_league": "APTACHICAGO",
    "match_id": "nndz-WWk2NnhydjZqQT09_Line1",
    "url": "https://aptachicago.tenniscores.com/print_match.php?sch=nndz-WWk2NnhydjZqQT09&print&",
    "Home Team": "Wilmette PD I 11",
    "Away Team": "Wilmette PD II 11",
    "Scores": "6-3, 6-4",
    "Line": "Line 1",
    "Away Player 1": "Joaquin Saravia",
    "Away Player 2": "Nathan Shook",
    "Away Player 1 ID": "nndz-WlNlN3diajlnZz09",
    "Away Player 2 ID": "nndz-WkNHd3diejVoZz09",
    "Home Player 1": "Mark Rollings",
    "Home Player 2": "Brian  Langs",
    "Home Player 1 ID": "nndz-WkNHNXdidjRqQT09",
    "Home Player 2 ID": "nndz-WkNHNXc3ajlnUT09",
    "Winner": "away",
    "Date": "11-Sep-25"
  },
  {
    "league_id": "APTACHICAGO",
    "source_league": "APTACHICAGO",
    "match_id": "nndz-WWk2NnhydjZqQT09_Line2",
    "url": "https://aptachicago.tenniscores.com/print_match.php?sch=nndz-WWk2NnhydjZqQT09&print&",
    "Home Team": "Wilmette PD I 11",
    "Away Team": "Wilmette PD II 11",
    "Scores": "7-6, 6-3",
    "Line": "Line 2",
    "Away Player 1": "Jason Ethington",
    "Away Player 2": "Kyle Gemp",
    "Away Player 1 ID": "nndz-WkM2K3didjZqUT09",
    "Away Player 2 ID": "nndz-WkNDNnlMandndz09",
    "Home Player 1": "Nick Martin",
    "Home Player 2": "Tristan Farrell",
    "Home Player 1 ID": "nndz-WkNHNXdibi9ndz09",
    "Home Player 2 ID": "nndz-WkNPd3g3bjZqUT09",
    "Winner": "away",
    "Date": "11-Sep-25"
  },
  {
    "league_id": "APTACHICAGO",
    "source_league": "APTACHICAGO",
    "match_id": "nndz-WWk2NnhydjZqQT09_Line3",
    "url": "https://aptachicago.tenniscores.com/print_match.php?sch=nndz-WWk2NnhydjZqQT09&print&",
    "Home Team": "Wilmette PD I 11",
    "Away Team": "Wilmette PD II 11",
    "Scores": "6-4, 7-5",
    "Line": "Line 3",
    "Away Player 1": "Chris Kozak",
    "Away Player 2": "Chris Tag",
    "Away Player 1 ID": "nndz-WkNHd3diL3dnZz09",
    "Away Player 2 ID": "nndz-WkNHd3diLytnUT09",
    "Home Player 1": "Chris Rollings",
    "Home Player 2": "David Bailey",
    "Home Player 1 ID": "nndz-WkNPd3lMajlnQT09",
    "Home Player 2 ID": "nndz-WkNPd3g3N3hqUT09",
    "Winner": "away",
    "Date": "11-Sep-25"
  },
  {
    "league_id": "APTACHICAGO",
    "source_league": "APTACHICAGO",
    "match_id": "nndz-WWk2NnhydjZqQT09_Line4",
    "url": "https://aptachicago.tenniscores.com/print_match.php?sch=nndz-WWk2NnhydjZqQT09&print&",
    "Home Team": "Wilmette PD I 11",
    "Away Team": "Wilmette PD II 11",
    "Scores": "6-4, 7-5",
    "Line": "Line 4",
    "Away Player 1": "Brett Polivka",
    "Away Player 2": "Matt Nels",
    "Away Player 1 ID": "nndz-WkNPd3liai9nUT09",
    "Away Player 2 ID": "nndz-WkNPd3liL3hnUT09",
    "Home Player 1": "Mark McGuire",
    "Home Player 2": "Tim  Mulcrone",
    "Home Player 1 ID": "nndz-WkNDOXdiajVndz09",
    "Home Player 2 ID": "nndz-WkNHNXdiLzRnZz09",
    "Winner": "away",
    "Date": "11-Sep-25"
  },
  {
    "league_id": "APTACHICAGO",
    "source_league": "APTACHICAGO",
    "match_id": "nndz-WWk2NnhydjRodz09_Line1",
    "url": "https://aptachicago.tenniscores.com/print_match.php?sch=nndz-WWk2NnhydjRodz09&print&",
    "Home Team": "Prairie Club 11",
    "Away Team": "Valley Lo 11",
    "Scores": "3-6, 6-3, 6-0",
    "Line": "Line 1",
    "Away Player 1": "Steven Fass",
    "Away Player 2": "Connor Person",
    "Away Player 1 ID": "nndz-WkNPd3hMZjhoUT09",
    "Away Player 2 ID": "nndz-WkNPd3lMNzdqQT09",
    "Home Player 1": "Saumil Sheth",
    "Home Player 2": "Danny Caruso",
    "Home Player 1 ID": "nndz-WkNPd3hyLy9odz09",
    "Home Player 2 ID": "nndz-WkNHeHdiZjRqUT09",
    "Winner": "away",
    "Date": "11-Sep-25"
  },
  {
    "league_id": "APTACHICAGO",
    "source_league": "APTACHICAGO",
    "match_id": "nndz-WWk2NnhydjRodz09_Line2",
    "url": "https://aptachicago.tenniscores.com/print_match.php?sch=nndz-WWk2NnhydjRodz09&print&",
    "Home Team": "Prairie Club 11",
    "Away Team": "Valley Lo 11",
    "Scores": "7-6, 6-4",
    "Line": "Line 2",
    "Away Player 1": "Paul Bockwoldt",
    "Away Player 2": "Merek Aman",
    "Away Player 1 ID": "nndz-WkNDNnhyM3hoQT09",
    "Away Player 2 ID": "nndz-WkM2L3c3Yndndz09",
    "Home Player 1": "Max West",
    "Home Player 2": "Jim Laurie",
    "Home Player 1 ID": "nndz-WkNPd3g3YjdnZz09",
    "Home Player 2 ID": "nndz-WkNPd3g3Zjlndz09",
    "Winner": "away",
    "Date": "11-Sep-25"
  },
  {
    "league_id": "APTACHICAGO",
    "source_league": "APTACHICAGO",
    "match_id": "nndz-WWk2NnhydjRodz09_Line3",
    "url": "https://aptachicago.tenniscores.com/print_match.php?sch=nndz-WWk2NnhydjRodz09&print&",
    "Home Team": "Prairie Club 11",
    "Away Team": "Valley Lo 11",
    "Scores": "2-6, 3-6",
    "Line": "Line 3",
    "Away Player 1": "Greg Eshoo",
    "Away Player 2": "Jon Davidson",
    "Away Player 1 ID": "nndz-WkNPd3hMZjRoZz09",
    "Away Player 2 ID": "nndz-WkNPd3hMZi9oZz09",
    "Home Player 1": "Pete Walther",
    "Home Player 2": "Michael Moran",
    "Home Player 1 ID": "nndz-WkNPd3hyLy9oZz09",
    "Home Player 2 ID": "nndz-WkNPd3g3djdnUT09",
    "Winner": "home",
    "Date": "11-Sep-25"
  },
  {
    "league_id": "APTACHICAGO",
    "source_league": "APTACHICAGO",
    "match_id": "nndz-WWk2NnhydjRodz09_Line4",
    "url": "https://aptachicago.tenniscores.com/print_match.php?sch=nndz-WWk2NnhydjRodz09&print&",
    "Home Team": "Prairie Club 11",
    "Away Team": "Valley Lo 11",
    "Scores": "6-7, 7-6, 6-2",
    "Line": "Line 4",
    "Away Player 1": "Ernie Rogers",
    "Away Player 2": "greg rounds",
    "Away Player 1 ID": "nndz-WkNPd3g3M3dndz09",
    "Away Player 2 ID": "nndz-WkNPd3libnhnQT09",
    "Home Player 1": "Keith Bergeron",
    "Home Player 2": "Bernie Glavin",
    "Home Player 1 ID": "nndz-WkNPd3g3Zjhodz09",
    "Home Player 2 ID": "nndz-WkNPd3liLytnUT09",
    "Winner": "away",
    "Date": "11-Sep-25"
  },
  {
    "league_id": "APTACHICAGO",
    "source_league": "APTACHICAGO",
    "match_id": "nndz-WWk2NnhydjlnZz09_Line1",
    "url": "https://aptachicago.tenniscores.com/print_match.php?sch=nndz-WWk2NnhydjlnZz09&print&",
    "Home Team": "Winter Club 11",
    "Away Team": "Birchwood 11",
    "Scores": "3-6, 6-4, 4-6",
    "Line": "Line 1",
    "Away Player 1": "Greg Block",
    "Away Player 2": "Matt Nadell",
    "Away Player 1 ID": "nndz-WkNDNnhyYjlqUT09",
    "Away Player 2 ID": "nndz-WkM2L3hMcjhodz09",
    "Home Player 1": "Rick Florjancic",
    "Home Player 2": "David Winebrenner",
    "Home Player 1 ID": "nndz-WkNPd3hyLytqQT09",
    "Home Player 2 ID": "nndz-WkNPd3hyejhqUT09",
    "Winner": "home",
    "Date": "11-Sep-25"
  },
  {
    "league_id": "APTACHICAGO",
    "source_league": "APTACHICAGO",
    "match_id": "nndz-WWk2NnhydjlnZz09_Line2",
    "url": "https://aptachicago.tenniscores.com/print_match.php?sch=nndz-WWk2NnhydjlnZz09&print&",
    "Home Team": "Winter Club 11",
    "Away Team": "Birchwood 11",
    "Scores": "6-4, 6-4",
    "Line": "Line 2",
    "Away Player 1": "Tim Holbrook",
    "Away Player 2": "Vince LoGrande",
    "Away Player 1 ID": "nndz-WkNHeHhiditndz09",
    "Away Player 2 ID": "nndz-WkNPd3hMYjhnQT09",
    "Home Player 1": "Sock Woodruff",
    "Home Player 2": "Rob Peeler",
    "Home Player 1 ID": "nndz-WkNPd3liendndz09",
    "Home Player 2 ID": "nndz-WkNDNnlMajloUT09",
    "Winner": "away",
    "Date": "11-Sep-25"
  },
  {
    "league_id": "APTACHICAGO",
    "source_league": "APTACHICAGO",
    "match_id": "nndz-WWk2NnhydjlnZz09_Line3",
    "url": "https://aptachicago.tenniscores.com/print_match.php?sch=nndz-WWk2NnhydjlnZz09&print&",
    "Home Team": "Winter Club 11",
    "Away Team": "Birchwood 11",
    "Scores": "6-3, 6-4",
    "Line": "Line 3",
    "Away Player 1": "Benjamin Gottlieb",
    "Away Player 2": "Adam Markman",
    "Away Player 1 ID": "nndz-WkNHd3dyendqQT09",
    "Away Player 2 ID": "nndz-WkNHeHhidjhqQT09",
    "Home Player 1": "Sean Longworth",
    "Home Player 2": "Brad Moore",
    "Home Player 1 ID": "nndz-WkNPd3hyai9odz09",
    "Home Player 2 ID": "nndz-WkNPd3g3YjVndz09",
    "Winner": "away",
    "Date": "11-Sep-25"
  },
  {
    "league_id": "APTACHICAGO",
    "source_league": "APTACHICAGO",
    "match_id": "nndz-WWk2NnhydjlnZz09_Line4",
    "url": "https://aptachicago.tenniscores.com/print_match.php?sch=nndz-WWk2NnhydjlnZz09&print&",
    "Home Team": "Winter Club 11",
    "Away Team": "Birchwood 11",
    "Scores": "3-6, 1-6",
    "Line": "Line 4",
    "Away Player 1": "Gregg Falberg",
    "Away Player 2": "Steve Teufel",
    "Away Player 1 ID": "nndz-WkNPd3hMYjlqQT09",
    "Away Player 2 ID": "nndz-WkNHeHhidnhodz09",
    "Home Player 1": "Rob Davis",
    "Home Player 2": "Matthew Miclea",
    "Home Player 1 ID": "nndz-WkNPd3g3Ly9oZz09",
    "Home Player 2 ID": "nndz-WkMrK3dMZndqUT09",
    "Winner": "home",
    "Date": "11-Sep-25"
  }
]