[
  {
    "League": "APTA_CHICAGO",
    "Club": "Butterfield",
    "Series": "Series 19 SW",
    "Team": "Butterfield 19 SW",
    "Player ID": "nndz-WkNPd3lici9qQT09",
    "First Name": "Don",
    "Last Name": "Ensing",
    "PTI": "N/A",
    "Wins": "",
    "Losses": "0",
    "Win %": "0.0%",
    "Captain": "Yes",
    "Source URL": "https://aptachicago.tenniscores.com/?mod=nndz-TjJiOWtORzkwTlJFb0NVU1NzOD0%3D&team=nndz-WkNld3lMYng%3D",
    "source_league": "APTA_CHICAGO",
    "extraction_method": "team_roster",
    "team_context": "Butterfield 19 SW"
  },
  {
    "League": "APTA_CHICAGO",
    "Club": "Butterfield",
    "Series": "Series 19 SW",
    "Team": "Butterfield 19 SW",
    "Player ID": "nndz-WkNPd3hyaitndz09",
    "First Name": "Chris",
    "Last Name": "Nield",
    "PTI": "57.5",
    "Wins": "0",
    "Losses": "0",
    "Win %": "0.0%",
    "Captain": "No",
    "Source URL": "https://aptachicago.tenniscores.com/?mod=nndz-TjJiOWtORzkwTlJFb0NVU1NzOD0%3D&team=nndz-WkNld3lMYng%3D",
    "source_league": "APTA_CHICAGO",
    "extraction_method": "team_roster",
    "team_context": "Butterfield 19 SW"
  },
  {
    "League": "APTA_CHICAGO",
    "Club": "Butterfield",
    "Series": "Series 19 SW",
    "Team": "Butterfield 19 SW",
    "Player ID": "nndz-WkNDNnlMbjZnQT09",
    "First Name": "Jeff",
    "Last Name": "Bagull",
    "PTI": "N/A",
    "Wins": "0",
    "Losses": "0",
    "Win %": "0.0%",
    "Captain": "No",
    "Source URL": "https://aptachicago.tenniscores.com/?mod=nndz-TjJiOWtORzkwTlJFb0NVU1NzOD0%3D&team=nndz-WkNld3lMYng%3D",
    "source_league": "APTA_CHICAGO",
    "extraction_method": "team_roster",
    "team_context": "Butterfield 19 SW"
  },
  {
    "League": "APTA_CHICAGO",
    "Club": "Butterfield",
    "Series": "Series 19 SW",
    "Team": "Butterfield 19 SW",
    "Player ID": "nndz-WkNPd3g3ajdoUT09",
    "First Name": "John",
    "Last Name": "Coffey",
    "PTI": "N/A",
    "Wins": "0",
    "Losses": "0",
    "Win %": "0.0%",
    "Captain": "No",
    "Source URL": "https://aptachicago.tenniscores.com/?mod=nndz-TjJiOWtORzkwTlJFb0NVU1NzOD0%3D&team=nndz-WkNld3lMYng%3D",
    "source_league": "APTA_CHICAGO",
    "extraction_method": "team_roster",
    "team_context": "Butterfield 19 SW"
  },
  {
    "League": "APTA_CHICAGO",
    "Club": "Butterfield",
    "Series": "Series 19 SW",
    "Team": "Butterfield 19 SW",
    "Player ID": "nndz-WkNPd3hybjZoQT09",
    "First Name": "Don",
    "Last Name": "Draudt",
    "PTI": "N/A",
    "Wins": "0",
    "Losses": "0",
    "Win %": "0.0%",
    "Captain": "No",
    "Source URL": "https://aptachicago.tenniscores.com/?mod=nndz-TjJiOWtORzkwTlJFb0NVU1NzOD0%3D&team=nndz-WkNld3lMYng%3D",
    "source_league": "APTA_CHICAGO",
    "extraction_method": "team_roster",
    "team_context": "Butterfield 19 SW"
  },
  {
    "League": "APTA_CHICAGO",
    "Club": "Butterfield",
    "Series": "Series 19 SW",
    "Team": "Butterfield 19 SW",
    "Player ID": "nndz-WkM2NHhidjhqQT09",
    "First Name": "Dave",
    "Last Name": "Egan",
    "PTI": "N/A",
    "Wins": "0",
    "Losses": "0",
    "Win %": "0.0%",
    "Captain": "No",
    "Source URL": "https://aptachicago.tenniscores.com/?mod=nndz-TjJiOWtORzkwTlJFb0NVU1NzOD0%3D&team=nndz-WkNld3lMYng%3D",
    "source_league": "APTA_CHICAGO",
    "extraction_method": "team_roster",
    "team_context": "Butterfield 19 SW"
  },
  {
    "League": "APTA_CHICAGO",
    "Club": "Butterfield",
    "Series": "Series 19 SW",
    "Team": "Butterfield 19 SW",
    "Player ID": "nndz-WkNPd3hyMzlndz09",
    "First Name": "Rich",
    "Last Name": "Knitter",
    "PTI": "N/A",
    "Wins": "0",
    "Losses": "0",
    "Win %": "0.0%",
    "Captain": "No",
    "Source URL": "https://aptachicago.tenniscores.com/?mod=nndz-TjJiOWtORzkwTlJFb0NVU1NzOD0%3D&team=nndz-WkNld3lMYng%3D",
    "source_league": "APTA_CHICAGO",
    "extraction_method": "team_roster",
    "team_context": "Butterfield 19 SW"
  },
  {
    "League": "APTA_CHICAGO",
    "Club": "Butterfield",
    "Series": "Series 19 SW",
    "Team": "Butterfield 19 SW",
    "Player ID": "nndz-WkNPd3hyMytnZz09",
    "First Name": "Greg",
    "Last Name": "Kohut",
    "PTI": "N/A",
    "Wins": "0",
    "Losses": "0",
    "Win %": "0.0%",
    "Captain": "No",
    "Source URL": "https://aptachicago.tenniscores.com/?mod=nndz-TjJiOWtORzkwTlJFb0NVU1NzOD0%3D&team=nndz-WkNld3lMYng%3D",
    "source_league": "APTA_CHICAGO",
    "extraction_method": "team_roster",
    "team_context": "Butterfield 19 SW"
  },
  {
    "League": "APTA_CHICAGO",
    "Club": "Butterfield",
    "Series": "Series 19 SW",
    "Team": "Butterfield 19 SW",
    "Player ID": "nndz-WkNPd3liMy9nUT09",
    "First Name": "Ryan",
    "Last Name": "Kramer",
    "PTI": "N/A",
    "Wins": "0",
    "Losses": "0",
    "Win %": "0.0%",
    "Captain": "No",
    "Source URL": "https://aptachicago.tenniscores.com/?mod=nndz-TjJiOWtORzkwTlJFb0NVU1NzOD0%3D&team=nndz-WkNld3lMYng%3D",
    "source_league": "APTA_CHICAGO",
    "extraction_method": "team_roster",
    "team_context": "Butterfield 19 SW"
  },
  {
    "League": "APTA_CHICAGO",
    "Club": "Butterfield",
    "Series": "Series 19 SW",
    "Team": "Butterfield 19 SW",
    "Player ID": "nndz-WkNDd3hyM3dnUT09",
    "First Name": "Scott",
    "Last Name": "Marshall",
    "PTI": "N/A",
    "Wins": "0",
    "Losses": "0",
    "Win %": "0.0%",
    "Captain": "No",
    "Source URL": "https://aptachicago.tenniscores.com/?mod=nndz-TjJiOWtORzkwTlJFb0NVU1NzOD0%3D&team=nndz-WkNld3lMYng%3D",
    "source_league": "APTA_CHICAGO",
    "extraction_method": "team_roster",
    "team_context": "Butterfield 19 SW"
  },
  {
    "League": "APTA_CHICAGO",
    "Club": "Butterfield",
    "Series": "Series 19 SW",
    "Team": "Butterfield 19 SW",
    "Player ID": "nndz-WkNPd3hybjhndz09",
    "First Name": "Marc",
    "Last Name": "Poskin",
    "PTI": "N/A",
    "Wins": "0",
    "Losses": "0",
    "Win %": "0.0%",
    "Captain": "No",
    "Source URL": "https://aptachicago.tenniscores.com/?mod=nndz-TjJiOWtORzkwTlJFb0NVU1NzOD0%3D&team=nndz-WkNld3lMYng%3D",
    "source_league": "APTA_CHICAGO",
    "extraction_method": "team_roster",
    "team_context": "Butterfield 19 SW"
  },
  {
    "League": "APTA_CHICAGO",
    "Club": "Butterfield",
    "Series": "Series 19 SW",
    "Team": "Butterfield 19 SW",
    "Player ID": "nndz-WkNPd3hyei9odz09",
    "First Name": "Sean",
    "Last Name": "Reynolds",
    "PTI": "N/A",
    "Wins": "0",
    "Losses": "0",
    "Win %": "0.0%",
    "Captain": "No",
    "Source URL": "https://aptachicago.tenniscores.com/?mod=nndz-TjJiOWtORzkwTlJFb0NVU1NzOD0%3D&team=nndz-WkNld3lMYng%3D",
    "source_league": "APTA_CHICAGO",
    "extraction_method": "team_roster",
    "team_context": "Butterfield 19 SW"
  },
  {
    "League": "APTA_CHICAGO",
    "Club": "Butterfield",
    "Series": "Series 19 SW",
    "Team": "Butterfield 19 SW",
    "Player ID": "nndz-WkM2L3g3MzVnUT09",
    "First Name": "Michael",
    "Last Name": "Romano",
    "PTI": "N/A",
    "Wins": "0",
    "Losses": "0",
    "Win %": "0.0%",
    "Captain": "No",
    "Source URL": "https://aptachicago.tenniscores.com/?mod=nndz-TjJiOWtORzkwTlJFb0NVU1NzOD0%3D&team=nndz-WkNld3lMYng%3D",
    "source_league": "APTA_CHICAGO",
    "extraction_method": "team_roster",
    "team_context": "Butterfield 19 SW"
  },
  {
    "League": "APTA_CHICAGO",
    "Club": "Butterfield",
    "Series": "Series 19 SW",
    "Team": "Butterfield 19 SW",
    "Player ID": "nndz-WkNPd3hycjVodz09",
    "First Name": "Jeff",
    "Last Name": "Wilson",
    "PTI": "N/A",
    "Wins": "0",
    "Losses": "0",
    "Win %": "0.0%",
    "Captain": "No",
    "Source URL": "https://aptachicago.tenniscores.com/?mod=nndz-TjJiOWtORzkwTlJFb0NVU1NzOD0%3D&team=nndz-WkNld3lMYng%3D",
    "source_league": "APTA_CHICAGO",
    "extraction_method": "team_roster",
    "team_context": "Butterfield 19 SW"
  },
  {
    "League": "APTA_CHICAGO",
    "Club": "Chicago Highlands",
    "Series": "Series 19 SW",
    "Team": "Chicago Highlands 19 SW",
    "Player ID": "nndz-WkNPd3hyanhqUT09",
    "First Name": "Chris",
    "Last Name": "White",
    "PTI": "46.6",
    "Wins": "0",
    "Losses": "0",
    "Win %": "0.0%",
    "Captain": "Yes",
    "Source URL": "https://aptachicago.tenniscores.com/?mod=nndz-TjJiOWtORzkwTlJFb0NVU1NzOD0%3D&team=nndz-WkNld3lMYng%3D",
    "source_league": "APTA_CHICAGO",
    "extraction_method": "team_roster",
    "team_context": "Chicago Highlands 19 SW"
  },
  {
    "League": "APTA_CHICAGO",
    "Club": "Chicago Highlands",
    "Series": "Series 19 SW",
    "Team": "Chicago Highlands 19 SW",
    "Player ID": "nndz-WkNDNnlMbjRqUT09",
    "First Name": "Jay",
    "Last Name": "Lovelace",
    "PTI": "55.8",
    "Wins": "0",
    "Losses": "0",
    "Win %": "0.0%",
    "Captain": "No",
    "Source URL": "https://aptachicago.tenniscores.com/?mod=nndz-TjJiOWtORzkwTlJFb0NVU1NzOD0%3D&team=nndz-WkNld3lMYng%3D",
    "source_league": "APTA_CHICAGO",
    "extraction_method": "team_roster",
    "team_context": "Chicago Highlands 19 SW"
  },
  {
    "League": "APTA_CHICAGO",
    "Club": "Chicago Highlands",
    "Series": "Series 19 SW",
    "Team": "Chicago Highlands 19 SW",
    "Player ID": "nndz-WkNHNXc3bi9ndz09",
    "First Name": "Maju",
    "Last Name": "Abraham",
    "PTI": "N/A",
    "Wins": "0",
    "Losses": "0",
    "Win %": "0.0%",
    "Captain": "No",
    "Source URL": "https://aptachicago.tenniscores.com/?mod=nndz-TjJiOWtORzkwTlJFb0NVU1NzOD0%3D&team=nndz-WkNld3lMYng%3D",
    "source_league": "APTA_CHICAGO",
    "extraction_method": "team_roster",
    "team_context": "Chicago Highlands 19 SW"
  },
  {
    "League": "APTA_CHICAGO",
    "Club": "Chicago Highlands",
    "Series": "Series 19 SW",
    "Team": "Chicago Highlands 19 SW",
    "Player ID": "nndz-WkM2L3dyYjVnUT09",
    "First Name": "Michael",
    "Last Name": "Cordaro",
    "PTI": "62.7",
    "Wins": "0",
    "Losses": "0",
    "Win %": "0.0%",
    "Captain": "No",
    "Source URL": "https://aptachicago.tenniscores.com/?mod=nndz-TjJiOWtORzkwTlJFb0NVU1NzOD0%3D&team=nndz-WkNld3lMYng%3D",
    "source_league": "APTA_CHICAGO",
    "extraction_method": "team_roster",
    "team_context": "Chicago Highlands 19 SW"
  },
  {
    "League": "APTA_CHICAGO",
    "Club": "Chicago Highlands",
    "Series": "Series 19 SW",
    "Team": "Chicago Highlands 19 SW",
    "Player ID": "nndz-WkMrK3g3cjlnUT09",
    "First Name": "David",
    "Last Name": "Iantosca",
    "PTI": "49.1",
    "Wins": "0",
    "Losses": "0",
    "Win %": "0.0%",
    "Captain": "No",
    "Source URL": "https://aptachicago.tenniscores.com/?mod=nndz-TjJiOWtORzkwTlJFb0NVU1NzOD0%3D&team=nndz-WkNld3lMYng%3D",
    "source_league": "APTA_CHICAGO",
    "extraction_method": "team_roster",
    "team_context": "Chicago Highlands 19 SW"
  },
  {
    "League": "APTA_CHICAGO",
    "Club": "Chicago Highlands",
    "Series": "Series 19 SW",
    "Team": "Chicago Highlands 19 SW",
    "Player ID": "nndz-WkNPd3hybjlndz09",
    "First Name": "Anees",
    "Last Name": "Jaber",
    "PTI": "N/A",
    "Wins": "0",
    "Losses": "0",
    "Win %": "0.0%",
    "Captain": "No",
    "Source URL": "https://aptachicago.tenniscores.com/?mod=nndz-TjJiOWtORzkwTlJFb0NVU1NzOD0%3D&team=nndz-WkNld3lMYng%3D",
    "source_league": "APTA_CHICAGO",
    "extraction_method": "team_roster",
    "team_context": "Chicago Highlands 19 SW"
  },
  {
    "League": "APTA_CHICAGO",
    "Club": "Chicago Highlands",
    "Series": "Series 19 SW",
    "Team": "Chicago Highlands 19 SW",
    "Player ID": "nndz-WkNPd3lMLzlodz09",
    "First Name": "Joey",
    "Last Name": "Matos",
    "PTI": "53.4",
    "Wins": "0",
    "Losses": "0",
    "Win %": "0.0%",
    "Captain": "No",
    "Source URL": "https://aptachicago.tenniscores.com/?mod=nndz-TjJiOWtORzkwTlJFb0NVU1NzOD0%3D&team=nndz-WkNld3lMYng%3D",
    "source_league": "APTA_CHICAGO",
    "extraction_method": "team_roster",
    "team_context": "Chicago Highlands 19 SW"
  },
  {
    "League": "APTA_CHICAGO",
    "Club": "Chicago Highlands",
    "Series": "Series 19 SW",
    "Team": "Chicago Highlands 19 SW",
    "Player ID": "nndz-WkNPd3liLzZndz09",
    "First Name": "Darrell",
    "Last Name": "McConnell",
    "PTI": "N/A",
    "Wins": "0",
    "Losses": "0",
    "Win %": "0.0%",
    "Captain": "No",
    "Source URL": "https://aptachicago.tenniscores.com/?mod=nndz-TjJiOWtORzkwTlJFb0NVU1NzOD0%3D&team=nndz-WkNld3lMYng%3D",
    "source_league": "APTA_CHICAGO",
    "extraction_method": "team_roster",
    "team_context": "Chicago Highlands 19 SW"
  },
  {
    "League": "APTA_CHICAGO",
    "Club": "Chicago Highlands",
    "Series": "Series 19 SW",
    "Team": "Chicago Highlands 19 SW",
    "Player ID": "nndz-WkM2d3hMNzVnUT09",
    "First Name": "Blake",
    "Last Name": "Mueller",
    "PTI": "50.8",
    "Wins": "0",
    "Losses": "0",
    "Win %": "0.0%",
    "Captain": "No",
    "Source URL": "https://aptachicago.tenniscores.com/?mod=nndz-TjJiOWtORzkwTlJFb0NVU1NzOD0%3D&team=nndz-WkNld3lMYng%3D",
    "source_league": "APTA_CHICAGO",
    "extraction_method": "team_roster",
    "team_context": "Chicago Highlands 19 SW"
  },
  {
    "League": "APTA_CHICAGO",
    "Club": "Chicago Highlands",
    "Series": "Series 19 SW",
    "Team": "Chicago Highlands 19 SW",
    "Player ID": "nndz-WkNHd3g3N3dqUT09",
    "First Name": "Matt",
    "Last Name": "Nabavian",
    "PTI": "N/A",
    "Wins": "0",
    "Losses": "0",
    "Win %": "0.0%",
    "Captain": "No",
    "Source URL": "https://aptachicago.tenniscores.com/?mod=nndz-TjJiOWtORzkwTlJFb0NVU1NzOD0%3D&team=nndz-WkNld3lMYng%3D",
    "source_league": "APTA_CHICAGO",
    "extraction_method": "team_roster",
    "team_context": "Chicago Highlands 19 SW"
  },
  {
    "League": "APTA_CHICAGO",
    "Club": "Chicago Highlands",
    "Series": "Series 19 SW",
    "Team": "Chicago Highlands 19 SW",
    "Player ID": "nndz-WkNPd3hyanhndz09",
    "First Name": "Jamie",
    "Last Name": "Newcomer",
    "PTI": "N/A",
    "Wins": "0",
    "Losses": "0",
    "Win %": "0.0%",
    "Captain": "No",
    "Source URL": "https://aptachicago.tenniscores.com/?mod=nndz-TjJiOWtORzkwTlJFb0NVU1NzOD0%3D&team=nndz-WkNld3lMYng%3D",
    "source_league": "APTA_CHICAGO",
    "extraction_method": "team_roster",
    "team_context": "Chicago Highlands 19 SW"
  },
  {
    "League": "APTA_CHICAGO",
    "Club": "Chicago Highlands",
    "Series": "Series 19 SW",
    "Team": "Chicago Highlands 19 SW",
    "Player ID": "nndz-WkNPd3hybjlnZz09",
    "First Name": "Roger",
    "Last Name": "Veome",
    "PTI": "N/A",
    "Wins": "0",
    "Losses": "0",
    "Win %": "0.0%",
    "Captain": "No",
    "Source URL": "https://aptachicago.tenniscores.com/?mod=nndz-TjJiOWtORzkwTlJFb0NVU1NzOD0%3D&team=nndz-WkNld3lMYng%3D",
    "source_league": "APTA_CHICAGO",
    "extraction_method": "team_roster",
    "team_context": "Chicago Highlands 19 SW"
  },
  {
    "League": "APTA_CHICAGO",
    "Club": "Glen Ellyn",
    "Series": "Series 19 SW",
    "Team": "Glen Ellyn 19 SW",
    "Player ID": "nndz-WkNHeHdMdjVqQT09",
    "First Name": "Parag",
    "Last Name": "Thakkar",
    "PTI": "58.7",
    "Wins": "0",
    "Losses": "0",
    "Win %": "0.0%",
    "Captain": "Yes",
    "Source URL": "https://aptachicago.tenniscores.com/?mod=nndz-TjJiOWtORzkwTlJFb0NVU1NzOD0%3D&team=nndz-WkNld3lMYng%3D",
    "source_league": "APTA_CHICAGO",
    "extraction_method": "team_roster",
    "team_context": "Glen Ellyn 19 SW"
  },
  {
    "League": "APTA_CHICAGO",
    "Club": "Glen Ellyn",
    "Series": "Series 19 SW",
    "Team": "Glen Ellyn 19 SW",
    "Player ID": "nndz-WkM2L3dMbjloQT09",
    "First Name": "Neil",
    "Last Name": "Moscicki",
    "PTI": "54.2",
    "Wins": "0",
    "Losses": "0",
    "Win %": "0.0%",
    "Captain": "No",
    "Source URL": "https://aptachicago.tenniscores.com/?mod=nndz-TjJiOWtORzkwTlJFb0NVU1NzOD0%3D&team=nndz-WkNld3lMYng%3D",
    "source_league": "APTA_CHICAGO",
    "extraction_method": "team_roster",
    "team_context": "Glen Ellyn 19 SW"
  },
  {
    "League": "APTA_CHICAGO",
    "Club": "Glen Ellyn",
    "Series": "Series 19 SW",
    "Team": "Glen Ellyn 19 SW",
    "Player ID": "nndz-WkM2L3dMbjZnZz09",
    "First Name": "Jim",
    "Last Name": "Dewitt",
    "PTI": "N/A",
    "Wins": "0",
    "Losses": "0",
    "Win %": "0.0%",
    "Captain": "No",
    "Source URL": "https://aptachicago.tenniscores.com/?mod=nndz-TjJiOWtORzkwTlJFb0NVU1NzOD0%3D&team=nndz-WkNld3lMYng%3D",
    "source_league": "APTA_CHICAGO",
    "extraction_method": "team_roster",
    "team_context": "Glen Ellyn 19 SW"
  },
  {
    "League": "APTA_CHICAGO",
    "Club": "Glen Ellyn",
    "Series": "Series 19 SW",
    "Team": "Glen Ellyn 19 SW",
    "Player ID": "nndz-WkNHeHdMdjVndz09",
    "First Name": "Orian",
    "Last Name": "Galey",
    "PTI": "56.6",
    "Wins": "0",
    "Losses": "0",
    "Win %": "0.0%",
    "Captain": "No",
    "Source URL": "https://aptachicago.tenniscores.com/?mod=nndz-TjJiOWtORzkwTlJFb0NVU1NzOD0%3D&team=nndz-WkNld3lMYng%3D",
    "source_league": "APTA_CHICAGO",
    "extraction_method": "team_roster",
    "team_context": "Glen Ellyn 19 SW"
  },
  {
    "League": "APTA_CHICAGO",
    "Club": "Glen Ellyn",
    "Series": "Series 19 SW",
    "Team": "Glen Ellyn 19 SW",
    "Player ID": "nndz-WkNHeHdMcjdnQT09",
    "First Name": "Blake",
    "Last Name": "Johnson",
    "PTI": "57.1",
    "Wins": "0",
    "Losses": "0",
    "Win %": "0.0%",
    "Captain": "No",
    "Source URL": "https://aptachicago.tenniscores.com/?mod=nndz-TjJiOWtORzkwTlJFb0NVU1NzOD0%3D&team=nndz-WkNld3lMYng%3D",
    "source_league": "APTA_CHICAGO",
    "extraction_method": "team_roster",
    "team_context": "Glen Ellyn 19 SW"
  },
  {
    "League": "APTA_CHICAGO",
    "Club": "Glen Ellyn",
    "Series": "Series 19 SW",
    "Team": "Glen Ellyn 19 SW",
    "Player ID": "nndz-WkNHeHdMdjdoUT09",
    "First Name": "Vik",
    "Last Name": "Mehta",
    "PTI": "N/A",
    "Wins": "0",
    "Losses": "0",
    "Win %": "0.0%",
    "Captain": "No",
    "Source URL": "https://aptachicago.tenniscores.com/?mod=nndz-TjJiOWtORzkwTlJFb0NVU1NzOD0%3D&team=nndz-WkNld3lMYng%3D",
    "source_league": "APTA_CHICAGO",
    "extraction_method": "team_roster",
    "team_context": "Glen Ellyn 19 SW"
  },
  {
    "League": "APTA_CHICAGO",
    "Club": "Glen Ellyn",
    "Series": "Series 19 SW",
    "Team": "Glen Ellyn 19 SW",
    "Player ID": "nndz-WkNPd3licjVodz09",
    "First Name": "Karl",
    "Last Name": "Peter",
    "PTI": "44.1",
    "Wins": "0",
    "Losses": "0",
    "Win %": "0.0%",
    "Captain": "No",
    "Source URL": "https://aptachicago.tenniscores.com/?mod=nndz-TjJiOWtORzkwTlJFb0NVU1NzOD0%3D&team=nndz-WkNld3lMYng%3D",
    "source_league": "APTA_CHICAGO",
    "extraction_method": "team_roster",
    "team_context": "Glen Ellyn 19 SW"
  },
  {
    "League": "APTA_CHICAGO",
    "Club": "Glen Ellyn",
    "Series": "Series 19 SW",
    "Team": "Glen Ellyn 19 SW",
    "Player ID": "nndz-WkNPd3hybjZqUT09",
    "First Name": "Derek",
    "Last Name": "Peterson",
    "PTI": "57.0",
    "Wins": "0",
    "Losses": "0",
    "Win %": "0.0%",
    "Captain": "No",
    "Source URL": "https://aptachicago.tenniscores.com/?mod=nndz-TjJiOWtORzkwTlJFb0NVU1NzOD0%3D&team=nndz-WkNld3lMYng%3D",
    "source_league": "APTA_CHICAGO",
    "extraction_method": "team_roster",
    "team_context": "Glen Ellyn 19 SW"
  },
  {
    "League": "APTA_CHICAGO",
    "Club": "Glen Ellyn",
    "Series": "Series 19 SW",
    "Team": "Glen Ellyn 19 SW",
    "Player ID": "nndz-WkM2L3dMbjZoZz09",
    "First Name": "Bob",
    "Last Name": "Provax",
    "PTI": "47.7",
    "Wins": "0",
    "Losses": "0",
    "Win %": "0.0%",
    "Captain": "No",
    "Source URL": "https://aptachicago.tenniscores.com/?mod=nndz-TjJiOWtORzkwTlJFb0NVU1NzOD0%3D&team=nndz-WkNld3lMYng%3D",
    "source_league": "APTA_CHICAGO",
    "extraction_method": "team_roster",
    "team_context": "Glen Ellyn 19 SW"
  },
  {
    "League": "APTA_CHICAGO",
    "Club": "Glen Ellyn",
    "Series": "Series 19 SW",
    "Team": "Glen Ellyn 19 SW",
    "Player ID": "nndz-WkM2L3dMbjlndz09",
    "First Name": "Trevor",
    "Last Name": "Ryan",
    "PTI": "N/A",
    "Wins": "0",
    "Losses": "0",
    "Win %": "0.0%",
    "Captain": "No",
    "Source URL": "https://aptachicago.tenniscores.com/?mod=nndz-TjJiOWtORzkwTlJFb0NVU1NzOD0%3D&team=nndz-WkNld3lMYng%3D",
    "source_league": "APTA_CHICAGO",
    "extraction_method": "team_roster",
    "team_context": "Glen Ellyn 19 SW"
  },
  {
    "League": "APTA_CHICAGO",
    "Club": "Glen Ellyn",
    "Series": "Series 19 SW",
    "Team": "Glen Ellyn 19 SW",
    "Player ID": "nndz-WkM2L3dMbjZqUT09",
    "First Name": "JJ",
    "Last Name": "Smith",
    "PTI": "52.7",
    "Wins": "0",
    "Losses": "0",
    "Win %": "0.0%",
    "Captain": "No",
    "Source URL": "https://aptachicago.tenniscores.com/?mod=nndz-TjJiOWtORzkwTlJFb0NVU1NzOD0%3D&team=nndz-WkNld3lMYng%3D",
    "source_league": "APTA_CHICAGO",
    "extraction_method": "team_roster",
    "team_context": "Glen Ellyn 19 SW"
  },
  {
    "League": "APTA_CHICAGO",
    "Club": "Glen Ellyn",
    "Series": "Series 19 SW",
    "Team": "Glen Ellyn 19 SW",
    "Player ID": "nndz-WkNHeHdyL3hoQT09",
    "First Name": "Randy",
    "Last Name": "Vlach",
    "PTI": "53.4",
    "Wins": "0",
    "Losses": "0",
    "Win %": "0.0%",
    "Captain": "No",
    "Source URL": "https://aptachicago.tenniscores.com/?mod=nndz-TjJiOWtORzkwTlJFb0NVU1NzOD0%3D&team=nndz-WkNld3lMYng%3D",
    "source_league": "APTA_CHICAGO",
    "extraction_method": "team_roster",
    "team_context": "Glen Ellyn 19 SW"
  },
  {
    "League": "APTA_CHICAGO",
    "Club": "Glen Oak",
    "Series": "Series 19 SW",
    "Team": "Glen Oak 19 SW",
    "Player ID": "nndz-WkNPd3liLzVnQT09",
    "First Name": "Rishi",
    "Last Name": "Gauri",
    "PTI": "N/A",
    "Wins": "",
    "Losses": "0",
    "Win %": "0.0%",
    "Captain": "Yes",
    "Source URL": "https://aptachicago.tenniscores.com/?mod=nndz-TjJiOWtORzkwTlJFb0NVU1NzOD0%3D&team=nndz-WkNld3lMYng%3D",
    "source_league": "APTA_CHICAGO",
    "extraction_method": "team_roster",
    "team_context": "Glen Oak 19 SW"
  },
  {
    "League": "APTA_CHICAGO",
    "Club": "Glen Oak",
    "Series": "Series 19 SW",
    "Team": "Glen Oak 19 SW",
    "Player ID": "nndz-WkMrK3dyZjlqQT09",
    "First Name": "Ryan",
    "Last Name": "Anetsberger",
    "PTI": "N/A",
    "Wins": "0",
    "Losses": "0",
    "Win %": "0.0%",
    "Captain": "No",
    "Source URL": "https://aptachicago.tenniscores.com/?mod=nndz-TjJiOWtORzkwTlJFb0NVU1NzOD0%3D&team=nndz-WkNld3lMYng%3D",
    "source_league": "APTA_CHICAGO",
    "extraction_method": "team_roster",
    "team_context": "Glen Oak 19 SW"
  },
  {
    "League": "APTA_CHICAGO",
    "Club": "Glen Oak",
    "Series": "Series 19 SW",
    "Team": "Glen Oak 19 SW",
    "Player ID": "nndz-WlNlN3liMzlqQT09",
    "First Name": "Raj",
    "Last Name": "Basu",
    "PTI": "N/A",
    "Wins": "0",
    "Losses": "0",
    "Win %": "0.0%",
    "Captain": "No",
    "Source URL": "https://aptachicago.tenniscores.com/?mod=nndz-TjJiOWtORzkwTlJFb0NVU1NzOD0%3D&team=nndz-WkNld3lMYng%3D",
    "source_league": "APTA_CHICAGO",
    "extraction_method": "team_roster",
    "team_context": "Glen Oak 19 SW"
  },
  {
    "League": "APTA_CHICAGO",
    "Club": "Glen Oak",
    "Series": "Series 19 SW",
    "Team": "Glen Oak 19 SW",
    "Player ID": "nndz-WkM2L3dyajdnQT09",
    "First Name": "DJ",
    "Last Name": "Busch",
    "PTI": "N/A",
    "Wins": "0",
    "Losses": "0",
    "Win %": "0.0%",
    "Captain": "No",
    "Source URL": "https://aptachicago.tenniscores.com/?mod=nndz-TjJiOWtORzkwTlJFb0NVU1NzOD0%3D&team=nndz-WkNld3lMYng%3D",
    "source_league": "APTA_CHICAGO",
    "extraction_method": "team_roster",
    "team_context": "Glen Oak 19 SW"
  },
  {
    "League": "APTA_CHICAGO",
    "Club": "Glen Oak",
    "Series": "Series 19 SW",
    "Team": "Glen Oak 19 SW",
    "Player ID": "nndz-WkNPd3liNy9qQT09",
    "First Name": "Chris",
    "Last Name": "Camp",
    "PTI": "N/A",
    "Wins": "0",
    "Losses": "0",
    "Win %": "0.0%",
    "Captain": "No",
    "Source URL": "https://aptachicago.tenniscores.com/?mod=nndz-TjJiOWtORzkwTlJFb0NVU1NzOD0%3D&team=nndz-WkNld3lMYng%3D",
    "source_league": "APTA_CHICAGO",
    "extraction_method": "team_roster",
    "team_context": "Glen Oak 19 SW"
  },
  {
    "League": "APTA_CHICAGO",
    "Club": "Glen Oak",
    "Series": "Series 19 SW",
    "Team": "Glen Oak 19 SW",
    "Player ID": "nndz-WkM2L3dydndqUT09",
    "First Name": "John",
    "Last Name": "Frank",
    "PTI": "N/A",
    "Wins": "0",
    "Losses": "0",
    "Win %": "0.0%",
    "Captain": "No",
    "Source URL": "https://aptachicago.tenniscores.com/?mod=nndz-TjJiOWtORzkwTlJFb0NVU1NzOD0%3D&team=nndz-WkNld3lMYng%3D",
    "source_league": "APTA_CHICAGO",
    "extraction_method": "team_roster",
    "team_context": "Glen Oak 19 SW"
  },
  {
    "League": "APTA_CHICAGO",
    "Club": "Glen Oak",
    "Series": "Series 19 SW",
    "Team": "Glen Oak 19 SW",
    "Player ID": "nndz-WkNPd3liNy9qUT09",
    "First Name": "Steve",
    "Last Name": "Greanias",
    "PTI": "N/A",
    "Wins": "0",
    "Losses": "0",
    "Win %": "0.0%",
    "Captain": "No",
    "Source URL": "https://aptachicago.tenniscores.com/?mod=nndz-TjJiOWtORzkwTlJFb0NVU1NzOD0%3D&team=nndz-WkNld3lMYng%3D",
    "source_league": "APTA_CHICAGO",
    "extraction_method": "team_roster",
    "team_context": "Glen Oak 19 SW"
  },
  {
    "League": "APTA_CHICAGO",
    "Club": "Glen Oak",
    "Series": "Series 19 SW",
    "Team": "Glen Oak 19 SW",
    "Player ID": "nndz-WkNDd3lManhqQT09",
    "First Name": "Mike",
    "Last Name": "McNeive",
    "PTI": "N/A",
    "Wins": "0",
    "Losses": "0",
    "Win %": "0.0%",
    "Captain": "No",
    "Source URL": "https://aptachicago.tenniscores.com/?mod=nndz-TjJiOWtORzkwTlJFb0NVU1NzOD0%3D&team=nndz-WkNld3lMYng%3D",
    "source_league": "APTA_CHICAGO",
    "extraction_method": "team_roster",
    "team_context": "Glen Oak 19 SW"
  },
  {
    "League": "APTA_CHICAGO",
    "Club": "Glen Oak",
    "Series": "Series 19 SW",
    "Team": "Glen Oak 19 SW",
    "Player ID": "nndz-WkM2L3dydndndz09",
    "First Name": "David",
    "Last Name": "Powers",
    "PTI": "N/A",
    "Wins": "0",
    "Losses": "0",
    "Win %": "0.0%",
    "Captain": "No",
    "Source URL": "https://aptachicago.tenniscores.com/?mod=nndz-TjJiOWtORzkwTlJFb0NVU1NzOD0%3D&team=nndz-WkNld3lMYng%3D",
    "source_league": "APTA_CHICAGO",
    "extraction_method": "team_roster",
    "team_context": "Glen Oak 19 SW"
  },
  {
    "League": "APTA_CHICAGO",
    "Club": "Glen Oak",
    "Series": "Series 19 SW",
    "Team": "Glen Oak 19 SW",
    "Player ID": "nndz-WkNDd3lManhndz09",
    "First Name": "Joe",
    "Last Name": "Skarda",
    "PTI": "N/A",
    "Wins": "0",
    "Losses": "0",
    "Win %": "0.0%",
    "Captain": "No",
    "Source URL": "https://aptachicago.tenniscores.com/?mod=nndz-TjJiOWtORzkwTlJFb0NVU1NzOD0%3D&team=nndz-WkNld3lMYng%3D",
    "source_league": "APTA_CHICAGO",
    "extraction_method": "team_roster",
    "team_context": "Glen Oak 19 SW"
  },
  {
    "League": "APTA_CHICAGO",
    "Club": "Glen Oak",
    "Series": "Series 19 SW",
    "Team": "Glen Oak 19 SW",
    "Player ID": "nndz-WkNDd3lMandoQT09",
    "First Name": "Paul",
    "Last Name": "Skarr",
    "PTI": "N/A",
    "Wins": "0",
    "Losses": "0",
    "Win %": "0.0%",
    "Captain": "No",
    "Source URL": "https://aptachicago.tenniscores.com/?mod=nndz-TjJiOWtORzkwTlJFb0NVU1NzOD0%3D&team=nndz-WkNld3lMYng%3D",
    "source_league": "APTA_CHICAGO",
    "extraction_method": "team_roster",
    "team_context": "Glen Oak 19 SW"
  },
  {
    "League": "APTA_CHICAGO",
    "Club": "Glen Oak",
    "Series": "Series 19 SW",
    "Team": "Glen Oak 19 SW",
    "Player ID": "nndz-WkNDd3lManhnQT09",
    "First Name": "Jeff",
    "Last Name": "Swatzell",
    "PTI": "N/A",
    "Wins": "0",
    "Losses": "0",
    "Win %": "0.0%",
    "Captain": "No",
    "Source URL": "https://aptachicago.tenniscores.com/?mod=nndz-TjJiOWtORzkwTlJFb0NVU1NzOD0%3D&team=nndz-WkNld3lMYng%3D",
    "source_league": "APTA_CHICAGO",
    "extraction_method": "team_roster",
    "team_context": "Glen Oak 19 SW"
  },
  {
    "League": "APTA_CHICAGO",
    "Club": "Glen Oak",
    "Series": "Series 19 SW",
    "Team": "Glen Oak 19 SW",
    "Player ID": "nndz-WkM2eHlMcjlqQT09",
    "First Name": "Grant",
    "Last Name": "Terrell",
    "PTI": "N/A",
    "Wins": "0",
    "Losses": "0",
    "Win %": "0.0%",
    "Captain": "No",
    "Source URL": "https://aptachicago.tenniscores.com/?mod=nndz-TjJiOWtORzkwTlJFb0NVU1NzOD0%3D&team=nndz-WkNld3lMYng%3D",
    "source_league": "APTA_CHICAGO",
    "extraction_method": "team_roster",
    "team_context": "Glen Oak 19 SW"
  },
  {
    "League": "APTA_CHICAGO",
    "Club": "Glen Oak",
    "Series": "Series 19 SW",
    "Team": "Glen Oak 19 SW",
    "Player ID": "nndz-WkM2L3dyajRqQT09",
    "First Name": "Josh",
    "Last Name": "Weiss",
    "PTI": "N/A",
    "Wins": "0",
    "Losses": "0",
    "Win %": "0.0%",
    "Captain": "No",
    "Source URL": "https://aptachicago.tenniscores.com/?mod=nndz-TjJiOWtORzkwTlJFb0NVU1NzOD0%3D&team=nndz-WkNld3lMYng%3D",
    "source_league": "APTA_CHICAGO",
    "extraction_method": "team_roster",
    "team_context": "Glen Oak 19 SW"
  },
  {
    "League": "APTA_CHICAGO",
    "Club": "Hinsdale GC",
    "Series": "Series 19 SW",
    "Team": "Hinsdale GC 19 SW",
    "Player ID": "nndz-WkNPd3licjlnZz09",
    "First Name": "Sheldon",
    "Last Name": "Woldt",
    "PTI": "N/A",
    "Wins": "",
    "Losses": "0",
    "Win %": "0.0%",
    "Captain": "Yes",
    "Source URL": "https://aptachicago.tenniscores.com/?mod=nndz-TjJiOWtORzkwTlJFb0NVU1NzOD0%3D&team=nndz-WkNld3lMYng%3D",
    "source_league": "APTA_CHICAGO",
    "extraction_method": "team_roster",
    "team_context": "Hinsdale GC 19 SW"
  },
  {
    "League": "APTA_CHICAGO",
    "Club": "Hinsdale GC",
    "Series": "Series 19 SW",
    "Team": "Hinsdale GC 19 SW",
    "Player ID": "nndz-WkNHNXdybnhoUT09",
    "First Name": "Tom",
    "Last Name": "Besio",
    "PTI": "N/A",
    "Wins": "0",
    "Losses": "0",
    "Win %": "0.0%",
    "Captain": "No",
    "Source URL": "https://aptachicago.tenniscores.com/?mod=nndz-TjJiOWtORzkwTlJFb0NVU1NzOD0%3D&team=nndz-WkNld3lMYng%3D",
    "source_league": "APTA_CHICAGO",
    "extraction_method": "team_roster",
    "team_context": "Hinsdale GC 19 SW"
  },
  {
    "League": "APTA_CHICAGO",
    "Club": "Hinsdale GC",
    "Series": "Series 19 SW",
    "Team": "Hinsdale GC 19 SW",
    "Player ID": "nndz-WkNHd3dMbjhndz09",
    "First Name": "Jordan",
    "Last Name": "Cray",
    "PTI": "N/A",
    "Wins": "0",
    "Losses": "0",
    "Win %": "0.0%",
    "Captain": "No",
    "Source URL": "https://aptachicago.tenniscores.com/?mod=nndz-TjJiOWtORzkwTlJFb0NVU1NzOD0%3D&team=nndz-WkNld3lMYng%3D",
    "source_league": "APTA_CHICAGO",
    "extraction_method": "team_roster",
    "team_context": "Hinsdale GC 19 SW"
  },
  {
    "League": "APTA_CHICAGO",
    "Club": "Hinsdale GC",
    "Series": "Series 19 SW",
    "Team": "Hinsdale GC 19 SW",
    "Player ID": "nndz-WkNHNXdMLzhndz09",
    "First Name": "Christian",
    "Last Name": "Early",
    "PTI": "N/A",
    "Wins": "0",
    "Losses": "0",
    "Win %": "0.0%",
    "Captain": "No",
    "Source URL": "https://aptachicago.tenniscores.com/?mod=nndz-TjJiOWtORzkwTlJFb0NVU1NzOD0%3D&team=nndz-WkNld3lMYng%3D",
    "source_league": "APTA_CHICAGO",
    "extraction_method": "team_roster",
    "team_context": "Hinsdale GC 19 SW"
  },
  {
    "League": "APTA_CHICAGO",
    "Club": "Hinsdale GC",
    "Series": "Series 19 SW",
    "Team": "Hinsdale GC 19 SW",
    "Player ID": "nndz-WkNPd3lMLy9oQT09",
    "First Name": "Scott",
    "Last Name": "Elmore",
    "PTI": "N/A",
    "Wins": "0",
    "Losses": "0",
    "Win %": "0.0%",
    "Captain": "No",
    "Source URL": "https://aptachicago.tenniscores.com/?mod=nndz-TjJiOWtORzkwTlJFb0NVU1NzOD0%3D&team=nndz-WkNld3lMYng%3D",
    "source_league": "APTA_CHICAGO",
    "extraction_method": "team_roster",
    "team_context": "Hinsdale GC 19 SW"
  },
  {
    "League": "APTA_CHICAGO",
    "Club": "Hinsdale GC",
    "Series": "Series 19 SW",
    "Team": "Hinsdale GC 19 SW",
    "Player ID": "nndz-WkNHK3lMbitnUT09",
    "First Name": "Rob",
    "Last Name": "Fuller",
    "PTI": "N/A",
    "Wins": "0",
    "Losses": "0",
    "Win %": "0.0%",
    "Captain": "No",
    "Source URL": "https://aptachicago.tenniscores.com/?mod=nndz-TjJiOWtORzkwTlJFb0NVU1NzOD0%3D&team=nndz-WkNld3lMYng%3D",
    "source_league": "APTA_CHICAGO",
    "extraction_method": "team_roster",
    "team_context": "Hinsdale GC 19 SW"
  },
  {
    "League": "APTA_CHICAGO",
    "Club": "Hinsdale GC",
    "Series": "Series 19 SW",
    "Team": "Hinsdale GC 19 SW",
    "Player ID": "nndz-WkNPd3hybjdoZz09",
    "First Name": "Victor",
    "Last Name": "Galati",
    "PTI": "62.6",
    "Wins": "0",
    "Losses": "0",
    "Win %": "0.0%",
    "Captain": "No",
    "Source URL": "https://aptachicago.tenniscores.com/?mod=nndz-TjJiOWtORzkwTlJFb0NVU1NzOD0%3D&team=nndz-WkNld3lMYng%3D",
    "source_league": "APTA_CHICAGO",
    "extraction_method": "team_roster",
    "team_context": "Hinsdale GC 19 SW"
  },
  {
    "League": "APTA_CHICAGO",
    "Club": "Hinsdale GC",
    "Series": "Series 19 SW",
    "Team": "Hinsdale GC 19 SW",
    "Player ID": "nndz-WkNHK3lMZjVnZz09",
    "First Name": "John",
    "Last Name": "Goebel",
    "PTI": "N/A",
    "Wins": "0",
    "Losses": "0",
    "Win %": "0.0%",
    "Captain": "No",
    "Source URL": "https://aptachicago.tenniscores.com/?mod=nndz-TjJiOWtORzkwTlJFb0NVU1NzOD0%3D&team=nndz-WkNld3lMYng%3D",
    "source_league": "APTA_CHICAGO",
    "extraction_method": "team_roster",
    "team_context": "Hinsdale GC 19 SW"
  },
  {
    "League": "APTA_CHICAGO",
    "Club": "Hinsdale GC",
    "Series": "Series 19 SW",
    "Team": "Hinsdale GC 19 SW",
    "Player ID": "nndz-WkNHd3dycjhoQT09",
    "First Name": "Corey",
    "Last Name": "Simspson",
    "PTI": "N/A",
    "Wins": "0",
    "Losses": "0",
    "Win %": "0.0%",
    "Captain": "No",
    "Source URL": "https://aptachicago.tenniscores.com/?mod=nndz-TjJiOWtORzkwTlJFb0NVU1NzOD0%3D&team=nndz-WkNld3lMYng%3D",
    "source_league": "APTA_CHICAGO",
    "extraction_method": "team_roster",
    "team_context": "Hinsdale GC 19 SW"
  },
  {
    "League": "APTA_CHICAGO",
    "Club": "Hinsdale GC",
    "Series": "Series 19 SW",
    "Team": "Hinsdale GC 19 SW",
    "Player ID": "nndz-WkM2NHdyZjVoUT09",
    "First Name": "Bryant",
    "Last Name": "Steele",
    "PTI": "N/A",
    "Wins": "0",
    "Losses": "0",
    "Win %": "0.0%",
    "Captain": "No",
    "Source URL": "https://aptachicago.tenniscores.com/?mod=nndz-TjJiOWtORzkwTlJFb0NVU1NzOD0%3D&team=nndz-WkNld3lMYng%3D",
    "source_league": "APTA_CHICAGO",
    "extraction_method": "team_roster",
    "team_context": "Hinsdale GC 19 SW"
  },
  {
    "League": "APTA_CHICAGO",
    "Club": "Hinsdale GC",
    "Series": "Series 19 SW",
    "Team": "Hinsdale GC 19 SW",
    "Player ID": "nndz-WkNHd3dMbjhnZz09",
    "First Name": "Matt",
    "Last Name": "Tuthill",
    "PTI": "N/A",
    "Wins": "0",
    "Losses": "0",
    "Win %": "0.0%",
    "Captain": "No",
    "Source URL": "https://aptachicago.tenniscores.com/?mod=nndz-TjJiOWtORzkwTlJFb0NVU1NzOD0%3D&team=nndz-WkNld3lMYng%3D",
    "source_league": "APTA_CHICAGO",
    "extraction_method": "team_roster",
    "team_context": "Hinsdale GC 19 SW"
  },
  {
    "League": "APTA_CHICAGO",
    "Club": "Hinsdale GC",
    "Series": "Series 19 SW",
    "Team": "Hinsdale GC 19 SW",
    "Player ID": "nndz-WkNPd3licjhoUT09",
    "First Name": "Jason",
    "Last Name": "VanZant",
    "PTI": "N/A",
    "Wins": "0",
    "Losses": "0",
    "Win %": "0.0%",
    "Captain": "No",
    "Source URL": "https://aptachicago.tenniscores.com/?mod=nndz-TjJiOWtORzkwTlJFb0NVU1NzOD0%3D&team=nndz-WkNld3lMYng%3D",
    "source_league": "APTA_CHICAGO",
    "extraction_method": "team_roster",
    "team_context": "Hinsdale GC 19 SW"
  },
  {
    "League": "APTA_CHICAGO",
    "Club": "Hinsdale PC",
    "Series": "Series 19 SW",
    "Team": "Hinsdale PC 19 SW",
    "Player ID": "nndz-WkNHeHhMdi9ndz09",
    "First Name": "Joe",
    "Last Name": "Kelly",
    "PTI": "51.2",
    "Wins": "0",
    "Losses": "0",
    "Win %": "0.0%",
    "Captain": "Yes",
    "Source URL": "https://aptachicago.tenniscores.com/?mod=nndz-TjJiOWtORzkwTlJFb0NVU1NzOD0%3D&team=nndz-WkNld3lMYng%3D",
    "source_league": "APTA_CHICAGO",
    "extraction_method": "team_roster",
    "team_context": "Hinsdale PC 19 SW"
  },
  {
    "League": "APTA_CHICAGO",
    "Club": "Hinsdale PC",
    "Series": "Series 19 SW",
    "Team": "Hinsdale PC 19 SW",
    "Player ID": "nndz-WkNDd3lMajlodz09",
    "First Name": "Kevin",
    "Last Name": "Backus",
    "PTI": "46.2",
    "Wins": "0",
    "Losses": "0",
    "Win %": "0.0%",
    "Captain": "No",
    "Source URL": "https://aptachicago.tenniscores.com/?mod=nndz-TjJiOWtORzkwTlJFb0NVU1NzOD0%3D&team=nndz-WkNld3lMYng%3D",
    "source_league": "APTA_CHICAGO",
    "extraction_method": "team_roster",
    "team_context": "Hinsdale PC 19 SW"
  },
  {
    "League": "APTA_CHICAGO",
    "Club": "Hinsdale PC",
    "Series": "Series 19 SW",
    "Team": "Hinsdale PC 19 SW",
    "Player ID": "nndz-WkNPd3liN3hnZz09",
    "First Name": "Todd",
    "Last Name": "Bucciarelli",
    "PTI": "N/A",
    "Wins": "0",
    "Losses": "0",
    "Win %": "0.0%",
    "Captain": "No",
    "Source URL": "https://aptachicago.tenniscores.com/?mod=nndz-TjJiOWtORzkwTlJFb0NVU1NzOD0%3D&team=nndz-WkNld3lMYng%3D",
    "source_league": "APTA_CHICAGO",
    "extraction_method": "team_roster",
    "team_context": "Hinsdale PC 19 SW"
  },
  {
    "League": "APTA_CHICAGO",
    "Club": "Hinsdale PC",
    "Series": "Series 19 SW",
    "Team": "Hinsdale PC 19 SW",
    "Player ID": "nndz-WkNPd3liMy9nZz09",
    "First Name": "Jim",
    "Last Name": "Cochonour",
    "PTI": "N/A",
    "Wins": "0",
    "Losses": "0",
    "Win %": "0.0%",
    "Captain": "No",
    "Source URL": "https://aptachicago.tenniscores.com/?mod=nndz-TjJiOWtORzkwTlJFb0NVU1NzOD0%3D&team=nndz-WkNld3lMYng%3D",
    "source_league": "APTA_CHICAGO",
    "extraction_method": "team_roster",
    "team_context": "Hinsdale PC 19 SW"
  },
  {
    "League": "APTA_CHICAGO",
    "Club": "Hinsdale PC",
    "Series": "Series 19 SW",
    "Team": "Hinsdale PC 19 SW",
    "Player ID": "nndz-WkNPd3liNytnZz09",
    "First Name": "Brian",
    "Last Name": "Driscoll",
    "PTI": "N/A",
    "Wins": "0",
    "Losses": "0",
    "Win %": "0.0%",
    "Captain": "No",
    "Source URL": "https://aptachicago.tenniscores.com/?mod=nndz-TjJiOWtORzkwTlJFb0NVU1NzOD0%3D&team=nndz-WkNld3lMYng%3D",
    "source_league": "APTA_CHICAGO",
    "extraction_method": "team_roster",
    "team_context": "Hinsdale PC 19 SW"
  },
  {
    "League": "APTA_CHICAGO",
    "Club": "Hinsdale PC",
    "Series": "Series 19 SW",
    "Team": "Hinsdale PC 19 SW",
    "Player ID": "nndz-WkMrK3dMYjlodz09",
    "First Name": "Josh",
    "Last Name": "Dunn",
    "PTI": "N/A",
    "Wins": "0",
    "Losses": "0",
    "Win %": "0.0%",
    "Captain": "No",
    "Source URL": "https://aptachicago.tenniscores.com/?mod=nndz-TjJiOWtORzkwTlJFb0NVU1NzOD0%3D&team=nndz-WkNld3lMYng%3D",
    "source_league": "APTA_CHICAGO",
    "extraction_method": "team_roster",
    "team_context": "Hinsdale PC 19 SW"
  },
  {
    "League": "APTA_CHICAGO",
    "Club": "Hinsdale PC",
    "Series": "Series 19 SW",
    "Team": "Hinsdale PC 19 SW",
    "Player ID": "nndz-WkNPd3hMZnhoQT09",
    "First Name": "Phil",
    "Last Name": "Lorenz",
    "PTI": "N/A",
    "Wins": "0",
    "Losses": "0",
    "Win %": "0.0%",
    "Captain": "No",
    "Source URL": "https://aptachicago.tenniscores.com/?mod=nndz-TjJiOWtORzkwTlJFb0NVU1NzOD0%3D&team=nndz-WkNld3lMYng%3D",
    "source_league": "APTA_CHICAGO",
    "extraction_method": "team_roster",
    "team_context": "Hinsdale PC 19 SW"
  },
  {
    "League": "APTA_CHICAGO",
    "Club": "Hinsdale PC",
    "Series": "Series 19 SW",
    "Team": "Hinsdale PC 19 SW",
    "Player ID": "nndz-WkNPd3lMNzdqUT09",
    "First Name": "Tim",
    "Last Name": "Person",
    "PTI": "N/A",
    "Wins": "0",
    "Losses": "0",
    "Win %": "0.0%",
    "Captain": "No",
    "Source URL": "https://aptachicago.tenniscores.com/?mod=nndz-TjJiOWtORzkwTlJFb0NVU1NzOD0%3D&team=nndz-WkNld3lMYng%3D",
    "source_league": "APTA_CHICAGO",
    "extraction_method": "team_roster",
    "team_context": "Hinsdale PC 19 SW"
  },
  {
    "League": "APTA_CHICAGO",
    "Club": "Hinsdale PC",
    "Series": "Series 19 SW",
    "Team": "Hinsdale PC 19 SW",
    "Player ID": "nndz-WkNPd3hyMy9nZz09",
    "First Name": "Kevin",
    "Last Name": "Rogers",
    "PTI": "N/A",
    "Wins": "0",
    "Losses": "0",
    "Win %": "0.0%",
    "Captain": "No",
    "Source URL": "https://aptachicago.tenniscores.com/?mod=nndz-TjJiOWtORzkwTlJFb0NVU1NzOD0%3D&team=nndz-WkNld3lMYng%3D",
    "source_league": "APTA_CHICAGO",
    "extraction_method": "team_roster",
    "team_context": "Hinsdale PC 19 SW"
  },
  {
    "League": "APTA_CHICAGO",
    "Club": "Hinsdale PC",
    "Series": "Series 19 SW",
    "Team": "Hinsdale PC 19 SW",
    "Player ID": "nndz-WkNHeHg3ajRqUT09",
    "First Name": "Chris",
    "Last Name": "Sioukas",
    "PTI": "N/A",
    "Wins": "0",
    "Losses": "0",
    "Win %": "0.0%",
    "Captain": "No",
    "Source URL": "https://aptachicago.tenniscores.com/?mod=nndz-TjJiOWtORzkwTlJFb0NVU1NzOD0%3D&team=nndz-WkNld3lMYng%3D",
    "source_league": "APTA_CHICAGO",
    "extraction_method": "team_roster",
    "team_context": "Hinsdale PC 19 SW"
  },
  {
    "League": "APTA_CHICAGO",
    "Club": "Hinsdale PC",
    "Series": "Series 19 SW",
    "Team": "Hinsdale PC 19 SW",
    "Player ID": "nndz-WkNPd3hybjVnQT09",
    "First Name": "Mark",
    "Last Name": "Staelgraeve",
    "PTI": "N/A",
    "Wins": "0",
    "Losses": "0",
    "Win %": "0.0%",
    "Captain": "No",
    "Source URL": "https://aptachicago.tenniscores.com/?mod=nndz-TjJiOWtORzkwTlJFb0NVU1NzOD0%3D&team=nndz-WkNld3lMYng%3D",
    "source_league": "APTA_CHICAGO",
    "extraction_method": "team_roster",
    "team_context": "Hinsdale PC 19 SW"
  },
  {
    "League": "APTA_CHICAGO",
    "Club": "LaGrange CC",
    "Series": "Series 19 SW",
    "Team": "LaGrange CC 19 SW",
    "Player ID": "nndz-WkNDNnhyYitnUT09",
    "First Name": "Mike",
    "Last Name": "Obloy",
    "PTI": "N/A",
    "Wins": "",
    "Losses": "0",
    "Win %": "0.0%",
    "Captain": "Yes",
    "Source URL": "https://aptachicago.tenniscores.com/?mod=nndz-TjJiOWtORzkwTlJFb0NVU1NzOD0%3D&team=nndz-WkNld3lMYng%3D",
    "source_league": "APTA_CHICAGO",
    "extraction_method": "team_roster",
    "team_context": "LaGrange CC 19 SW"
  },
  {
    "League": "APTA_CHICAGO",
    "Club": "LaGrange CC",
    "Series": "Series 19 SW",
    "Team": "LaGrange CC 19 SW",
    "Player ID": "nndz-WkNHNXc3bjVndz09",
    "First Name": "Steve",
    "Last Name": "Fleischmann",
    "PTI": "N/A",
    "Wins": "0",
    "Losses": "0",
    "Win %": "0.0%",
    "Captain": "No",
    "Source URL": "https://aptachicago.tenniscores.com/?mod=nndz-TjJiOWtORzkwTlJFb0NVU1NzOD0%3D&team=nndz-WkNld3lMYng%3D",
    "source_league": "APTA_CHICAGO",
    "extraction_method": "team_roster",
    "team_context": "LaGrange CC 19 SW"
  },
  {
    "League": "APTA_CHICAGO",
    "Club": "LaGrange CC",
    "Series": "Series 19 SW",
    "Team": "LaGrange CC 19 SW",
    "Player ID": "nndz-WkNDNnhyYitndz09",
    "First Name": "Luke",
    "Last Name": "Bagato",
    "PTI": "53.2",
    "Wins": "0",
    "Losses": "0",
    "Win %": "0.0%",
    "Captain": "No",
    "Source URL": "https://aptachicago.tenniscores.com/?mod=nndz-TjJiOWtORzkwTlJFb0NVU1NzOD0%3D&team=nndz-WkNld3lMYng%3D",
    "source_league": "APTA_CHICAGO",
    "extraction_method": "team_roster",
    "team_context": "LaGrange CC 19 SW"
  },
  {
    "League": "APTA_CHICAGO",
    "Club": "LaGrange CC",
    "Series": "Series 19 SW",
    "Team": "LaGrange CC 19 SW",
    "Player ID": "nndz-WkNDNnhyYitoZz09",
    "First Name": "Tom",
    "Last Name": "Biwan",
    "PTI": "62.2",
    "Wins": "0",
    "Losses": "0",
    "Win %": "0.0%",
    "Captain": "No",
    "Source URL": "https://aptachicago.tenniscores.com/?mod=nndz-TjJiOWtORzkwTlJFb0NVU1NzOD0%3D&team=nndz-WkNld3lMYng%3D",
    "source_league": "APTA_CHICAGO",
    "extraction_method": "team_roster",
    "team_context": "LaGrange CC 19 SW"
  },
  {
    "League": "APTA_CHICAGO",
    "Club": "LaGrange CC",
    "Series": "Series 19 SW",
    "Team": "LaGrange CC 19 SW",
    "Player ID": "nndz-WkNPd3lMLzRqUT09",
    "First Name": "Dan",
    "Last Name": "Crowe",
    "PTI": "N/A",
    "Wins": "0",
    "Losses": "0",
    "Win %": "0.0%",
    "Captain": "No",
    "Source URL": "https://aptachicago.tenniscores.com/?mod=nndz-TjJiOWtORzkwTlJFb0NVU1NzOD0%3D&team=nndz-WkNld3lMYng%3D",
    "source_league": "APTA_CHICAGO",
    "extraction_method": "team_roster",
    "team_context": "LaGrange CC 19 SW"
  },
  {
    "League": "APTA_CHICAGO",
    "Club": "LaGrange CC",
    "Series": "Series 19 SW",
    "Team": "LaGrange CC 19 SW",
    "Player ID": "nndz-WkNHeHhMYjdoZz09",
    "First Name": "Tom",
    "Last Name": "Gallant",
    "PTI": "N/A",
    "Wins": "0",
    "Losses": "0",
    "Win %": "0.0%",
    "Captain": "No",
    "Source URL": "https://aptachicago.tenniscores.com/?mod=nndz-TjJiOWtORzkwTlJFb0NVU1NzOD0%3D&team=nndz-WkNld3lMYng%3D",
    "source_league": "APTA_CHICAGO",
    "extraction_method": "team_roster",
    "team_context": "LaGrange CC 19 SW"
  },
  {
    "League": "APTA_CHICAGO",
    "Club": "LaGrange CC",
    "Series": "Series 19 SW",
    "Team": "LaGrange CC 19 SW",
    "Player ID": "nndz-WkNPd3liLzloZz09",
    "First Name": "Bill",
    "Last Name": "Hajiharis",
    "PTI": "N/A",
    "Wins": "0",
    "Losses": "0",
    "Win %": "0.0%",
    "Captain": "No",
    "Source URL": "https://aptachicago.tenniscores.com/?mod=nndz-TjJiOWtORzkwTlJFb0NVU1NzOD0%3D&team=nndz-WkNld3lMYng%3D",
    "source_league": "APTA_CHICAGO",
    "extraction_method": "team_roster",
    "team_context": "LaGrange CC 19 SW"
  },
  {
    "League": "APTA_CHICAGO",
    "Club": "LaGrange CC",
    "Series": "Series 19 SW",
    "Team": "LaGrange CC 19 SW",
    "Player ID": "nndz-WkNPd3lMLzdodz09",
    "First Name": "Jim",
    "Last Name": "Kelly",
    "PTI": "65.5",
    "Wins": "0",
    "Losses": "0",
    "Win %": "0.0%",
    "Captain": "No",
    "Source URL": "https://aptachicago.tenniscores.com/?mod=nndz-TjJiOWtORzkwTlJFb0NVU1NzOD0%3D&team=nndz-WkNld3lMYng%3D",
    "source_league": "APTA_CHICAGO",
    "extraction_method": "team_roster",
    "team_context": "LaGrange CC 19 SW"
  },
  {
    "League": "APTA_CHICAGO",
    "Club": "LaGrange CC",
    "Series": "Series 19 SW",
    "Team": "LaGrange CC 19 SW",
    "Player ID": "nndz-WkNPd3liLzZoZz09",
    "First Name": "Ryan",
    "Last Name": "Murphy",
    "PTI": "57.9",
    "Wins": "0",
    "Losses": "0",
    "Win %": "0.0%",
    "Captain": "No",
    "Source URL": "https://aptachicago.tenniscores.com/?mod=nndz-TjJiOWtORzkwTlJFb0NVU1NzOD0%3D&team=nndz-WkNld3lMYng%3D",
    "source_league": "APTA_CHICAGO",
    "extraction_method": "team_roster",
    "team_context": "LaGrange CC 19 SW"
  },
  {
    "League": "APTA_CHICAGO",
    "Club": "LaGrange CC",
    "Series": "Series 19 SW",
    "Team": "LaGrange CC 19 SW",
    "Player ID": "nndz-WkM2L3lMcitqUT09",
    "First Name": "Kurt",
    "Last Name": "Reichenbach",
    "PTI": "N/A",
    "Wins": "0",
    "Losses": "0",
    "Win %": "0.0%",
    "Captain": "No",
    "Source URL": "https://aptachicago.tenniscores.com/?mod=nndz-TjJiOWtORzkwTlJFb0NVU1NzOD0%3D&team=nndz-WkNld3lMYng%3D",
    "source_league": "APTA_CHICAGO",
    "extraction_method": "team_roster",
    "team_context": "LaGrange CC 19 SW"
  },
  {
    "League": "APTA_CHICAGO",
    "Club": "LaGrange CC",
    "Series": "Series 19 SW",
    "Team": "LaGrange CC 19 SW",
    "Player ID": "nndz-WkNPd3liLzZoUT09",
    "First Name": "Charles",
    "Last Name": "Straface",
    "PTI": "60.6",
    "Wins": "0",
    "Losses": "0",
    "Win %": "0.0%",
    "Captain": "No",
    "Source URL": "https://aptachicago.tenniscores.com/?mod=nndz-TjJiOWtORzkwTlJFb0NVU1NzOD0%3D&team=nndz-WkNld3lMYng%3D",
    "source_league": "APTA_CHICAGO",
    "extraction_method": "team_roster",
    "team_context": "LaGrange CC 19 SW"
  },
  {
    "League": "APTA_CHICAGO",
    "Club": "LaGrange CC",
    "Series": "Series 19 SW",
    "Team": "LaGrange CC 19 SW",
    "Player ID": "nndz-WkNPd3lMLzloZz09",
    "First Name": "Tom",
    "Last Name": "Trail",
    "PTI": "59.6",
    "Wins": "0",
    "Losses": "0",
    "Win %": "0.0%",
    "Captain": "No",
    "Source URL": "https://aptachicago.tenniscores.com/?mod=nndz-TjJiOWtORzkwTlJFb0NVU1NzOD0%3D&team=nndz-WkNld3lMYng%3D",
    "source_league": "APTA_CHICAGO",
    "extraction_method": "team_roster",
    "team_context": "LaGrange CC 19 SW"
  },
  {
    "League": "APTA_CHICAGO",
    "Club": "Ruth Lake",
    "Series": "Series 19 SW",
    "Team": "Ruth Lake 19 SW",
    "Player ID": "nndz-WkNPd3hyMytqUT09",
    "First Name": "Brad",
    "Last Name": "Angeletti",
    "PTI": "N/A",
    "Wins": "",
    "Losses": "0",
    "Win %": "0.0%",
    "Captain": "Yes",
    "Source URL": "https://aptachicago.tenniscores.com/?mod=nndz-TjJiOWtORzkwTlJFb0NVU1NzOD0%3D&team=nndz-WkNld3lMYng%3D",
    "source_league": "APTA_CHICAGO",
    "extraction_method": "team_roster",
    "team_context": "Ruth Lake 19 SW"
  },
  {
    "League": "APTA_CHICAGO",
    "Club": "Ruth Lake",
    "Series": "Series 19 SW",
    "Team": "Ruth Lake 19 SW",
    "Player ID": "nndz-WkNPd3lMLzRnUT09",
    "First Name": "John",
    "Last Name": "McGowan",
    "PTI": "57.2",
    "Wins": "0",
    "Losses": "0",
    "Win %": "0.0%",
    "Captain": "No",
    "Source URL": "https://aptachicago.tenniscores.com/?mod=nndz-TjJiOWtORzkwTlJFb0NVU1NzOD0%3D&team=nndz-WkNld3lMYng%3D",
    "source_league": "APTA_CHICAGO",
    "extraction_method": "team_roster",
    "team_context": "Ruth Lake 19 SW"
  },
  {
    "League": "APTA_CHICAGO",
    "Club": "Ruth Lake",
    "Series": "Series 19 SW",
    "Team": "Ruth Lake 19 SW",
    "Player ID": "nndz-WkNDNnlMbjdndz09",
    "First Name": "Phil",
    "Last Name": "Cornies",
    "PTI": "53.6",
    "Wins": "0",
    "Losses": "0",
    "Win %": "0.0%",
    "Captain": "No",
    "Source URL": "https://aptachicago.tenniscores.com/?mod=nndz-TjJiOWtORzkwTlJFb0NVU1NzOD0%3D&team=nndz-WkNld3lMYng%3D",
    "source_league": "APTA_CHICAGO",
    "extraction_method": "team_roster",
    "team_context": "Ruth Lake 19 SW"
  },
  {
    "League": "APTA_CHICAGO",
    "Club": "Ruth Lake",
    "Series": "Series 19 SW",
    "Team": "Ruth Lake 19 SW",
    "Player ID": "nndz-WkNDd3lMajloUT09",
    "First Name": "Jack",
    "Last Name": "Cumming",
    "PTI": "N/A",
    "Wins": "0",
    "Losses": "0",
    "Win %": "0.0%",
    "Captain": "No",
    "Source URL": "https://aptachicago.tenniscores.com/?mod=nndz-TjJiOWtORzkwTlJFb0NVU1NzOD0%3D&team=nndz-WkNld3lMYng%3D",
    "source_league": "APTA_CHICAGO",
    "extraction_method": "team_roster",
    "team_context": "Ruth Lake 19 SW"
  },
  {
    "League": "APTA_CHICAGO",
    "Club": "Ruth Lake",
    "Series": "Series 19 SW",
    "Team": "Ruth Lake 19 SW",
    "Player ID": "nndz-WkNPd3hybi9qQT09",
    "First Name": "Sandeep",
    "Last Name": "Devata",
    "PTI": "N/A",
    "Wins": "0",
    "Losses": "0",
    "Win %": "0.0%",
    "Captain": "No",
    "Source URL": "https://aptachicago.tenniscores.com/?mod=nndz-TjJiOWtORzkwTlJFb0NVU1NzOD0%3D&team=nndz-WkNld3lMYng%3D",
    "source_league": "APTA_CHICAGO",
    "extraction_method": "team_roster",
    "team_context": "Ruth Lake 19 SW"
  },
  {
    "League": "APTA_CHICAGO",
    "Club": "Ruth Lake",
    "Series": "Series 19 SW",
    "Team": "Ruth Lake 19 SW",
    "Player ID": "nndz-WkNDNnhyYjhqUT09",
    "First Name": "Mark",
    "Last Name": "Fisher",
    "PTI": "N/A",
    "Wins": "0",
    "Losses": "0",
    "Win %": "0.0%",
    "Captain": "No",
    "Source URL": "https://aptachicago.tenniscores.com/?mod=nndz-TjJiOWtORzkwTlJFb0NVU1NzOD0%3D&team=nndz-WkNld3lMYng%3D",
    "source_league": "APTA_CHICAGO",
    "extraction_method": "team_roster",
    "team_context": "Ruth Lake 19 SW"
  },
  {
    "League": "APTA_CHICAGO",
    "Club": "Ruth Lake",
    "Series": "Series 19 SW",
    "Team": "Ruth Lake 19 SW",
    "Player ID": "nndz-WkNPd3hyMytoQT09",
    "First Name": "Joe",
    "Last Name": "Fodor",
    "PTI": "56.0",
    "Wins": "0",
    "Losses": "0",
    "Win %": "0.0%",
    "Captain": "No",
    "Source URL": "https://aptachicago.tenniscores.com/?mod=nndz-TjJiOWtORzkwTlJFb0NVU1NzOD0%3D&team=nndz-WkNld3lMYng%3D",
    "source_league": "APTA_CHICAGO",
    "extraction_method": "team_roster",
    "team_context": "Ruth Lake 19 SW"
  },
  {
    "League": "APTA_CHICAGO",
    "Club": "Ruth Lake",
    "Series": "Series 19 SW",
    "Team": "Ruth Lake 19 SW",
    "Player ID": "nndz-WkNHN3hiM3dnUT09",
    "First Name": "Kelly",
    "Last Name": "Isenhart",
    "PTI": "N/A",
    "Wins": "0",
    "Losses": "0",
    "Win %": "0.0%",
    "Captain": "No",
    "Source URL": "https://aptachicago.tenniscores.com/?mod=nndz-TjJiOWtORzkwTlJFb0NVU1NzOD0%3D&team=nndz-WkNld3lMYng%3D",
    "source_league": "APTA_CHICAGO",
    "extraction_method": "team_roster",
    "team_context": "Ruth Lake 19 SW"
  },
  {
    "League": "APTA_CHICAGO",
    "Club": "Ruth Lake",
    "Series": "Series 19 SW",
    "Team": "Ruth Lake 19 SW",
    "Player ID": "nndz-WkNPd3liM3doQT09",
    "First Name": "Lucas",
    "Last Name": "Pain",
    "PTI": "N/A",
    "Wins": "0",
    "Losses": "0",
    "Win %": "0.0%",
    "Captain": "No",
    "Source URL": "https://aptachicago.tenniscores.com/?mod=nndz-TjJiOWtORzkwTlJFb0NVU1NzOD0%3D&team=nndz-WkNld3lMYng%3D",
    "source_league": "APTA_CHICAGO",
    "extraction_method": "team_roster",
    "team_context": "Ruth Lake 19 SW"
  },
  {
    "League": "APTA_CHICAGO",
    "Club": "Ruth Lake",
    "Series": "Series 19 SW",
    "Team": "Ruth Lake 19 SW",
    "Player ID": "nndz-WkMrK3lidjlqUT09",
    "First Name": "Mitchell",
    "Last Name": "Parse",
    "PTI": "54.0",
    "Wins": "0",
    "Losses": "0",
    "Win %": "0.0%",
    "Captain": "No",
    "Source URL": "https://aptachicago.tenniscores.com/?mod=nndz-TjJiOWtORzkwTlJFb0NVU1NzOD0%3D&team=nndz-WkNld3lMYng%3D",
    "source_league": "APTA_CHICAGO",
    "extraction_method": "team_roster",
    "team_context": "Ruth Lake 19 SW"
  },
  {
    "League": "APTA_CHICAGO",
    "Club": "Ruth Lake",
    "Series": "Series 19 SW",
    "Team": "Ruth Lake 19 SW",
    "Player ID": "nndz-WkNDd3lMajdoUT09",
    "First Name": "Chris",
    "Last Name": "Skerrett",
    "PTI": "N/A",
    "Wins": "0",
    "Losses": "0",
    "Win %": "0.0%",
    "Captain": "No",
    "Source URL": "https://aptachicago.tenniscores.com/?mod=nndz-TjJiOWtORzkwTlJFb0NVU1NzOD0%3D&team=nndz-WkNld3lMYng%3D",
    "source_league": "APTA_CHICAGO",
    "extraction_method": "team_roster",
    "team_context": "Ruth Lake 19 SW"
  },
  {
    "League": "APTA_CHICAGO",
    "Club": "Ruth Lake",
    "Series": "Series 19 SW",
    "Team": "Ruth Lake 19 SW",
    "Player ID": "nndz-WkNHNXg3djVnQT09",
    "First Name": "Tom",
    "Last Name": "Will",
    "PTI": "56.5",
    "Wins": "0",
    "Losses": "0",
    "Win %": "0.0%",
    "Captain": "No",
    "Source URL": "https://aptachicago.tenniscores.com/?mod=nndz-TjJiOWtORzkwTlJFb0NVU1NzOD0%3D&team=nndz-WkNld3lMYng%3D",
    "source_league": "APTA_CHICAGO",
    "extraction_method": "team_roster",
    "team_context": "Ruth Lake 19 SW"
  },
  {
    "League": "APTA_CHICAGO",
    "Club": "Salt Creek",
    "Series": "Series 19 SW",
    "Team": "Salt Creek 19 SW",
    "Player ID": "nndz-WkNPd3hybjRnQT09",
    "First Name": "Tom",
    "Last Name": "Dziedzic",
    "PTI": "N/A",
    "Wins": "",
    "Losses": "0",
    "Win %": "0.0%",
    "Captain": "Yes",
    "Source URL": "https://aptachicago.tenniscores.com/?mod=nndz-TjJiOWtORzkwTlJFb0NVU1NzOD0%3D&team=nndz-WkNld3lMYng%3D",
    "source_league": "APTA_CHICAGO",
    "extraction_method": "team_roster",
    "team_context": "Salt Creek 19 SW"
  },
  {
    "League": "APTA_CHICAGO",
    "Club": "Salt Creek",
    "Series": "Series 19 SW",
    "Team": "Salt Creek 19 SW",
    "Player ID": "nndz-WkNPd3liLzRoQT09",
    "First Name": "Frank",
    "Last Name": "Adamo",
    "PTI": "N/A",
    "Wins": "0",
    "Losses": "0",
    "Win %": "0.0%",
    "Captain": "No",
    "Source URL": "https://aptachicago.tenniscores.com/?mod=nndz-TjJiOWtORzkwTlJFb0NVU1NzOD0%3D&team=nndz-WkNld3lMYng%3D",
    "source_league": "APTA_CHICAGO",
    "extraction_method": "team_roster",
    "team_context": "Salt Creek 19 SW"
  },
  {
    "League": "APTA_CHICAGO",
    "Club": "Salt Creek",
    "Series": "Series 19 SW",
    "Team": "Salt Creek 19 SW",
    "Player ID": "nndz-WkNPd3g3endnZz09",
    "First Name": "Graham",
    "Last Name": "Hershman",
    "PTI": "N/A",
    "Wins": "0",
    "Losses": "0",
    "Win %": "0.0%",
    "Captain": "No",
    "Source URL": "https://aptachicago.tenniscores.com/?mod=nndz-TjJiOWtORzkwTlJFb0NVU1NzOD0%3D&team=nndz-WkNld3lMYng%3D",
    "source_league": "APTA_CHICAGO",
    "extraction_method": "team_roster",
    "team_context": "Salt Creek 19 SW"
  },
  {
    "League": "APTA_CHICAGO",
    "Club": "Salt Creek",
    "Series": "Series 19 SW",
    "Team": "Salt Creek 19 SW",
    "Player ID": "nndz-WkNDd3g3bnhndz09",
    "First Name": "Dan",
    "Last Name": "Letizia",
    "PTI": "N/A",
    "Wins": "0",
    "Losses": "0",
    "Win %": "0.0%",
    "Captain": "No",
    "Source URL": "https://aptachicago.tenniscores.com/?mod=nndz-TjJiOWtORzkwTlJFb0NVU1NzOD0%3D&team=nndz-WkNld3lMYng%3D",
    "source_league": "APTA_CHICAGO",
    "extraction_method": "team_roster",
    "team_context": "Salt Creek 19 SW"
  },
  {
    "League": "APTA_CHICAGO",
    "Club": "Salt Creek",
    "Series": "Series 19 SW",
    "Team": "Salt Creek 19 SW",
    "Player ID": "nndz-WkNPd3licitndz09",
    "First Name": "Jack",
    "Last Name": "Lopez",
    "PTI": "N/A",
    "Wins": "0",
    "Losses": "0",
    "Win %": "0.0%",
    "Captain": "No",
    "Source URL": "https://aptachicago.tenniscores.com/?mod=nndz-TjJiOWtORzkwTlJFb0NVU1NzOD0%3D&team=nndz-WkNld3lMYng%3D",
    "source_league": "APTA_CHICAGO",
    "extraction_method": "team_roster",
    "team_context": "Salt Creek 19 SW"
  },
  {
    "League": "APTA_CHICAGO",
    "Club": "Salt Creek",
    "Series": "Series 19 SW",
    "Team": "Salt Creek 19 SW",
    "Player ID": "nndz-WkNPd3hyMzdnUT09",
    "First Name": "David",
    "Last Name": "Marcet",
    "PTI": "N/A",
    "Wins": "0",
    "Losses": "0",
    "Win %": "0.0%",
    "Captain": "No",
    "Source URL": "https://aptachicago.tenniscores.com/?mod=nndz-TjJiOWtORzkwTlJFb0NVU1NzOD0%3D&team=nndz-WkNld3lMYng%3D",
    "source_league": "APTA_CHICAGO",
    "extraction_method": "team_roster",
    "team_context": "Salt Creek 19 SW"
  },
  {
    "League": "APTA_CHICAGO",
    "Club": "Salt Creek",
    "Series": "Series 19 SW",
    "Team": "Salt Creek 19 SW",
    "Player ID": "nndz-WkNPd3hyMzdnZz09",
    "First Name": "Ben",
    "Last Name": "McLaughlin",
    "PTI": "N/A",
    "Wins": "0",
    "Losses": "0",
    "Win %": "0.0%",
    "Captain": "No",
    "Source URL": "https://aptachicago.tenniscores.com/?mod=nndz-TjJiOWtORzkwTlJFb0NVU1NzOD0%3D&team=nndz-WkNld3lMYng%3D",
    "source_league": "APTA_CHICAGO",
    "extraction_method": "team_roster",
    "team_context": "Salt Creek 19 SW"
  },
  {
    "League": "APTA_CHICAGO",
    "Club": "Salt Creek",
    "Series": "Series 19 SW",
    "Team": "Salt Creek 19 SW",
    "Player ID": "nndz-WkNPd3licjdoQT09",
    "First Name": "Jeremy",
    "Last Name": "Parwani",
    "PTI": "N/A",
    "Wins": "0",
    "Losses": "0",
    "Win %": "0.0%",
    "Captain": "No",
    "Source URL": "https://aptachicago.tenniscores.com/?mod=nndz-TjJiOWtORzkwTlJFb0NVU1NzOD0%3D&team=nndz-WkNld3lMYng%3D",
    "source_league": "APTA_CHICAGO",
    "extraction_method": "team_roster",
    "team_context": "Salt Creek 19 SW"
  },
  {
    "League": "APTA_CHICAGO",
    "Club": "Salt Creek",
    "Series": "Series 19 SW",
    "Team": "Salt Creek 19 SW",
    "Player ID": "nndz-WkNHeHdyNy9nQT09",
    "First Name": "Sook",
    "Last Name": "Shah",
    "PTI": "N/A",
    "Wins": "0",
    "Losses": "0",
    "Win %": "0.0%",
    "Captain": "No",
    "Source URL": "https://aptachicago.tenniscores.com/?mod=nndz-TjJiOWtORzkwTlJFb0NVU1NzOD0%3D&team=nndz-WkNld3lMYng%3D",
    "source_league": "APTA_CHICAGO",
    "extraction_method": "team_roster",
    "team_context": "Salt Creek 19 SW"
  },
  {
    "League": "APTA_CHICAGO",
    "Club": "Salt Creek",
    "Series": "Series 19 SW",
    "Team": "Salt Creek 19 SW",
    "Player ID": "nndz-WkNPd3hybndoZz09",
    "First Name": "Steve",
    "Last Name": "Smith",
    "PTI": "N/A",
    "Wins": "0",
    "Losses": "0",
    "Win %": "0.0%",
    "Captain": "No",
    "Source URL": "https://aptachicago.tenniscores.com/?mod=nndz-TjJiOWtORzkwTlJFb0NVU1NzOD0%3D&team=nndz-WkNld3lMYng%3D",
    "source_league": "APTA_CHICAGO",
    "extraction_method": "team_roster",
    "team_context": "Salt Creek 19 SW"
  },
  {
    "League": "APTA_CHICAGO",
    "Club": "Salt Creek",
    "Series": "Series 19 SW",
    "Team": "Salt Creek 19 SW",
    "Player ID": "nndz-WkNPd3liNytqUT09",
    "First Name": "Aaron",
    "Last Name": "Tucke",
    "PTI": "N/A",
    "Wins": "0",
    "Losses": "0",
    "Win %": "0.0%",
    "Captain": "No",
    "Source URL": "https://aptachicago.tenniscores.com/?mod=nndz-TjJiOWtORzkwTlJFb0NVU1NzOD0%3D&team=nndz-WkNld3lMYng%3D",
    "source_league": "APTA_CHICAGO",
    "extraction_method": "team_roster",
    "team_context": "Salt Creek 19 SW"
  },
  {
    "League": "APTA_CHICAGO",
    "Club": "Salt Creek",
    "Series": "Series 19 SW",
    "Team": "Salt Creek 19 SW",
    "Player ID": "nndz-WkNHNXdMN3hnQT09",
    "First Name": "Casey",
    "Last Name": "Tushaus",
    "PTI": "N/A",
    "Wins": "0",
    "Losses": "0",
    "Win %": "0.0%",
    "Captain": "No",
    "Source URL": "https://aptachicago.tenniscores.com/?mod=nndz-TjJiOWtORzkwTlJFb0NVU1NzOD0%3D&team=nndz-WkNld3lMYng%3D",
    "source_league": "APTA_CHICAGO",
    "extraction_method": "team_roster",
    "team_context": "Salt Creek 19 SW"
  }
]