[
  {
    "Player ID": "nndz-WkM2L3hMcjhoZz09",
    "First Name": "Michael",
    "Last Name": "Schallman",
    "Team": "Birchwood 19",
    "Series": "Series 19",
    "League": "APTA_CHICAGO",
    "Club": "Birchwood",
    "PTI": "50.3",
    "Wins": "1",
    "Losses": "0",
    "Win %": "100.0%",
    "Captain": "Yes",
    "Source URL": "https://aptachicago.tenniscores.com/?mod=nndz-TjJiOWtORzkwTlJFb0NVU1NzOD0%3D&team=nndz-WkNld3lMdjU%3D",
    "source_league": "APTA_CHICAGO",
    "Scraped At": "2025-09-25T08:36:09.487910"
  },
  {
    "Player ID": "nndz-WkM2L3hMcjloQT09",
    "First Name": "David",
    "Last Name": "Israel",
    "Team": "Birchwood 19",
    "Series": "Series 19",
    "League": "APTA_CHICAGO",
    "Club": "Birchwood 19",
    "PTI": "47.2",
    "Wins": "1",
    "Losses": "0",
    "Win %": "100.0%",
    "Captain": "Yes",
    "Source URL": "https://aptachicago.tenniscores.com/?mod=nndz-TjJiOWtORzkwTlJFb0NVU1NzOD0%3D&team=nndz-WkNld3lMdjU%3D",
    "source_league": "APTA_CHICAGO",
    "Scraped At": "2025-09-25T08:36:09.487968"
  },
  {
    "Player ID": "nndz-WlNlN3lMcjRoQT09",
    "First Name": "Kenny",
    "Last Name": "Eagle",
    "Team": "Birchwood 19",
    "Series": "Series 19",
    "League": "APTA_CHICAGO",
    "Club": "Birchwood 19",
    "PTI": "51.2",
    "Wins": "0",
    "Losses": "1",
    "Win %": "0.0%",
    "Captain": "No",
    "Source URL": "https://aptachicago.tenniscores.com/?mod=nndz-TjJiOWtORzkwTlJFb0NVU1NzOD0%3D&team=nndz-WkNld3lMdjU%3D",
    "source_league": "APTA_CHICAGO",
    "Scraped At": "2025-09-25T08:36:09.488023"
  },
  {
    "Player ID": "nndz-WkM2L3hMcjlnQT09",
    "First Name": "Erik",
    "Last Name": "Gimbel",
    "Team": "Birchwood 19",
    "Series": "Series 19",
    "League": "APTA_CHICAGO",
    "Club": "Birchwood 19",
    "PTI": "51.6",
    "Wins": "1",
    "Losses": "0",
    "Win %": "100.0%",
    "Captain": "No",
    "Source URL": "https://aptachicago.tenniscores.com/?mod=nndz-TjJiOWtORzkwTlJFb0NVU1NzOD0%3D&team=nndz-WkNld3lMdjU%3D",
    "source_league": "APTA_CHICAGO",
    "Scraped At": "2025-09-25T08:36:09.488067"
  },
  {
    "Player ID": "nndz-WkNPd3g3YjZndz09",
    "First Name": "Greg",
    "Last Name": "Goldsmith",
    "Team": "Birchwood 19",
    "Series": "Series 19",
    "League": "APTA_CHICAGO",
    "Club": "Birchwood 19",
    "PTI": "N/A",
    "Wins": "0",
    "Losses": "0",
    "Win %": "0.0%",
    "Captain": "No",
    "Source URL": "https://aptachicago.tenniscores.com/?mod=nndz-TjJiOWtORzkwTlJFb0NVU1NzOD0%3D&team=nndz-WkNld3lMdjU%3D",
    "source_league": "APTA_CHICAGO",
    "Scraped At": "2025-09-25T08:36:09.488111"
  },
  {
    "Player ID": "nndz-WkNPd3liZjdnQT09",
    "First Name": "Andy",
    "Last Name": "Henoch",
    "Team": "Birchwood 19",
    "Series": "Series 19",
    "League": "APTA_CHICAGO",
    "Club": "Birchwood 19",
    "PTI": "48.6",
    "Wins": "0",
    "Losses": "1",
    "Win %": "0.0%",
    "Captain": "No",
    "Source URL": "https://aptachicago.tenniscores.com/?mod=nndz-TjJiOWtORzkwTlJFb0NVU1NzOD0%3D&team=nndz-WkNld3lMdjU%3D",
    "source_league": "APTA_CHICAGO",
    "Scraped At": "2025-09-25T08:36:09.488154"
  },
  {
    "Player ID": "nndz-WkNDd3lMdjlnUT09",
    "First Name": "Adam",
    "Last Name": "Kaplan",
    "Team": "Birchwood 19",
    "Series": "Series 19",
    "League": "APTA_CHICAGO",
    "Club": "Birchwood 19",
    "PTI": "52.3",
    "Wins": "0",
    "Losses": "0",
    "Win %": "0.0%",
    "Captain": "No",
    "Source URL": "https://aptachicago.tenniscores.com/?mod=nndz-TjJiOWtORzkwTlJFb0NVU1NzOD0%3D&team=nndz-WkNld3lMdjU%3D",
    "source_league": "APTA_CHICAGO",
    "Scraped At": "2025-09-25T08:36:09.488217"
  },
  {
    "Player ID": "nndz-WkNPd3g3Yjlodz09",
    "First Name": "Howard",
    "Last Name": "Klieger",
    "Team": "Birchwood 19",
    "Series": "Series 19",
    "League": "APTA_CHICAGO",
    "Club": "Birchwood 19",
    "PTI": "51.2",
    "Wins": "0",
    "Losses": "1",
    "Win %": "0.0%",
    "Captain": "No",
    "Source URL": "https://aptachicago.tenniscores.com/?mod=nndz-TjJiOWtORzkwTlJFb0NVU1NzOD0%3D&team=nndz-WkNld3lMdjU%3D",
    "source_league": "APTA_CHICAGO",
    "Scraped At": "2025-09-25T08:36:09.488263"
  },
  {
    "Player ID": "nndz-WkNHd3dManhoZz09",
    "First Name": "Ken",
    "Last Name": "Kravenas",
    "Team": "Birchwood 19",
    "Series": "Series 19",
    "League": "APTA_CHICAGO",
    "Club": "Birchwood 19",
    "PTI": "44.5",
    "Wins": "0",
    "Losses": "1",
    "Win %": "0.0%",
    "Captain": "No",
    "Source URL": "https://aptachicago.tenniscores.com/?mod=nndz-TjJiOWtORzkwTlJFb0NVU1NzOD0%3D&team=nndz-WkNld3lMdjU%3D",
    "source_league": "APTA_CHICAGO",
    "Scraped At": "2025-09-25T08:36:09.488382"
  },
  {
    "Player ID": "nndz-WkNHeHhiditoUT09",
    "First Name": "Russell",
    "Last Name": "Mollen",
    "Team": "Birchwood 19",
    "Series": "Series 19",
    "League": "APTA_CHICAGO",
    "Club": "Birchwood 19",
    "PTI": "50.2",
    "Wins": "1",
    "Losses": "0",
    "Win %": "100.0%",
    "Captain": "No",
    "Source URL": "https://aptachicago.tenniscores.com/?mod=nndz-TjJiOWtORzkwTlJFb0NVU1NzOD0%3D&team=nndz-WkNld3lMdjU%3D",
    "source_league": "APTA_CHICAGO",
    "Scraped At": "2025-09-25T08:36:09.488456"
  },
  {
    "Player ID": "nndz-WkNDOHhMdjRodz09",
    "First Name": "Tim",
    "Last Name": "Sperling",
    "Team": "Birchwood 19",
    "Series": "Series 19",
    "League": "APTA_CHICAGO",
    "Club": "Birchwood 19",
    "PTI": "46.4",
    "Wins": "0",
    "Losses": "0",
    "Win %": "0.0%",
    "Captain": "No",
    "Source URL": "https://aptachicago.tenniscores.com/?mod=nndz-TjJiOWtORzkwTlJFb0NVU1NzOD0%3D&team=nndz-WkNld3lMdjU%3D",
    "source_league": "APTA_CHICAGO",
    "Scraped At": "2025-09-25T08:36:09.488513"
  },
  {
    "Player ID": "nndz-WkNDd3lMbjdqUT09",
    "First Name": "Dean",
    "Last Name": "Lurie",
    "Team": "Bryn Mawr 19",
    "Series": "Series 19",
    "League": "APTA_CHICAGO",
    "Club": "Bryn Mawr",
    "PTI": "53.5",
    "Wins": "1",
    "Losses": "0",
    "Win %": "100.0%",
    "Captain": "Yes",
    "Source URL": "https://aptachicago.tenniscores.com/?mod=nndz-TjJiOWtORzkwTlJFb0NVU1NzOD0%3D&team=nndz-WkNDOXhyejk%3D",
    "source_league": "APTA_CHICAGO",
    "Scraped At": "2025-09-25T08:36:11.973020"
  },
  {
    "Player ID": "nndz-WkMrK3hMMzhnQT09",
    "First Name": "scott",
    "Last Name": "fisher",
    "Team": "Bryn Mawr 19",
    "Series": "Series 19",
    "League": "APTA_CHICAGO",
    "Club": "Bryn Mawr 19",
    "PTI": "57.9",
    "Wins": "0",
    "Losses": "1",
    "Win %": "0.0%",
    "Captain": "Yes",
    "Source URL": "https://aptachicago.tenniscores.com/?mod=nndz-TjJiOWtORzkwTlJFb0NVU1NzOD0%3D&team=nndz-WkNDOXhyejk%3D",
    "source_league": "APTA_CHICAGO",
    "Scraped At": "2025-09-25T08:36:11.973089"
  },
  {
    "Player ID": "nndz-WlNlNnhMNy9qUT09",
    "First Name": "Justin",
    "Last Name": "Magale",
    "Team": "Bryn Mawr 19",
    "Series": "Series 19",
    "League": "APTA_CHICAGO",
    "Club": "Bryn Mawr 19",
    "PTI": "36.9",
    "Wins": "1",
    "Losses": "0",
    "Win %": "100.0%",
    "Captain": "No",
    "Source URL": "https://aptachicago.tenniscores.com/?mod=nndz-TjJiOWtORzkwTlJFb0NVU1NzOD0%3D&team=nndz-WkNDOXhyejk%3D",
    "source_league": "APTA_CHICAGO",
    "Scraped At": "2025-09-25T08:36:11.973136"
  },
  {
    "Player ID": "nndz-WkMrK3hMMzZnZz09",
    "First Name": "Andrew",
    "Last Name": "Ahitow",
    "Team": "Bryn Mawr 19",
    "Series": "Series 19",
    "League": "APTA_CHICAGO",
    "Club": "Bryn Mawr 19",
    "PTI": "58.6",
    "Wins": "0",
    "Losses": "1",
    "Win %": "0.0%",
    "Captain": "No",
    "Source URL": "https://aptachicago.tenniscores.com/?mod=nndz-TjJiOWtORzkwTlJFb0NVU1NzOD0%3D&team=nndz-WkNDOXhyejk%3D",
    "source_league": "APTA_CHICAGO",
    "Scraped At": "2025-09-25T08:36:11.973176"
  },
  {
    "Player ID": "nndz-WkMrK3hMZnhndz09",
    "First Name": "andrew",
    "Last Name": "bluestein",
    "Team": "Bryn Mawr 19",
    "Series": "Series 19",
    "League": "APTA_CHICAGO",
    "Club": "Bryn Mawr 19",
    "PTI": "56.1",
    "Wins": "0",
    "Losses": "0",
    "Win %": "0.0%",
    "Captain": "No",
    "Source URL": "https://aptachicago.tenniscores.com/?mod=nndz-TjJiOWtORzkwTlJFb0NVU1NzOD0%3D&team=nndz-WkNDOXhyejk%3D",
    "source_league": "APTA_CHICAGO",
    "Scraped At": "2025-09-25T08:36:11.973214"
  },
  {
    "Player ID": "nndz-WkNPd3hyYjZndz09",
    "First Name": "Dan",
    "Last Name": "Bodde",
    "Team": "Bryn Mawr 19",
    "Series": "Series 19",
    "League": "APTA_CHICAGO",
    "Club": "Bryn Mawr 19",
    "PTI": "N/A",
    "Wins": "0",
    "Losses": "0",
    "Win %": "0.0%",
    "Captain": "No",
    "Source URL": "https://aptachicago.tenniscores.com/?mod=nndz-TjJiOWtORzkwTlJFb0NVU1NzOD0%3D&team=nndz-WkNDOXhyejk%3D",
    "source_league": "APTA_CHICAGO",
    "Scraped At": "2025-09-25T08:36:11.973254"
  },
  {
    "Player ID": "nndz-WkNHNXdiLzRoQT09",
    "First Name": "Neil",
    "Last Name": "Book",
    "Team": "Bryn Mawr 19",
    "Series": "Series 19",
    "League": "APTA_CHICAGO",
    "Club": "Bryn Mawr 19",
    "PTI": "N/A",
    "Wins": "0",
    "Losses": "0",
    "Win %": "0.0%",
    "Captain": "No",
    "Source URL": "https://aptachicago.tenniscores.com/?mod=nndz-TjJiOWtORzkwTlJFb0NVU1NzOD0%3D&team=nndz-WkNDOXhyejk%3D",
    "source_league": "APTA_CHICAGO",
    "Scraped At": "2025-09-25T08:36:11.973291"
  },
  {
    "Player ID": "nndz-WkMrK3g3andoUT09",
    "First Name": "Andrew",
    "Last Name": "Connor",
    "Team": "Bryn Mawr 19",
    "Series": "Series 19",
    "League": "APTA_CHICAGO",
    "Club": "Bryn Mawr 19",
    "PTI": "31.8",
    "Wins": "0",
    "Losses": "0",
    "Win %": "0.0%",
    "Captain": "No",
    "Source URL": "https://aptachicago.tenniscores.com/?mod=nndz-TjJiOWtORzkwTlJFb0NVU1NzOD0%3D&team=nndz-WkNDOXhyejk%3D",
    "source_league": "APTA_CHICAGO",
    "Scraped At": "2025-09-25T08:36:11.973327"
  },
  {
    "Player ID": "nndz-WkNPd3hyYjZoZz09",
    "First Name": "Bradley",
    "Last Name": "Dawson",
    "Team": "Bryn Mawr 19",
    "Series": "Series 19",
    "League": "APTA_CHICAGO",
    "Club": "Bryn Mawr 19",
    "PTI": "N/A",
    "Wins": "0",
    "Losses": "0",
    "Win %": "0.0%",
    "Captain": "No",
    "Source URL": "https://aptachicago.tenniscores.com/?mod=nndz-TjJiOWtORzkwTlJFb0NVU1NzOD0%3D&team=nndz-WkNDOXhyejk%3D",
    "source_league": "APTA_CHICAGO",
    "Scraped At": "2025-09-25T08:36:11.973363"
  },
  {
    "Player ID": "nndz-WlNlOXhyendodz09",
    "First Name": "michael",
    "Last Name": "gendell",
    "Team": "Bryn Mawr 19",
    "Series": "Series 19",
    "League": "APTA_CHICAGO",
    "Club": "Bryn Mawr 19",
    "PTI": "51.9",
    "Wins": "0",
    "Losses": "0",
    "Win %": "0.0%",
    "Captain": "No",
    "Source URL": "https://aptachicago.tenniscores.com/?mod=nndz-TjJiOWtORzkwTlJFb0NVU1NzOD0%3D&team=nndz-WkNDOXhyejk%3D",
    "source_league": "APTA_CHICAGO",
    "Scraped At": "2025-09-25T08:36:11.973400"
  },
  {
    "Player ID": "nndz-WkNPd3g3ejRodz09",
    "First Name": "Mitch",
    "Last Name": "Hamer",
    "Team": "Bryn Mawr 19",
    "Series": "Series 19",
    "League": "APTA_CHICAGO",
    "Club": "Bryn Mawr 19",
    "PTI": "26.8",
    "Wins": "0",
    "Losses": "0",
    "Win %": "0.0%",
    "Captain": "No",
    "Source URL": "https://aptachicago.tenniscores.com/?mod=nndz-TjJiOWtORzkwTlJFb0NVU1NzOD0%3D&team=nndz-WkNDOXhyejk%3D",
    "source_league": "APTA_CHICAGO",
    "Scraped At": "2025-09-25T08:36:11.973436"
  },
  {
    "Player ID": "nndz-WkNDOHhydjZqQT09",
    "First Name": "Steve",
    "Last Name": "Hearn",
    "Team": "Bryn Mawr 19",
    "Series": "Series 19",
    "League": "APTA_CHICAGO",
    "Club": "Bryn Mawr 19",
    "PTI": "N/A",
    "Wins": "0",
    "Losses": "0",
    "Win %": "0.0%",
    "Captain": "No",
    "Source URL": "https://aptachicago.tenniscores.com/?mod=nndz-TjJiOWtORzkwTlJFb0NVU1NzOD0%3D&team=nndz-WkNDOXhyejk%3D",
    "source_league": "APTA_CHICAGO",
    "Scraped At": "2025-09-25T08:36:11.973472"
  },
  {
    "Player ID": "nndz-WkMreHdybitnUT09",
    "First Name": "Tyler",
    "Last Name": "Jay",
    "Team": "Bryn Mawr 19",
    "Series": "Series 19",
    "League": "APTA_CHICAGO",
    "Club": "Bryn Mawr 19",
    "PTI": "34.4",
    "Wins": "0",
    "Losses": "0",
    "Win %": "0.0%",
    "Captain": "No",
    "Source URL": "https://aptachicago.tenniscores.com/?mod=nndz-TjJiOWtORzkwTlJFb0NVU1NzOD0%3D&team=nndz-WkNDOXhyejk%3D",
    "source_league": "APTA_CHICAGO",
    "Scraped At": "2025-09-25T08:36:11.973509"
  },
  {
    "Player ID": "nndz-WlNTN3lMZjdqQT09",
    "First Name": "Phil",
    "Last Name": "Mikhaylov",
    "Team": "Bryn Mawr 19",
    "Series": "Series 19",
    "League": "APTA_CHICAGO",
    "Club": "Bryn Mawr 19",
    "PTI": "48.5",
    "Wins": "1",
    "Losses": "0",
    "Win %": "100.0%",
    "Captain": "No",
    "Source URL": "https://aptachicago.tenniscores.com/?mod=nndz-TjJiOWtORzkwTlJFb0NVU1NzOD0%3D&team=nndz-WkNDOXhyejk%3D",
    "source_league": "APTA_CHICAGO",
    "Scraped At": "2025-09-25T08:36:11.973545"
  },
  {
    "Player ID": "nndz-WlNTNHlMNytqUT09",
    "First Name": "Justin",
    "Last Name": "Penados",
    "Team": "Bryn Mawr 19",
    "Series": "Series 19",
    "League": "APTA_CHICAGO",
    "Club": "Bryn Mawr 19",
    "PTI": "51.4",
    "Wins": "0",
    "Losses": "1",
    "Win %": "0.0%",
    "Captain": "No",
    "Source URL": "https://aptachicago.tenniscores.com/?mod=nndz-TjJiOWtORzkwTlJFb0NVU1NzOD0%3D&team=nndz-WkNDOXhyejk%3D",
    "source_league": "APTA_CHICAGO",
    "Scraped At": "2025-09-25T08:36:11.973582"
  },
  {
    "Player ID": "nndz-WkMrK3hMZitnQT09",
    "First Name": "Jeff",
    "Last Name": "Randall",
    "Team": "Bryn Mawr 19",
    "Series": "Series 19",
    "League": "APTA_CHICAGO",
    "Club": "Bryn Mawr 19",
    "PTI": "46.9",
    "Wins": "0",
    "Losses": "1",
    "Win %": "0.0%",
    "Captain": "No",
    "Source URL": "https://aptachicago.tenniscores.com/?mod=nndz-TjJiOWtORzkwTlJFb0NVU1NzOD0%3D&team=nndz-WkNDOXhyejk%3D",
    "source_league": "APTA_CHICAGO",
    "Scraped At": "2025-09-25T08:36:11.973624"
  },
  {
    "Player ID": "nndz-WlNlNnhMNytoUT09",
    "First Name": "Miro",
    "Last Name": "Zivak",
    "Team": "Bryn Mawr 19",
    "Series": "Series 19",
    "League": "APTA_CHICAGO",
    "Club": "Bryn Mawr 19",
    "PTI": "46.5",
    "Wins": "1",
    "Losses": "0",
    "Win %": "100.0%",
    "Captain": "No",
    "Source URL": "https://aptachicago.tenniscores.com/?mod=nndz-TjJiOWtORzkwTlJFb0NVU1NzOD0%3D&team=nndz-WkNDOXhyejk%3D",
    "source_league": "APTA_CHICAGO",
    "Scraped At": "2025-09-25T08:36:11.973661"
  },
  {
    "Player ID": "nndz-WkNHNXdibndoQT09",
    "First Name": "Kevin",
    "Last Name": "Brannick",
    "Team": "Hawthorn Woods 19",
    "Series": "Series 19",
    "League": "APTA_CHICAGO",
    "Club": "Hawthorn Woods",
    "PTI": "45.1",
    "Wins": "0",
    "Losses": "0",
    "Win %": "0.0%",
    "Captain": "Yes",
    "Source URL": "https://aptachicago.tenniscores.com/?mod=nndz-TjJiOWtORzkwTlJFb0NVU1NzOD0%3D&team=nndz-WkNTL3dyYjk%3D",
    "source_league": "APTA_CHICAGO",
    "Scraped At": "2025-09-25T08:36:15.671918"
  },
  {
    "Player ID": "nndz-WkNPd3g3ZnhnZz09",
    "First Name": "Daniel",
    "Last Name": "Caldwell",
    "Team": "Hawthorn Woods 19",
    "Series": "Series 19",
    "League": "APTA_CHICAGO",
    "Club": "Hawthorn Woods 19",
    "PTI": "45.2",
    "Wins": "0",
    "Losses": "0",
    "Win %": "0.0%",
    "Captain": "No",
    "Source URL": "https://aptachicago.tenniscores.com/?mod=nndz-TjJiOWtORzkwTlJFb0NVU1NzOD0%3D&team=nndz-WkNTL3dyYjk%3D",
    "source_league": "APTA_CHICAGO",
    "Scraped At": "2025-09-25T08:36:15.671982"
  },
  {
    "Player ID": "nndz-WkNPd3liYjZoUT09",
    "First Name": "Sean",
    "Last Name": "Cocat",
    "Team": "Hawthorn Woods 19",
    "Series": "Series 19",
    "League": "APTA_CHICAGO",
    "Club": "Hawthorn Woods 19",
    "PTI": "N/A",
    "Wins": "0",
    "Losses": "0",
    "Win %": "0.0%",
    "Captain": "No",
    "Source URL": "https://aptachicago.tenniscores.com/?mod=nndz-TjJiOWtORzkwTlJFb0NVU1NzOD0%3D&team=nndz-WkNTL3dyYjk%3D",
    "source_league": "APTA_CHICAGO",
    "Scraped At": "2025-09-25T08:36:15.672026"
  },
  {
    "Player ID": "nndz-WkNPd3g3ejVoQT09",
    "First Name": "Ralph",
    "Last Name": "Ensign",
    "Team": "Hawthorn Woods 19",
    "Series": "Series 19",
    "League": "APTA_CHICAGO",
    "Club": "Hawthorn Woods 19",
    "PTI": "48.8",
    "Wins": "0",
    "Losses": "0",
    "Win %": "0.0%",
    "Captain": "No",
    "Source URL": "https://aptachicago.tenniscores.com/?mod=nndz-TjJiOWtORzkwTlJFb0NVU1NzOD0%3D&team=nndz-WkNTL3dyYjk%3D",
    "source_league": "APTA_CHICAGO",
    "Scraped At": "2025-09-25T08:36:15.672068"
  },
  {
    "Player ID": "nndz-WkNPd3hyN3hoQT09",
    "First Name": "Jeff",
    "Last Name": "Gilbert",
    "Team": "Hawthorn Woods 19",
    "Series": "Series 19",
    "League": "APTA_CHICAGO",
    "Club": "Hawthorn Woods 19",
    "PTI": "56.3",
    "Wins": "0",
    "Losses": "0",
    "Win %": "0.0%",
    "Captain": "No",
    "Source URL": "https://aptachicago.tenniscores.com/?mod=nndz-TjJiOWtORzkwTlJFb0NVU1NzOD0%3D&team=nndz-WkNTL3dyYjk%3D",
    "source_league": "APTA_CHICAGO",
    "Scraped At": "2025-09-25T08:36:15.672110"
  },
  {
    "Player ID": "nndz-WkNPd3lMcnhnQT09",
    "First Name": "Slava",
    "Last Name": "Leschinsky",
    "Team": "Hawthorn Woods 19",
    "Series": "Series 19",
    "League": "APTA_CHICAGO",
    "Club": "Hawthorn Woods 19",
    "PTI": "49.7",
    "Wins": "0",
    "Losses": "0",
    "Win %": "0.0%",
    "Captain": "No",
    "Source URL": "https://aptachicago.tenniscores.com/?mod=nndz-TjJiOWtORzkwTlJFb0NVU1NzOD0%3D&team=nndz-WkNTL3dyYjk%3D",
    "source_league": "APTA_CHICAGO",
    "Scraped At": "2025-09-25T08:36:15.672151"
  },
  {
    "Player ID": "nndz-WkNHeHg3andnUT09",
    "First Name": "Nick",
    "Last Name": "Lollino",
    "Team": "Hawthorn Woods 19",
    "Series": "Series 19",
    "League": "APTA_CHICAGO",
    "Club": "Hawthorn Woods 19",
    "PTI": "46.8",
    "Wins": "0",
    "Losses": "0",
    "Win %": "0.0%",
    "Captain": "No",
    "Source URL": "https://aptachicago.tenniscores.com/?mod=nndz-TjJiOWtORzkwTlJFb0NVU1NzOD0%3D&team=nndz-WkNTL3dyYjk%3D",
    "source_league": "APTA_CHICAGO",
    "Scraped At": "2025-09-25T08:36:15.672192"
  },
  {
    "Player ID": "nndz-WkNPd3liYnhodz09",
    "First Name": "Steve",
    "Last Name": "Muntz",
    "Team": "Hawthorn Woods 19",
    "Series": "Series 19",
    "League": "APTA_CHICAGO",
    "Club": "Hawthorn Woods 19",
    "PTI": "52.0",
    "Wins": "0",
    "Losses": "0",
    "Win %": "0.0%",
    "Captain": "No",
    "Source URL": "https://aptachicago.tenniscores.com/?mod=nndz-TjJiOWtORzkwTlJFb0NVU1NzOD0%3D&team=nndz-WkNTL3dyYjk%3D",
    "source_league": "APTA_CHICAGO",
    "Scraped At": "2025-09-25T08:36:15.672233"
  },
  {
    "Player ID": "nndz-WkNPd3g3LytoZz09",
    "First Name": "Tim",
    "Last Name": "Svanson",
    "Team": "Hawthorn Woods 19",
    "Series": "Series 19",
    "League": "APTA_CHICAGO",
    "Club": "Hawthorn Woods 19",
    "PTI": "46.1",
    "Wins": "0",
    "Losses": "0",
    "Win %": "0.0%",
    "Captain": "No",
    "Source URL": "https://aptachicago.tenniscores.com/?mod=nndz-TjJiOWtORzkwTlJFb0NVU1NzOD0%3D&team=nndz-WkNTL3dyYjk%3D",
    "source_league": "APTA_CHICAGO",
    "Scraped At": "2025-09-25T08:36:15.672274"
  },
  {
    "Player ID": "nndz-WlNlN3diZitqQT09",
    "First Name": "Jay-Jay",
    "Last Name": "Tuazon",
    "Team": "Hawthorn Woods 19",
    "Series": "Series 19",
    "League": "APTA_CHICAGO",
    "Club": "Hawthorn Woods 19",
    "PTI": "55.7",
    "Wins": "0",
    "Losses": "0",
    "Win %": "0.0%",
    "Captain": "No",
    "Source URL": "https://aptachicago.tenniscores.com/?mod=nndz-TjJiOWtORzkwTlJFb0NVU1NzOD0%3D&team=nndz-WkNTL3dyYjk%3D",
    "source_league": "APTA_CHICAGO",
    "Scraped At": "2025-09-25T08:36:15.672315"
  },
  {
    "Player ID": "nndz-WkNPd3hyNzRoUT09",
    "First Name": "Ryan",
    "Last Name": "Wiklund",
    "Team": "Hawthorn Woods 19",
    "Series": "Series 19",
    "League": "APTA_CHICAGO",
    "Club": "Hawthorn Woods 19",
    "PTI": "49.1",
    "Wins": "0",
    "Losses": "0",
    "Win %": "0.0%",
    "Captain": "No",
    "Source URL": "https://aptachicago.tenniscores.com/?mod=nndz-TjJiOWtORzkwTlJFb0NVU1NzOD0%3D&team=nndz-WkNTL3dyYjk%3D",
    "source_league": "APTA_CHICAGO",
    "Scraped At": "2025-09-25T08:36:15.672355"
  },
  {
    "Player ID": "nndz-WkM2L3lMcndqUT09",
    "First Name": "Ryan",
    "Last Name": "Erwin",
    "Team": "Lake Shore CC 19",
    "Series": "Series 19",
    "League": "APTA_CHICAGO",
    "Club": "Lake Shore CC",
    "PTI": "48.5",
    "Wins": "0",
    "Losses": "0",
    "Win %": "0.0%",
    "Captain": "Yes",
    "Source URL": "https://aptachicago.tenniscores.com/?mod=nndz-TjJiOWtORzkwTlJFb0NVU1NzOD0%3D&team=nndz-WkNPOHhydng%3D",
    "source_league": "APTA_CHICAGO",
    "Scraped At": "2025-09-25T08:36:24.244535"
  },
  {
    "Player ID": "nndz-WkNPd3g3ejRqQT09",
    "First Name": "Mark",
    "Last Name": "Burnstine",
    "Team": "Lake Shore CC 19",
    "Series": "Series 19",
    "League": "APTA_CHICAGO",
    "Club": "Lake Shore CC 19",
    "PTI": "52.0",
    "Wins": "0",
    "Losses": "0",
    "Win %": "0.0%",
    "Captain": "No",
    "Source URL": "https://aptachicago.tenniscores.com/?mod=nndz-TjJiOWtORzkwTlJFb0NVU1NzOD0%3D&team=nndz-WkNPOHhydng%3D",
    "source_league": "APTA_CHICAGO",
    "Scraped At": "2025-09-25T08:36:24.244598"
  },
  {
    "Player ID": "nndz-WkNPd3lMNzVodz09",
    "First Name": "Justin",
    "Last Name": "Burton",
    "Team": "Lake Shore CC 19",
    "Series": "Series 19",
    "League": "APTA_CHICAGO",
    "Club": "Lake Shore CC 19",
    "PTI": "49.6",
    "Wins": "0",
    "Losses": "0",
    "Win %": "0.0%",
    "Captain": "No",
    "Source URL": "https://aptachicago.tenniscores.com/?mod=nndz-TjJiOWtORzkwTlJFb0NVU1NzOD0%3D&team=nndz-WkNPOHhydng%3D",
    "source_league": "APTA_CHICAGO",
    "Scraped At": "2025-09-25T08:36:24.244655"
  },
  {
    "Player ID": "nndz-WkNHeHhMNzZqQT09",
    "First Name": "Matt",
    "Last Name": "Colman",
    "Team": "Lake Shore CC 19",
    "Series": "Series 19",
    "League": "APTA_CHICAGO",
    "Club": "Lake Shore CC 19",
    "PTI": "44.1",
    "Wins": "0",
    "Losses": "0",
    "Win %": "0.0%",
    "Captain": "No",
    "Source URL": "https://aptachicago.tenniscores.com/?mod=nndz-TjJiOWtORzkwTlJFb0NVU1NzOD0%3D&team=nndz-WkNPOHhydng%3D",
    "source_league": "APTA_CHICAGO",
    "Scraped At": "2025-09-25T08:36:24.244698"
  },
  {
    "Player ID": "nndz-WkNPd3lianhoZz09",
    "First Name": "Eric",
    "Last Name": "Feinberg",
    "Team": "Lake Shore CC 19",
    "Series": "Series 19",
    "League": "APTA_CHICAGO",
    "Club": "Lake Shore CC 19",
    "PTI": "43.7",
    "Wins": "0",
    "Losses": "0",
    "Win %": "0.0%",
    "Captain": "No",
    "Source URL": "https://aptachicago.tenniscores.com/?mod=nndz-TjJiOWtORzkwTlJFb0NVU1NzOD0%3D&team=nndz-WkNPOHhydng%3D",
    "source_league": "APTA_CHICAGO",
    "Scraped At": "2025-09-25T08:36:24.244739"
  },
  {
    "Player ID": "nndz-WkNHeHhMNzhoZz09",
    "First Name": "Phil",
    "Last Name": "Gerber",
    "Team": "Lake Shore CC 19",
    "Series": "Series 19",
    "League": "APTA_CHICAGO",
    "Club": "Lake Shore CC 19",
    "PTI": "44.6",
    "Wins": "0",
    "Losses": "0",
    "Win %": "0.0%",
    "Captain": "No",
    "Source URL": "https://aptachicago.tenniscores.com/?mod=nndz-TjJiOWtORzkwTlJFb0NVU1NzOD0%3D&team=nndz-WkNPOHhydng%3D",
    "source_league": "APTA_CHICAGO",
    "Scraped At": "2025-09-25T08:36:24.244781"
  },
  {
    "Player ID": "nndz-WkNPd3g3ejhqQT09",
    "First Name": "Ethan",
    "Last Name": "Holland",
    "Team": "Lake Shore CC 19",
    "Series": "Series 19",
    "League": "APTA_CHICAGO",
    "Club": "Lake Shore CC 19",
    "PTI": "42.0",
    "Wins": "0",
    "Losses": "0",
    "Win %": "0.0%",
    "Captain": "No",
    "Source URL": "https://aptachicago.tenniscores.com/?mod=nndz-TjJiOWtORzkwTlJFb0NVU1NzOD0%3D&team=nndz-WkNPOHhydng%3D",
    "source_league": "APTA_CHICAGO",
    "Scraped At": "2025-09-25T08:36:24.244841"
  },
  {
    "Player ID": "nndz-WkM2L3hMdndndz09",
    "First Name": "Chris",
    "Last Name": "Najafi",
    "Team": "Lake Shore CC 19",
    "Series": "Series 19",
    "League": "APTA_CHICAGO",
    "Club": "Lake Shore CC 19",
    "PTI": "45.8",
    "Wins": "0",
    "Losses": "0",
    "Win %": "0.0%",
    "Captain": "No",
    "Source URL": "https://aptachicago.tenniscores.com/?mod=nndz-TjJiOWtORzkwTlJFb0NVU1NzOD0%3D&team=nndz-WkNPOHhydng%3D",
    "source_league": "APTA_CHICAGO",
    "Scraped At": "2025-09-25T08:36:24.244886"
  },
  {
    "Player ID": "nndz-WkNHNXc3MzVqQT09",
    "First Name": "Cody",
    "Last Name": "Scheyer",
    "Team": "Lake Shore CC 19",
    "Series": "Series 19",
    "League": "APTA_CHICAGO",
    "Club": "Lake Shore CC 19",
    "PTI": "47.8",
    "Wins": "0",
    "Losses": "0",
    "Win %": "0.0%",
    "Captain": "No",
    "Source URL": "https://aptachicago.tenniscores.com/?mod=nndz-TjJiOWtORzkwTlJFb0NVU1NzOD0%3D&team=nndz-WkNPOHhydng%3D",
    "source_league": "APTA_CHICAGO",
    "Scraped At": "2025-09-25T08:36:24.244928"
  },
  {
    "Player ID": "nndz-WkNPd3hMaitnUT09",
    "First Name": "Ed",
    "Last Name": "Weil",
    "Team": "Lake Shore CC 19",
    "Series": "Series 19",
    "League": "APTA_CHICAGO",
    "Club": "Lake Shore CC 19",
    "PTI": "42.2",
    "Wins": "0",
    "Losses": "0",
    "Win %": "0.0%",
    "Captain": "No",
    "Source URL": "https://aptachicago.tenniscores.com/?mod=nndz-TjJiOWtORzkwTlJFb0NVU1NzOD0%3D&team=nndz-WkNPOHhydng%3D",
    "source_league": "APTA_CHICAGO",
    "Scraped At": "2025-09-25T08:36:24.244971"
  },
  {
    "Player ID": "nndz-WkNHeHlMejVoUT09",
    "First Name": "Tyler",
    "Last Name": "Weinberg",
    "Team": "Lake Shore CC 19",
    "Series": "Series 19",
    "League": "APTA_CHICAGO",
    "Club": "Lake Shore CC 19",
    "PTI": "42.8",
    "Wins": "0",
    "Losses": "0",
    "Win %": "0.0%",
    "Captain": "No",
    "Source URL": "https://aptachicago.tenniscores.com/?mod=nndz-TjJiOWtORzkwTlJFb0NVU1NzOD0%3D&team=nndz-WkNPOHhydng%3D",
    "source_league": "APTA_CHICAGO",
    "Scraped At": "2025-09-25T08:36:24.245012"
  },
  {
    "Player ID": "nndz-WkNHeHliNzhqUT09",
    "First Name": "Adam",
    "Last Name": "Wexner",
    "Team": "Lake Shore CC 19",
    "Series": "Series 19",
    "League": "APTA_CHICAGO",
    "Club": "Lake Shore CC 19",
    "PTI": "46.7",
    "Wins": "0",
    "Losses": "0",
    "Win %": "0.0%",
    "Captain": "No",
    "Source URL": "https://aptachicago.tenniscores.com/?mod=nndz-TjJiOWtORzkwTlJFb0NVU1NzOD0%3D&team=nndz-WkNPOHhydng%3D",
    "source_league": "APTA_CHICAGO",
    "Scraped At": "2025-09-25T08:36:24.245054"
  },
  {
    "Player ID": "nndz-WkM2L3hMYjRqQT09",
    "First Name": "David",
    "Last Name": "Trumbell",
    "Team": "Michigan Shores 19",
    "Series": "Series 19",
    "League": "APTA_CHICAGO",
    "Club": "Michigan Shores",
    "PTI": "55.5",
    "Wins": "0",
    "Losses": "0",
    "Win %": "0.0%",
    "Captain": "Yes",
    "Source URL": "https://aptachicago.tenniscores.com/?mod=nndz-TjJiOWtORzkwTlJFb0NVU1NzOD0%3D&team=nndz-WkNld3lMejU%3D",
    "source_league": "APTA_CHICAGO",
    "Scraped At": "2025-09-25T08:36:26.736320"
  },
  {
    "Player ID": "nndz-WkNDd3g3bjZoUT09",
    "First Name": "Matt",
    "Last Name": "Singer",
    "Team": "Michigan Shores 19",
    "Series": "Series 19",
    "League": "APTA_CHICAGO",
    "Club": "Michigan Shores 19",
    "PTI": "53.0",
    "Wins": "0",
    "Losses": "0",
    "Win %": "0.0%",
    "Captain": "Yes",
    "Source URL": "https://aptachicago.tenniscores.com/?mod=nndz-TjJiOWtORzkwTlJFb0NVU1NzOD0%3D&team=nndz-WkNld3lMejU%3D",
    "source_league": "APTA_CHICAGO",
    "Scraped At": "2025-09-25T08:36:26.736375"
  },
  {
    "Player ID": "nndz-WkNPd3lMejRqQT09",
    "First Name": "Brock",
    "Last Name": "Blazo",
    "Team": "Michigan Shores 19",
    "Series": "Series 19",
    "League": "APTA_CHICAGO",
    "Club": "Michigan Shores 19",
    "PTI": "47.6",
    "Wins": "0",
    "Losses": "0",
    "Win %": "0.0%",
    "Captain": "No",
    "Source URL": "https://aptachicago.tenniscores.com/?mod=nndz-TjJiOWtORzkwTlJFb0NVU1NzOD0%3D&team=nndz-WkNld3lMejU%3D",
    "source_league": "APTA_CHICAGO",
    "Scraped At": "2025-09-25T08:36:26.736425"
  },
  {
    "Player ID": "nndz-WkNPd3lMejRqUT09",
    "First Name": "Mark",
    "Last Name": "Buckley",
    "Team": "Michigan Shores 19",
    "Series": "Series 19",
    "League": "APTA_CHICAGO",
    "Club": "Michigan Shores 19",
    "PTI": "47.6",
    "Wins": "0",
    "Losses": "0",
    "Win %": "0.0%",
    "Captain": "No",
    "Source URL": "https://aptachicago.tenniscores.com/?mod=nndz-TjJiOWtORzkwTlJFb0NVU1NzOD0%3D&team=nndz-WkNld3lMejU%3D",
    "source_league": "APTA_CHICAGO",
    "Scraped At": "2025-09-25T08:36:26.736469"
  },
  {
    "Player ID": "nndz-WkNDNnlMYjdnUT09",
    "First Name": "Phil",
    "Last Name": "Geiger",
    "Team": "Michigan Shores 19",
    "Series": "Series 19",
    "League": "APTA_CHICAGO",
    "Club": "Michigan Shores 19",
    "PTI": "47.3",
    "Wins": "0",
    "Losses": "0",
    "Win %": "0.0%",
    "Captain": "No",
    "Source URL": "https://aptachicago.tenniscores.com/?mod=nndz-TjJiOWtORzkwTlJFb0NVU1NzOD0%3D&team=nndz-WkNld3lMejU%3D",
    "source_league": "APTA_CHICAGO",
    "Scraped At": "2025-09-25T08:36:26.736511"
  },
  {
    "Player ID": "nndz-WkNDNnliLzdndz09",
    "First Name": "Ian",
    "Last Name": "Hinchcliffe",
    "Team": "Michigan Shores 19",
    "Series": "Series 19",
    "League": "APTA_CHICAGO",
    "Club": "Michigan Shores 19",
    "PTI": "51.5",
    "Wins": "0",
    "Losses": "0",
    "Win %": "0.0%",
    "Captain": "No",
    "Source URL": "https://aptachicago.tenniscores.com/?mod=nndz-TjJiOWtORzkwTlJFb0NVU1NzOD0%3D&team=nndz-WkNld3lMejU%3D",
    "source_league": "APTA_CHICAGO",
    "Scraped At": "2025-09-25T08:36:26.736574"
  },
  {
    "Player ID": "nndz-WkNPd3hyZjdndz09",
    "First Name": "Mike",
    "Last Name": "Martin",
    "Team": "Michigan Shores 19",
    "Series": "Series 19",
    "League": "APTA_CHICAGO",
    "Club": "Michigan Shores 19",
    "PTI": "40.9",
    "Wins": "0",
    "Losses": "0",
    "Win %": "0.0%",
    "Captain": "No",
    "Source URL": "https://aptachicago.tenniscores.com/?mod=nndz-TjJiOWtORzkwTlJFb0NVU1NzOD0%3D&team=nndz-WkNld3lMejU%3D",
    "source_league": "APTA_CHICAGO",
    "Scraped At": "2025-09-25T08:36:26.736617"
  },
  {
    "Player ID": "nndz-WkNPd3hyajdnZz09",
    "First Name": "Rob",
    "Last Name": "Merrilees",
    "Team": "Michigan Shores 19",
    "Series": "Series 19",
    "League": "APTA_CHICAGO",
    "Club": "Michigan Shores 19",
    "PTI": "49.2",
    "Wins": "0",
    "Losses": "0",
    "Win %": "0.0%",
    "Captain": "No",
    "Source URL": "https://aptachicago.tenniscores.com/?mod=nndz-TjJiOWtORzkwTlJFb0NVU1NzOD0%3D&team=nndz-WkNld3lMejU%3D",
    "source_league": "APTA_CHICAGO",
    "Scraped At": "2025-09-25T08:36:26.736659"
  },
  {
    "Player ID": "nndz-WkNPd3hyLytoUT09",
    "First Name": "Dave",
    "Last Name": "Morgan",
    "Team": "Michigan Shores 19",
    "Series": "Series 19",
    "League": "APTA_CHICAGO",
    "Club": "Michigan Shores 19",
    "PTI": "46.7",
    "Wins": "0",
    "Losses": "0",
    "Win %": "0.0%",
    "Captain": "No",
    "Source URL": "https://aptachicago.tenniscores.com/?mod=nndz-TjJiOWtORzkwTlJFb0NVU1NzOD0%3D&team=nndz-WkNld3lMejU%3D",
    "source_league": "APTA_CHICAGO",
    "Scraped At": "2025-09-25T08:36:26.736700"
  },
  {
    "Player ID": "nndz-WkNPd3lMajlodz09",
    "First Name": "Jason",
    "Last Name": "Moskowitz",
    "Team": "Michigan Shores 19",
    "Series": "Series 19",
    "League": "APTA_CHICAGO",
    "Club": "Michigan Shores 19",
    "PTI": "48.0",
    "Wins": "0",
    "Losses": "0",
    "Win %": "0.0%",
    "Captain": "No",
    "Source URL": "https://aptachicago.tenniscores.com/?mod=nndz-TjJiOWtORzkwTlJFb0NVU1NzOD0%3D&team=nndz-WkNld3lMejU%3D",
    "source_league": "APTA_CHICAGO",
    "Scraped At": "2025-09-25T08:36:26.736742"
  },
  {
    "Player ID": "nndz-WkNPd3lMai9nUT09",
    "First Name": "Brian",
    "Last Name": "Rogers",
    "Team": "Michigan Shores 19",
    "Series": "Series 19",
    "League": "APTA_CHICAGO",
    "Club": "Michigan Shores 19",
    "PTI": "45.9",
    "Wins": "0",
    "Losses": "0",
    "Win %": "0.0%",
    "Captain": "No",
    "Source URL": "https://aptachicago.tenniscores.com/?mod=nndz-TjJiOWtORzkwTlJFb0NVU1NzOD0%3D&team=nndz-WkNld3lMejU%3D",
    "source_league": "APTA_CHICAGO",
    "Scraped At": "2025-09-25T08:36:26.736783"
  },
  {
    "Player ID": "nndz-WkNDNnlMYjZoZz09",
    "First Name": "Patrick",
    "Last Name": "Sheedy",
    "Team": "Michigan Shores 19",
    "Series": "Series 19",
    "League": "APTA_CHICAGO",
    "Club": "Michigan Shores 19",
    "PTI": "40.5",
    "Wins": "0",
    "Losses": "0",
    "Win %": "0.0%",
    "Captain": "No",
    "Source URL": "https://aptachicago.tenniscores.com/?mod=nndz-TjJiOWtORzkwTlJFb0NVU1NzOD0%3D&team=nndz-WkNld3lMejU%3D",
    "source_league": "APTA_CHICAGO",
    "Scraped At": "2025-09-25T08:36:26.736825"
  },
  {
    "Player ID": "nndz-WkNPd3liMzlnUT09",
    "First Name": "Fred",
    "Last Name": "Betsoleiman",
    "Team": "Prairie Club 19",
    "Series": "Series 19",
    "League": "APTA_CHICAGO",
    "Club": "Prairie Club",
    "PTI": "52.9",
    "Wins": "0",
    "Losses": "0",
    "Win %": "0.0%",
    "Captain": "Yes",
    "Source URL": "https://aptachicago.tenniscores.com/?mod=nndz-TjJiOWtORzkwTlJFb0NVU1NzOD0%3D&team=nndz-WkNld3lMdjg%3D",
    "source_league": "APTA_CHICAGO",
    "Scraped At": "2025-09-25T08:36:31.287736"
  },
  {
    "Player ID": "nndz-WkNPd3liejVoUT09",
    "First Name": "Tim",
    "Last Name": "Merrigan",
    "Team": "Prairie Club 19",
    "Series": "Series 19",
    "League": "APTA_CHICAGO",
    "Club": "Prairie Club 19",
    "PTI": "45.3",
    "Wins": "0",
    "Losses": "0",
    "Win %": "0.0%",
    "Captain": "Yes",
    "Source URL": "https://aptachicago.tenniscores.com/?mod=nndz-TjJiOWtORzkwTlJFb0NVU1NzOD0%3D&team=nndz-WkNld3lMdjg%3D",
    "source_league": "APTA_CHICAGO",
    "Scraped At": "2025-09-25T08:36:31.287807"
  },
  {
    "Player ID": "nndz-WkM2L3dyejdndz09",
    "First Name": "Zac",
    "Last Name": "Barry",
    "Team": "Prairie Club 19",
    "Series": "Series 19",
    "League": "APTA_CHICAGO",
    "Club": "Prairie Club 19",
    "PTI": "51.6",
    "Wins": "0",
    "Losses": "0",
    "Win %": "0.0%",
    "Captain": "No",
    "Source URL": "https://aptachicago.tenniscores.com/?mod=nndz-TjJiOWtORzkwTlJFb0NVU1NzOD0%3D&team=nndz-WkNld3lMdjg%3D",
    "source_league": "APTA_CHICAGO",
    "Scraped At": "2025-09-25T08:36:31.287860"
  },
  {
    "Player ID": "nndz-WkNPd3g3djRodz09",
    "First Name": "Tod",
    "Last Name": "Folkl",
    "Team": "Prairie Club 19",
    "Series": "Series 19",
    "League": "APTA_CHICAGO",
    "Club": "Prairie Club 19",
    "PTI": "50.3",
    "Wins": "0",
    "Losses": "0",
    "Win %": "0.0%",
    "Captain": "No",
    "Source URL": "https://aptachicago.tenniscores.com/?mod=nndz-TjJiOWtORzkwTlJFb0NVU1NzOD0%3D&team=nndz-WkNld3lMdjg%3D",
    "source_league": "APTA_CHICAGO",
    "Scraped At": "2025-09-25T08:36:31.287918"
  },
  {
    "Player ID": "nndz-WkNPd3g3ZjlqQT09",
    "First Name": "Randall",
    "Last Name": "Kelly",
    "Team": "Prairie Club 19",
    "Series": "Series 19",
    "League": "APTA_CHICAGO",
    "Club": "Prairie Club 19",
    "PTI": "50.7",
    "Wins": "0",
    "Losses": "0",
    "Win %": "0.0%",
    "Captain": "No",
    "Source URL": "https://aptachicago.tenniscores.com/?mod=nndz-TjJiOWtORzkwTlJFb0NVU1NzOD0%3D&team=nndz-WkNld3lMdjg%3D",
    "source_league": "APTA_CHICAGO",
    "Scraped At": "2025-09-25T08:36:31.287963"
  },
  {
    "Player ID": "nndz-WkNPd3liMzhoQT09",
    "First Name": "Jeff",
    "Last Name": "Kolker",
    "Team": "Prairie Club 19",
    "Series": "Series 19",
    "League": "APTA_CHICAGO",
    "Club": "Prairie Club 19",
    "PTI": "40.7",
    "Wins": "0",
    "Losses": "0",
    "Win %": "0.0%",
    "Captain": "No",
    "Source URL": "https://aptachicago.tenniscores.com/?mod=nndz-TjJiOWtORzkwTlJFb0NVU1NzOD0%3D&team=nndz-WkNld3lMdjg%3D",
    "source_league": "APTA_CHICAGO",
    "Scraped At": "2025-09-25T08:36:31.288006"
  },
  {
    "Player ID": "nndz-WkNDNnhyYjdoQT09",
    "First Name": "Chris",
    "Last Name": "McDermott",
    "Team": "Prairie Club 19",
    "Series": "Series 19",
    "League": "APTA_CHICAGO",
    "Club": "Prairie Club 19",
    "PTI": "49.6",
    "Wins": "0",
    "Losses": "0",
    "Win %": "0.0%",
    "Captain": "No",
    "Source URL": "https://aptachicago.tenniscores.com/?mod=nndz-TjJiOWtORzkwTlJFb0NVU1NzOD0%3D&team=nndz-WkNld3lMdjg%3D",
    "source_league": "APTA_CHICAGO",
    "Scraped At": "2025-09-25T08:36:31.288049"
  },
  {
    "Player ID": "nndz-WkNPd3liYjloQT09",
    "First Name": "Andrew",
    "Last Name": "Miehl",
    "Team": "Prairie Club 19",
    "Series": "Series 19",
    "League": "APTA_CHICAGO",
    "Club": "Prairie Club 19",
    "PTI": "51.4",
    "Wins": "0",
    "Losses": "0",
    "Win %": "0.0%",
    "Captain": "No",
    "Source URL": "https://aptachicago.tenniscores.com/?mod=nndz-TjJiOWtORzkwTlJFb0NVU1NzOD0%3D&team=nndz-WkNld3lMdjg%3D",
    "source_league": "APTA_CHICAGO",
    "Scraped At": "2025-09-25T08:36:31.288092"
  },
  {
    "Player ID": "nndz-WkNPd3lieitqQT09",
    "First Name": "Bob",
    "Last Name": "Richmond",
    "Team": "Prairie Club 19",
    "Series": "Series 19",
    "League": "APTA_CHICAGO",
    "Club": "Prairie Club 19",
    "PTI": "43.6",
    "Wins": "0",
    "Losses": "0",
    "Win %": "0.0%",
    "Captain": "No",
    "Source URL": "https://aptachicago.tenniscores.com/?mod=nndz-TjJiOWtORzkwTlJFb0NVU1NzOD0%3D&team=nndz-WkNld3lMdjg%3D",
    "source_league": "APTA_CHICAGO",
    "Scraped At": "2025-09-25T08:36:31.288135"
  },
  {
    "Player ID": "nndz-WkNPd3g3ZjlnZz09",
    "First Name": "Jeff",
    "Last Name": "Schultz",
    "Team": "Prairie Club 19",
    "Series": "Series 19",
    "League": "APTA_CHICAGO",
    "Club": "Prairie Club 19",
    "PTI": "51.2",
    "Wins": "0",
    "Losses": "0",
    "Win %": "0.0%",
    "Captain": "No",
    "Source URL": "https://aptachicago.tenniscores.com/?mod=nndz-TjJiOWtORzkwTlJFb0NVU1NzOD0%3D&team=nndz-WkNld3lMdjg%3D",
    "source_league": "APTA_CHICAGO",
    "Scraped At": "2025-09-25T08:36:31.288178"
  },
  {
    "Player ID": "nndz-WkNPd3hyNzVnUT09",
    "First Name": "Brian",
    "Last Name": "Wrona",
    "Team": "Prairie Club 19",
    "Series": "Series 19",
    "League": "APTA_CHICAGO",
    "Club": "Prairie Club 19",
    "PTI": "49.5",
    "Wins": "0",
    "Losses": "0",
    "Win %": "0.0%",
    "Captain": "No",
    "Source URL": "https://aptachicago.tenniscores.com/?mod=nndz-TjJiOWtORzkwTlJFb0NVU1NzOD0%3D&team=nndz-WkNld3lMdjg%3D",
    "source_league": "APTA_CHICAGO",
    "Scraped At": "2025-09-25T08:36:31.288222"
  },
  {
    "Player ID": "nndz-WkNPd3liL3dqQT09",
    "First Name": "Bob",
    "Last Name": "Hamman",
    "Team": "Skokie 19",
    "Series": "Series 19",
    "League": "APTA_CHICAGO",
    "Club": "Skokie",
    "PTI": "48.3",
    "Wins": "0",
    "Losses": "1",
    "Win %": "0.0%",
    "Captain": "Yes",
    "Source URL": "https://aptachicago.tenniscores.com/?mod=nndz-TjJiOWtORzkwTlJFb0NVU1NzOD0%3D&team=nndz-WkNld3lMcjg%3D",
    "source_league": "APTA_CHICAGO",
    "Scraped At": "2025-09-25T08:36:34.616312"
  },
  {
    "Player ID": "nndz-WkNHd3hyNzdoQT09",
    "First Name": "Christopher",
    "Last Name": "Bechtel",
    "Team": "Skokie 19",
    "Series": "Series 19",
    "League": "APTA_CHICAGO",
    "Club": "Skokie 19",
    "PTI": "42.9",
    "Wins": "1",
    "Losses": "0",
    "Win %": "100.0%",
    "Captain": "No",
    "Source URL": "https://aptachicago.tenniscores.com/?mod=nndz-TjJiOWtORzkwTlJFb0NVU1NzOD0%3D&team=nndz-WkNld3lMcjg%3D",
    "source_league": "APTA_CHICAGO",
    "Scraped At": "2025-09-25T08:36:34.616377"
  },
  {
    "Player ID": "nndz-WkNPd3liL3dqUT09",
    "First Name": "Ned",
    "Last Name": "Frank",
    "Team": "Skokie 19",
    "Series": "Series 19",
    "League": "APTA_CHICAGO",
    "Club": "Skokie 19",
    "PTI": "49.1",
    "Wins": "1",
    "Losses": "0",
    "Win %": "100.0%",
    "Captain": "No",
    "Source URL": "https://aptachicago.tenniscores.com/?mod=nndz-TjJiOWtORzkwTlJFb0NVU1NzOD0%3D&team=nndz-WkNld3lMcjg%3D",
    "source_league": "APTA_CHICAGO",
    "Scraped At": "2025-09-25T08:36:34.616424"
  },
  {
    "Player ID": "nndz-WkNPd3hydi9qQT09",
    "First Name": "Gordon",
    "Last Name": "Gluckman",
    "Team": "Skokie 19",
    "Series": "Series 19",
    "League": "APTA_CHICAGO",
    "Club": "Skokie 19",
    "PTI": "45.2",
    "Wins": "0",
    "Losses": "0",
    "Win %": "0.0%",
    "Captain": "No",
    "Source URL": "https://aptachicago.tenniscores.com/?mod=nndz-TjJiOWtORzkwTlJFb0NVU1NzOD0%3D&team=nndz-WkNld3lMcjg%3D",
    "source_league": "APTA_CHICAGO",
    "Scraped At": "2025-09-25T08:36:34.616468"
  },
  {
    "Player ID": "nndz-WkNHeHlMbjlnUT09",
    "First Name": "Dan",
    "Last Name": "Hidder",
    "Team": "Skokie 19",
    "Series": "Series 19",
    "League": "APTA_CHICAGO",
    "Club": "Skokie 19",
    "PTI": "47.1",
    "Wins": "0",
    "Losses": "0",
    "Win %": "0.0%",
    "Captain": "No",
    "Source URL": "https://aptachicago.tenniscores.com/?mod=nndz-TjJiOWtORzkwTlJFb0NVU1NzOD0%3D&team=nndz-WkNld3lMcjg%3D",
    "source_league": "APTA_CHICAGO",
    "Scraped At": "2025-09-25T08:36:34.616513"
  },
  {
    "Player ID": "nndz-WkNPd3liejRodz09",
    "First Name": "Brad",
    "Last Name": "Jaros",
    "Team": "Skokie 19",
    "Series": "Series 19",
    "League": "APTA_CHICAGO",
    "Club": "Skokie 19",
    "PTI": "44.7",
    "Wins": "0",
    "Losses": "1",
    "Win %": "0.0%",
    "Captain": "No",
    "Source URL": "https://aptachicago.tenniscores.com/?mod=nndz-TjJiOWtORzkwTlJFb0NVU1NzOD0%3D&team=nndz-WkNld3lMcjg%3D",
    "source_league": "APTA_CHICAGO",
    "Scraped At": "2025-09-25T08:36:34.616555"
  },
  {
    "Player ID": "nndz-WkNPd3hyditoUT09",
    "First Name": "Ryan",
    "Last Name": "Malayter",
    "Team": "Skokie 19",
    "Series": "Series 19",
    "League": "APTA_CHICAGO",
    "Club": "Skokie 19",
    "PTI": "47.2",
    "Wins": "0",
    "Losses": "1",
    "Win %": "0.0%",
    "Captain": "No",
    "Source URL": "https://aptachicago.tenniscores.com/?mod=nndz-TjJiOWtORzkwTlJFb0NVU1NzOD0%3D&team=nndz-WkNld3lMcjg%3D",
    "source_league": "APTA_CHICAGO",
    "Scraped At": "2025-09-25T08:36:34.616596"
  },
  {
    "Player ID": "nndz-WkMrK3dMLzRnUT09",
    "First Name": "Scott",
    "Last Name": "Margolis",
    "Team": "Skokie 19",
    "Series": "Series 19",
    "League": "APTA_CHICAGO",
    "Club": "Skokie 19",
    "PTI": "54.1",
    "Wins": "1",
    "Losses": "0",
    "Win %": "100.0%",
    "Captain": "No",
    "Source URL": "https://aptachicago.tenniscores.com/?mod=nndz-TjJiOWtORzkwTlJFb0NVU1NzOD0%3D&team=nndz-WkNld3lMcjg%3D",
    "source_league": "APTA_CHICAGO",
    "Scraped At": "2025-09-25T08:36:34.616641"
  },
  {
    "Player ID": "nndz-WkM2NXlMLzlnQT09",
    "First Name": "Tom",
    "Last Name": "McKeown",
    "Team": "Skokie 19",
    "Series": "Series 19",
    "League": "APTA_CHICAGO",
    "Club": "Skokie 19",
    "PTI": "50.5",
    "Wins": "0",
    "Losses": "1",
    "Win %": "0.0%",
    "Captain": "No",
    "Source URL": "https://aptachicago.tenniscores.com/?mod=nndz-TjJiOWtORzkwTlJFb0NVU1NzOD0%3D&team=nndz-WkNld3lMcjg%3D",
    "source_league": "APTA_CHICAGO",
    "Scraped At": "2025-09-25T08:36:34.616687"
  },
  {
    "Player ID": "nndz-WkNDNnlManhqUT09",
    "First Name": "Matt",
    "Last Name": "Neal",
    "Team": "Skokie 19",
    "Series": "Series 19",
    "League": "APTA_CHICAGO",
    "Club": "Skokie 19",
    "PTI": "44.7",
    "Wins": "1",
    "Losses": "0",
    "Win %": "100.0%",
    "Captain": "No",
    "Source URL": "https://aptachicago.tenniscores.com/?mod=nndz-TjJiOWtORzkwTlJFb0NVU1NzOD0%3D&team=nndz-WkNld3lMcjg%3D",
    "source_league": "APTA_CHICAGO",
    "Scraped At": "2025-09-25T08:36:34.616732"
  },
  {
    "Player ID": "nndz-WkNPd3liL3dnZz09",
    "First Name": "Jon",
    "Last Name": "Skelly",
    "Team": "Skokie 19",
    "Series": "Series 19",
    "League": "APTA_CHICAGO",
    "Club": "Skokie 19",
    "PTI": "49.1",
    "Wins": "0",
    "Losses": "0",
    "Win %": "0.0%",
    "Captain": "No",
    "Source URL": "https://aptachicago.tenniscores.com/?mod=nndz-TjJiOWtORzkwTlJFb0NVU1NzOD0%3D&team=nndz-WkNld3lMcjg%3D",
    "source_league": "APTA_CHICAGO",
    "Scraped At": "2025-09-25T08:36:34.616791"
  },
  {
    "Player ID": "nndz-WkM2L3c3ajhoQT09",
    "First Name": "Jon",
    "Last Name": "Ziebarth",
    "Team": "Skokie 19",
    "Series": "Series 19",
    "League": "APTA_CHICAGO",
    "Club": "Skokie 19",
    "PTI": "47.3",
    "Wins": "0",
    "Losses": "0",
    "Win %": "0.0%",
    "Captain": "No",
    "Source URL": "https://aptachicago.tenniscores.com/?mod=nndz-TjJiOWtORzkwTlJFb0NVU1NzOD0%3D&team=nndz-WkNld3lMcjg%3D",
    "source_league": "APTA_CHICAGO",
    "Scraped At": "2025-09-25T08:36:34.616836"
  },
  {
    "Player ID": "nndz-WkNPd3g3ZjhoZz09",
    "First Name": "Bill",
    "Last Name": "McMenamin",
    "Team": "Sunset Ridge 19",
    "Series": "Series 19",
    "League": "APTA_CHICAGO",
    "Club": "Sunset Ridge",
    "PTI": "50.3",
    "Wins": "0",
    "Losses": "0",
    "Win %": "0.0%",
    "Captain": "Yes",
    "Source URL": "https://aptachicago.tenniscores.com/?mod=nndz-TjJiOWtORzkwTlJFb0NVU1NzOD0%3D&team=nndz-WkNld3lMM3c%3D",
    "source_league": "APTA_CHICAGO",
    "Scraped At": "2025-09-25T08:36:37.850593"
  },
  {
    "Player ID": "nndz-WkNHeHg3MzloQT09",
    "First Name": "Ryan",
    "Last Name": "Skaggs",
    "Team": "Sunset Ridge 19",
    "Series": "Series 19",
    "League": "APTA_CHICAGO",
    "Club": "Sunset Ridge 19",
    "PTI": "51.5",
    "Wins": "0",
    "Losses": "0",
    "Win %": "0.0%",
    "Captain": "Yes",
    "Source URL": "https://aptachicago.tenniscores.com/?mod=nndz-TjJiOWtORzkwTlJFb0NVU1NzOD0%3D&team=nndz-WkNld3lMM3c%3D",
    "source_league": "APTA_CHICAGO",
    "Scraped At": "2025-09-25T08:36:37.850649"
  },
  {
    "Player ID": "nndz-WkNPd3hyYjdqQT09",
    "First Name": "Jim",
    "Last Name": "Anetsberger",
    "Team": "Sunset Ridge 19",
    "Series": "Series 19",
    "League": "APTA_CHICAGO",
    "Club": "Sunset Ridge 19",
    "PTI": "52.4",
    "Wins": "0",
    "Losses": "0",
    "Win %": "0.0%",
    "Captain": "No",
    "Source URL": "https://aptachicago.tenniscores.com/?mod=nndz-TjJiOWtORzkwTlJFb0NVU1NzOD0%3D&team=nndz-WkNld3lMM3c%3D",
    "source_league": "APTA_CHICAGO",
    "Scraped At": "2025-09-25T08:36:37.850701"
  },
  {
    "Player ID": "nndz-WkNPd3g3Zi9oZz09",
    "First Name": "Scott",
    "Last Name": "Cyphers",
    "Team": "Sunset Ridge 19",
    "Series": "Series 19",
    "League": "APTA_CHICAGO",
    "Club": "Sunset Ridge 19",
    "PTI": "54.2",
    "Wins": "0",
    "Losses": "0",
    "Win %": "0.0%",
    "Captain": "No",
    "Source URL": "https://aptachicago.tenniscores.com/?mod=nndz-TjJiOWtORzkwTlJFb0NVU1NzOD0%3D&team=nndz-WkNld3lMM3c%3D",
    "source_league": "APTA_CHICAGO",
    "Scraped At": "2025-09-25T08:36:37.850745"
  },
  {
    "Player ID": "nndz-WkNPd3lMci9qQT09",
    "First Name": "James",
    "Last Name": "Dolan",
    "Team": "Sunset Ridge 19",
    "Series": "Series 19",
    "League": "APTA_CHICAGO",
    "Club": "Sunset Ridge 19",
    "PTI": "50.6",
    "Wins": "0",
    "Losses": "0",
    "Win %": "0.0%",
    "Captain": "No",
    "Source URL": "https://aptachicago.tenniscores.com/?mod=nndz-TjJiOWtORzkwTlJFb0NVU1NzOD0%3D&team=nndz-WkNld3lMM3c%3D",
    "source_league": "APTA_CHICAGO",
    "Scraped At": "2025-09-25T08:36:37.850788"
  },
  {
    "Player ID": "nndz-WkNDNnhydjhqUT09",
    "First Name": "Dan",
    "Last Name": "Farrell",
    "Team": "Sunset Ridge 19",
    "Series": "Series 19",
    "League": "APTA_CHICAGO",
    "Club": "Sunset Ridge 19",
    "PTI": "48.9",
    "Wins": "0",
    "Losses": "0",
    "Win %": "0.0%",
    "Captain": "No",
    "Source URL": "https://aptachicago.tenniscores.com/?mod=nndz-TjJiOWtORzkwTlJFb0NVU1NzOD0%3D&team=nndz-WkNld3lMM3c%3D",
    "source_league": "APTA_CHICAGO",
    "Scraped At": "2025-09-25T08:36:37.850830"
  },
  {
    "Player ID": "nndz-WlNTNndieitoUT09",
    "First Name": "Ben",
    "Last Name": "Hardiman",
    "Team": "Sunset Ridge 19",
    "Series": "Series 19",
    "League": "APTA_CHICAGO",
    "Club": "Sunset Ridge 19",
    "PTI": "56.3",
    "Wins": "0",
    "Losses": "0",
    "Win %": "0.0%",
    "Captain": "No",
    "Source URL": "https://aptachicago.tenniscores.com/?mod=nndz-TjJiOWtORzkwTlJFb0NVU1NzOD0%3D&team=nndz-WkNld3lMM3c%3D",
    "source_league": "APTA_CHICAGO",
    "Scraped At": "2025-09-25T08:36:37.850871"
  },
  {
    "Player ID": "nndz-WkNHeHg3MzloUT09",
    "First Name": "Willie",
    "Last Name": "Mullen",
    "Team": "Sunset Ridge 19",
    "Series": "Series 19",
    "League": "APTA_CHICAGO",
    "Club": "Sunset Ridge 19",
    "PTI": "52.9",
    "Wins": "0",
    "Losses": "0",
    "Win %": "0.0%",
    "Captain": "No",
    "Source URL": "https://aptachicago.tenniscores.com/?mod=nndz-TjJiOWtORzkwTlJFb0NVU1NzOD0%3D&team=nndz-WkNld3lMM3c%3D",
    "source_league": "APTA_CHICAGO",
    "Scraped At": "2025-09-25T08:36:37.850912"
  },
  {
    "Player ID": "nndz-WkNHeHhiejdnUT09",
    "First Name": "James",
    "Last Name": "Pike",
    "Team": "Sunset Ridge 19",
    "Series": "Series 19",
    "League": "APTA_CHICAGO",
    "Club": "Sunset Ridge 19",
    "PTI": "50.0",
    "Wins": "0",
    "Losses": "0",
    "Win %": "0.0%",
    "Captain": "No",
    "Source URL": "https://aptachicago.tenniscores.com/?mod=nndz-TjJiOWtORzkwTlJFb0NVU1NzOD0%3D&team=nndz-WkNld3lMM3c%3D",
    "source_league": "APTA_CHICAGO",
    "Scraped At": "2025-09-25T08:36:37.850974"
  },
  {
    "Player ID": "nndz-WkNPd3g3Znhodz09",
    "First Name": "Josh",
    "Last Name": "Robbins",
    "Team": "Sunset Ridge 19",
    "Series": "Series 19",
    "League": "APTA_CHICAGO",
    "Club": "Sunset Ridge 19",
    "PTI": "46.6",
    "Wins": "0",
    "Losses": "0",
    "Win %": "0.0%",
    "Captain": "No",
    "Source URL": "https://aptachicago.tenniscores.com/?mod=nndz-TjJiOWtORzkwTlJFb0NVU1NzOD0%3D&team=nndz-WkNld3lMM3c%3D",
    "source_league": "APTA_CHICAGO",
    "Scraped At": "2025-09-25T08:36:37.851016"
  },
  {
    "Player ID": "nndz-WkNDNnhycjlndz09",
    "First Name": "Christian",
    "Last Name": "Waite",
    "Team": "Sunset Ridge 19",
    "Series": "Series 19",
    "League": "APTA_CHICAGO",
    "Club": "Sunset Ridge 19",
    "PTI": "51.4",
    "Wins": "0",
    "Losses": "0",
    "Win %": "0.0%",
    "Captain": "No",
    "Source URL": "https://aptachicago.tenniscores.com/?mod=nndz-TjJiOWtORzkwTlJFb0NVU1NzOD0%3D&team=nndz-WkNld3lMM3c%3D",
    "source_league": "APTA_CHICAGO",
    "Scraped At": "2025-09-25T08:36:37.851057"
  },
  {
    "Player ID": "nndz-WkNPd3hyZjRoUT09",
    "First Name": "Andrew",
    "Last Name": "Wenk",
    "Team": "Sunset Ridge 19",
    "Series": "Series 19",
    "League": "APTA_CHICAGO",
    "Club": "Sunset Ridge 19",
    "PTI": "44.7",
    "Wins": "0",
    "Losses": "0",
    "Win %": "0.0%",
    "Captain": "No",
    "Source URL": "https://aptachicago.tenniscores.com/?mod=nndz-TjJiOWtORzkwTlJFb0NVU1NzOD0%3D&team=nndz-WkNld3lMM3c%3D",
    "source_league": "APTA_CHICAGO",
    "Scraped At": "2025-09-25T08:36:37.851099"
  },
  {
    "Player ID": "nndz-WkNPd3hycnhnQT09",
    "First Name": "Patrick",
    "Last Name": "McGowan",
    "Team": "Wilmette PD 19",
    "Series": "Series 19",
    "League": "APTA_CHICAGO",
    "Club": "Wilmette PD",
    "PTI": "39.0",
    "Wins": "1",
    "Losses": "0",
    "Win %": "100.0%",
    "Captain": "Yes",
    "Source URL": "https://aptachicago.tenniscores.com/?mod=nndz-TjJiOWtORzkwTlJFb0NVU1NzOD0%3D&team=nndz-WkNTL3dyZjc%3D",
    "source_league": "APTA_CHICAGO",
    "Scraped At": "2025-09-25T08:36:40.908523"
  },
  {
    "Player ID": "nndz-WkNPd3hyci9oUT09",
    "First Name": "Brody",
    "Last Name": "Lemire",
    "Team": "Wilmette PD 19",
    "Series": "Series 19",
    "League": "APTA_CHICAGO",
    "Club": "Wilmette PD 19",
    "PTI": "44.0",
    "Wins": "0",
    "Losses": "1",
    "Win %": "0.0%",
    "Captain": "Yes",
    "Source URL": "https://aptachicago.tenniscores.com/?mod=nndz-TjJiOWtORzkwTlJFb0NVU1NzOD0%3D&team=nndz-WkNTL3dyZjc%3D",
    "source_league": "APTA_CHICAGO",
    "Scraped At": "2025-09-25T08:36:40.908582"
  },
  {
    "Player ID": "nndz-WkNHeHhianhqQT09",
    "First Name": "Ricky",
    "Last Name": "Barnett",
    "Team": "Wilmette PD 19",
    "Series": "Series 19",
    "League": "APTA_CHICAGO",
    "Club": "Wilmette PD 19",
    "PTI": "46.6",
    "Wins": "0",
    "Losses": "1",
    "Win %": "0.0%",
    "Captain": "No",
    "Source URL": "https://aptachicago.tenniscores.com/?mod=nndz-TjJiOWtORzkwTlJFb0NVU1NzOD0%3D&team=nndz-WkNTL3dyZjc%3D",
    "source_league": "APTA_CHICAGO",
    "Scraped At": "2025-09-25T08:36:40.908634"
  },
  {
    "Player ID": "nndz-WkNHeHhianhnZz09",
    "First Name": "Tim",
    "Last Name": "Fields",
    "Team": "Wilmette PD 19",
    "Series": "Series 19",
    "League": "APTA_CHICAGO",
    "Club": "Wilmette PD 19",
    "PTI": "41.3",
    "Wins": "0",
    "Losses": "0",
    "Win %": "0.0%",
    "Captain": "No",
    "Source URL": "https://aptachicago.tenniscores.com/?mod=nndz-TjJiOWtORzkwTlJFb0NVU1NzOD0%3D&team=nndz-WkNTL3dyZjc%3D",
    "source_league": "APTA_CHICAGO",
    "Scraped At": "2025-09-25T08:36:40.908676"
  },
  {
    "Player ID": "nndz-WkNHNXhiL3hodz09",
    "First Name": "Dan",
    "Last Name": "Hannis",
    "Team": "Wilmette PD 19",
    "Series": "Series 19",
    "League": "APTA_CHICAGO",
    "Club": "Wilmette PD 19",
    "PTI": "42.9",
    "Wins": "1",
    "Losses": "0",
    "Win %": "100.0%",
    "Captain": "No",
    "Source URL": "https://aptachicago.tenniscores.com/?mod=nndz-TjJiOWtORzkwTlJFb0NVU1NzOD0%3D&team=nndz-WkNTL3dyZjc%3D",
    "source_league": "APTA_CHICAGO",
    "Scraped At": "2025-09-25T08:36:40.908718"
  },
  {
    "Player ID": "nndz-WkNPd3hyci9odz09",
    "First Name": "Chris",
    "Last Name": "Krueger",
    "Team": "Wilmette PD 19",
    "Series": "Series 19",
    "League": "APTA_CHICAGO",
    "Club": "Wilmette PD 19",
    "PTI": "61.0",
    "Wins": "0",
    "Losses": "0",
    "Win %": "0.0%",
    "Captain": "No",
    "Source URL": "https://aptachicago.tenniscores.com/?mod=nndz-TjJiOWtORzkwTlJFb0NVU1NzOD0%3D&team=nndz-WkNTL3dyZjc%3D",
    "source_league": "APTA_CHICAGO",
    "Scraped At": "2025-09-25T08:36:40.908768"
  },
  {
    "Player ID": "nndz-WkNPd3hydjRndz09",
    "First Name": "Beau",
    "Last Name": "Lemire",
    "Team": "Wilmette PD 19",
    "Series": "Series 19",
    "League": "APTA_CHICAGO",
    "Club": "Wilmette PD 19",
    "PTI": "56.2",
    "Wins": "1",
    "Losses": "0",
    "Win %": "100.0%",
    "Captain": "No",
    "Source URL": "https://aptachicago.tenniscores.com/?mod=nndz-TjJiOWtORzkwTlJFb0NVU1NzOD0%3D&team=nndz-WkNTL3dyZjc%3D",
    "source_league": "APTA_CHICAGO",
    "Scraped At": "2025-09-25T08:36:40.908809"
  },
  {
    "Player ID": "nndz-WkNHeHhiandoZz09",
    "First Name": "Cullan",
    "Last Name": "Stefanik",
    "Team": "Wilmette PD 19",
    "Series": "Series 19",
    "League": "APTA_CHICAGO",
    "Club": "Wilmette PD 19",
    "PTI": "58.7",
    "Wins": "0",
    "Losses": "1",
    "Win %": "0.0%",
    "Captain": "No",
    "Source URL": "https://aptachicago.tenniscores.com/?mod=nndz-TjJiOWtORzkwTlJFb0NVU1NzOD0%3D&team=nndz-WkNTL3dyZjc%3D",
    "source_league": "APTA_CHICAGO",
    "Scraped At": "2025-09-25T08:36:40.908851"
  },
  {
    "Player ID": "nndz-WkNHeHhianhnQT09",
    "First Name": "Kevin",
    "Last Name": "Swank",
    "Team": "Wilmette PD 19",
    "Series": "Series 19",
    "League": "APTA_CHICAGO",
    "Club": "Wilmette PD 19",
    "PTI": "49.1",
    "Wins": "0",
    "Losses": "1",
    "Win %": "0.0%",
    "Captain": "No",
    "Source URL": "https://aptachicago.tenniscores.com/?mod=nndz-TjJiOWtORzkwTlJFb0NVU1NzOD0%3D&team=nndz-WkNTL3dyZjc%3D",
    "source_league": "APTA_CHICAGO",
    "Scraped At": "2025-09-25T08:36:40.908914"
  },
  {
    "Player ID": "nndz-WkM2L3c3bnhnUT09",
    "First Name": "James",
    "Last Name": "Wigoda",
    "Team": "Winnetka 19",
    "Series": "Series 19",
    "League": "APTA_CHICAGO",
    "Club": "Winnetka",
    "PTI": "44.7",
    "Wins": "0",
    "Losses": "0",
    "Win %": "0.0%",
    "Captain": "Yes",
    "Source URL": "https://aptachicago.tenniscores.com/?mod=nndz-TjJiOWtORzkwTlJFb0NVU1NzOD0%3D&team=nndz-WkNLd3c3N3c%3D",
    "source_league": "APTA_CHICAGO",
    "Scraped At": "2025-09-25T08:36:44.831344"
  },
  {
    "Player ID": "nndz-WkM2L3c3bndqUT09",
    "First Name": "Danny",
    "Last Name": "Bogart",
    "Team": "Winnetka 19",
    "Series": "Series 19",
    "League": "APTA_CHICAGO",
    "Club": "Winnetka 19",
    "PTI": "48.2",
    "Wins": "0",
    "Losses": "0",
    "Win %": "0.0%",
    "Captain": "No",
    "Source URL": "https://aptachicago.tenniscores.com/?mod=nndz-TjJiOWtORzkwTlJFb0NVU1NzOD0%3D&team=nndz-WkNLd3c3N3c%3D",
    "source_league": "APTA_CHICAGO",
    "Scraped At": "2025-09-25T08:36:44.831406"
  },
  {
    "Player ID": "nndz-WkNHd3diLytqQT09",
    "First Name": "Bryan",
    "Last Name": "Fischer",
    "Team": "Winnetka 19",
    "Series": "Series 19",
    "League": "APTA_CHICAGO",
    "Club": "Winnetka 19",
    "PTI": "49.6",
    "Wins": "0",
    "Losses": "0",
    "Win %": "0.0%",
    "Captain": "No",
    "Source URL": "https://aptachicago.tenniscores.com/?mod=nndz-TjJiOWtORzkwTlJFb0NVU1NzOD0%3D&team=nndz-WkNLd3c3N3c%3D",
    "source_league": "APTA_CHICAGO",
    "Scraped At": "2025-09-25T08:36:44.831451"
  },
  {
    "Player ID": "nndz-WlNlNnhiLzhnZz09",
    "First Name": "Keith",
    "Last Name": "Gray",
    "Team": "Winnetka 19",
    "Series": "Series 19",
    "League": "APTA_CHICAGO",
    "Club": "Winnetka 19",
    "PTI": "53.3",
    "Wins": "0",
    "Losses": "0",
    "Win %": "0.0%",
    "Captain": "No",
    "Source URL": "https://aptachicago.tenniscores.com/?mod=nndz-TjJiOWtORzkwTlJFb0NVU1NzOD0%3D&team=nndz-WkNLd3c3N3c%3D",
    "source_league": "APTA_CHICAGO",
    "Scraped At": "2025-09-25T08:36:44.831505"
  },
  {
    "Player ID": "nndz-WkMrK3hMZjZnUT09",
    "First Name": "Brian",
    "Last Name": "Hannah",
    "Team": "Winnetka 19",
    "Series": "Series 19",
    "League": "APTA_CHICAGO",
    "Club": "Winnetka 19",
    "PTI": "52.8",
    "Wins": "0",
    "Losses": "0",
    "Win %": "0.0%",
    "Captain": "No",
    "Source URL": "https://aptachicago.tenniscores.com/?mod=nndz-TjJiOWtORzkwTlJFb0NVU1NzOD0%3D&team=nndz-WkNLd3c3N3c%3D",
    "source_league": "APTA_CHICAGO",
    "Scraped At": "2025-09-25T08:36:44.831547"
  },
  {
    "Player ID": "nndz-WlNlN3liNzZqUT09",
    "First Name": "Adam",
    "Last Name": "Hughes",
    "Team": "Winnetka 19",
    "Series": "Series 19",
    "League": "APTA_CHICAGO",
    "Club": "Winnetka 19",
    "PTI": "46.5",
    "Wins": "0",
    "Losses": "0",
    "Win %": "0.0%",
    "Captain": "No",
    "Source URL": "https://aptachicago.tenniscores.com/?mod=nndz-TjJiOWtORzkwTlJFb0NVU1NzOD0%3D&team=nndz-WkNLd3c3N3c%3D",
    "source_league": "APTA_CHICAGO",
    "Scraped At": "2025-09-25T08:36:44.831592"
  },
  {
    "Player ID": "nndz-WkM2L3dycjloUT09",
    "First Name": "Ryan",
    "Last Name": "Lovell",
    "Team": "Winnetka 19",
    "Series": "Series 19",
    "League": "APTA_CHICAGO",
    "Club": "Winnetka 19",
    "PTI": "48.3",
    "Wins": "0",
    "Losses": "0",
    "Win %": "0.0%",
    "Captain": "No",
    "Source URL": "https://aptachicago.tenniscores.com/?mod=nndz-TjJiOWtORzkwTlJFb0NVU1NzOD0%3D&team=nndz-WkNLd3c3N3c%3D",
    "source_league": "APTA_CHICAGO",
    "Scraped At": "2025-09-25T08:36:44.831637"
  },
  {
    "Player ID": "nndz-WkMrK3hiZjZodz09",
    "First Name": "William",
    "Last Name": "Parke",
    "Team": "Winnetka 19",
    "Series": "Series 19",
    "League": "APTA_CHICAGO",
    "Club": "Winnetka 19",
    "PTI": "50.8",
    "Wins": "0",
    "Losses": "0",
    "Win %": "0.0%",
    "Captain": "No",
    "Source URL": "https://aptachicago.tenniscores.com/?mod=nndz-TjJiOWtORzkwTlJFb0NVU1NzOD0%3D&team=nndz-WkNLd3c3N3c%3D",
    "source_league": "APTA_CHICAGO",
    "Scraped At": "2025-09-25T08:36:44.831679"
  },
  {
    "Player ID": "nndz-WkNHeHg3MytnUT09",
    "First Name": "Michael",
    "Last Name": "Snyder",
    "Team": "Winnetka 19",
    "Series": "Series 19",
    "League": "APTA_CHICAGO",
    "Club": "Winnetka 19",
    "PTI": "52.6",
    "Wins": "0",
    "Losses": "0",
    "Win %": "0.0%",
    "Captain": "No",
    "Source URL": "https://aptachicago.tenniscores.com/?mod=nndz-TjJiOWtORzkwTlJFb0NVU1NzOD0%3D&team=nndz-WkNLd3c3N3c%3D",
    "source_league": "APTA_CHICAGO",
    "Scraped At": "2025-09-25T08:36:44.831721"
  },
  {
    "Player ID": "nndz-WlNlN3hyZjlqUT09",
    "First Name": "Bill",
    "Last Name": "Valasek",
    "Team": "Winnetka 19",
    "Series": "Series 19",
    "League": "APTA_CHICAGO",
    "Club": "Winnetka 19",
    "PTI": "44.5",
    "Wins": "0",
    "Losses": "0",
    "Win %": "0.0%",
    "Captain": "No",
    "Source URL": "https://aptachicago.tenniscores.com/?mod=nndz-TjJiOWtORzkwTlJFb0NVU1NzOD0%3D&team=nndz-WkNLd3c3N3c%3D",
    "source_league": "APTA_CHICAGO",
    "Scraped At": "2025-09-25T08:36:44.831763"
  },
  {
    "Player ID": "nndz-WkNHeHg3ajloZz09",
    "First Name": "Tim",
    "Last Name": "Wheeler",
    "Team": "Winnetka 19",
    "Series": "Series 19",
    "League": "APTA_CHICAGO",
    "Club": "Winnetka 19",
    "PTI": "51.3",
    "Wins": "0",
    "Losses": "0",
    "Win %": "0.0%",
    "Captain": "No",
    "Source URL": "https://aptachicago.tenniscores.com/?mod=nndz-TjJiOWtORzkwTlJFb0NVU1NzOD0%3D&team=nndz-WkNLd3c3N3c%3D",
    "source_league": "APTA_CHICAGO",
    "Scraped At": "2025-09-25T08:36:44.831809"
  }
]