[
  {
    "Player ID": "nndz-WkMreHhMcnhqQT09",
    "First Name": "Phil",
    "Last Name": "Fijal Jr",
    "Team": "Biltmore CC 38",
    "Series": "Series 38",
    "League": "APTA_CHICAGO",
    "Club": "Biltmore CC",
    "PTI": "N/A",
    "Wins": "0",
    "Losses": "0",
    "Win %": "0.0%",
    "Captain": "",
    "Source URL": "https://aptachicago.tenniscores.com/?mod=nndz-TjJiOWtORzkwTlJFb0NVU1NzOD0%3D&team=nndz-WkNDOXliNzU%3D",
    "source_league": "APTA_CHICAGO",
    "Scraped At": "2025-09-16T21:03:28.773045"
  },
  {
    "Player ID": "nndz-WkMrK3dibjdndz09",
    "First Name": "Brian",
    "Last Name": "Rosenburg",
    "Team": "Biltmore CC 38",
    "Series": "Series 38",
    "League": "APTA_CHICAGO",
    "Club": "Biltmore CC 38",
    "PTI": "N/A",
    "Wins": "0",
    "Losses": "0",
    "Win %": "0.0%",
    "Captain": "",
    "Source URL": "https://aptachicago.tenniscores.com/?mod=nndz-TjJiOWtORzkwTlJFb0NVU1NzOD0%3D&team=nndz-WkNDOXliNzU%3D",
    "source_league": "APTA_CHICAGO",
    "Scraped At": "2025-09-16T21:03:28.773126"
  },
  {
    "Player ID": "nndz-WlNlN3lMaitqQT09",
    "First Name": "Peter",
    "Last Name": "Anastasiou",
    "Team": "Biltmore CC 38",
    "Series": "Series 38",
    "League": "APTA_CHICAGO",
    "Club": "Biltmore CC 38",
    "PTI": "N/A",
    "Wins": "0",
    "Losses": "0",
    "Win %": "0.0%",
    "Captain": "",
    "Source URL": "https://aptachicago.tenniscores.com/?mod=nndz-TjJiOWtORzkwTlJFb0NVU1NzOD0%3D&team=nndz-WkNDOXliNzU%3D",
    "source_league": "APTA_CHICAGO",
    "Scraped At": "2025-09-16T21:03:28.773176"
  },
  {
    "Player ID": "nndz-WkMrK3dibjdqQT09",
    "First Name": "Josh",
    "Last Name": "Brown",
    "Team": "Biltmore CC 38",
    "Series": "Series 38",
    "League": "APTA_CHICAGO",
    "Club": "Biltmore CC 38",
    "PTI": "N/A",
    "Wins": "0",
    "Losses": "0",
    "Win %": "0.0%",
    "Captain": "",
    "Source URL": "https://aptachicago.tenniscores.com/?mod=nndz-TjJiOWtORzkwTlJFb0NVU1NzOD0%3D&team=nndz-WkNDOXliNzU%3D",
    "source_league": "APTA_CHICAGO",
    "Scraped At": "2025-09-16T21:03:28.773217"
  },
  {
    "Player ID": "nndz-WlNlN3dyNzdqQT09",
    "First Name": "Mark",
    "Last Name": "Childers",
    "Team": "Biltmore CC 38",
    "Series": "Series 38",
    "League": "APTA_CHICAGO",
    "Club": "Biltmore CC 38",
    "PTI": "64.0",
    "Wins": "0",
    "Losses": "0",
    "Win %": "0.0%",
    "Captain": "",
    "Source URL": "https://aptachicago.tenniscores.com/?mod=nndz-TjJiOWtORzkwTlJFb0NVU1NzOD0%3D&team=nndz-WkNDOXliNzU%3D",
    "source_league": "APTA_CHICAGO",
    "Scraped At": "2025-09-16T21:03:28.773295"
  },
  {
    "Player ID": "nndz-WkMrK3dibjZoUT09",
    "First Name": "Craig",
    "Last Name": "Cook",
    "Team": "Biltmore CC 38",
    "Series": "Series 38",
    "League": "APTA_CHICAGO",
    "Club": "Biltmore CC 38",
    "PTI": "N/A",
    "Wins": "0",
    "Losses": "0",
    "Win %": "0.0%",
    "Captain": "",
    "Source URL": "https://aptachicago.tenniscores.com/?mod=nndz-TjJiOWtORzkwTlJFb0NVU1NzOD0%3D&team=nndz-WkNDOXliNzU%3D",
    "source_league": "APTA_CHICAGO",
    "Scraped At": "2025-09-16T21:03:28.773337"
  },
  {
    "Player ID": "nndz-WkMrK3dibjdnQT09",
    "First Name": "Davin",
    "Last Name": "Engelson",
    "Team": "Biltmore CC 38",
    "Series": "Series 38",
    "League": "APTA_CHICAGO",
    "Club": "Biltmore CC 38",
    "PTI": "78.0",
    "Wins": "0",
    "Losses": "0",
    "Win %": "0.0%",
    "Captain": "",
    "Source URL": "https://aptachicago.tenniscores.com/?mod=nndz-TjJiOWtORzkwTlJFb0NVU1NzOD0%3D&team=nndz-WkNDOXliNzU%3D",
    "source_league": "APTA_CHICAGO",
    "Scraped At": "2025-09-16T21:03:28.773378"
  },
  {
    "Player ID": "nndz-WkMrK3lMNytnQT09",
    "First Name": "Marvin",
    "Last Name": "Husby",
    "Team": "Biltmore CC 38",
    "Series": "Series 38",
    "League": "APTA_CHICAGO",
    "Club": "Biltmore CC 38",
    "PTI": "N/A",
    "Wins": "0",
    "Losses": "0",
    "Win %": "0.0%",
    "Captain": "",
    "Source URL": "https://aptachicago.tenniscores.com/?mod=nndz-TjJiOWtORzkwTlJFb0NVU1NzOD0%3D&team=nndz-WkNDOXliNzU%3D",
    "source_league": "APTA_CHICAGO",
    "Scraped At": "2025-09-16T21:03:28.773422"
  },
  {
    "Player ID": "nndz-WkMrK3dibjdqUT09",
    "First Name": "Jake",
    "Last Name": "Kiser",
    "Team": "Biltmore CC 38",
    "Series": "Series 38",
    "League": "APTA_CHICAGO",
    "Club": "Biltmore CC 38",
    "PTI": "N/A",
    "Wins": "0",
    "Losses": "0",
    "Win %": "0.0%",
    "Captain": "",
    "Source URL": "https://aptachicago.tenniscores.com/?mod=nndz-TjJiOWtORzkwTlJFb0NVU1NzOD0%3D&team=nndz-WkNDOXliNzU%3D",
    "source_league": "APTA_CHICAGO",
    "Scraped At": "2025-09-16T21:03:28.773471"
  },
  {
    "Player ID": "nndz-WkMrK3dibjdoUT09",
    "First Name": "John",
    "Last Name": "Leider",
    "Team": "Biltmore CC 38",
    "Series": "Series 38",
    "League": "APTA_CHICAGO",
    "Club": "Biltmore CC 38",
    "PTI": "N/A",
    "Wins": "0",
    "Losses": "0",
    "Win %": "0.0%",
    "Captain": "",
    "Source URL": "https://aptachicago.tenniscores.com/?mod=nndz-TjJiOWtORzkwTlJFb0NVU1NzOD0%3D&team=nndz-WkNDOXliNzU%3D",
    "source_league": "APTA_CHICAGO",
    "Scraped At": "2025-09-16T21:03:28.773511"
  },
  {
    "Player ID": "nndz-WkMrK3dibjdnUT09",
    "First Name": "Will",
    "Last Name": "McCoy",
    "Team": "Biltmore CC 38",
    "Series": "Series 38",
    "League": "APTA_CHICAGO",
    "Club": "Biltmore CC 38",
    "PTI": "N/A",
    "Wins": "0",
    "Losses": "0",
    "Win %": "0.0%",
    "Captain": "",
    "Source URL": "https://aptachicago.tenniscores.com/?mod=nndz-TjJiOWtORzkwTlJFb0NVU1NzOD0%3D&team=nndz-WkNDOXliNzU%3D",
    "source_league": "APTA_CHICAGO",
    "Scraped At": "2025-09-16T21:03:28.773551"
  },
  {
    "Player ID": "nndz-WkMreHhMN3doQT09",
    "First Name": "Joseph",
    "Last Name": "Messer",
    "Team": "Biltmore CC 38",
    "Series": "Series 38",
    "League": "APTA_CHICAGO",
    "Club": "Biltmore CC 38",
    "PTI": "N/A",
    "Wins": "0",
    "Losses": "0",
    "Win %": "0.0%",
    "Captain": "",
    "Source URL": "https://aptachicago.tenniscores.com/?mod=nndz-TjJiOWtORzkwTlJFb0NVU1NzOD0%3D&team=nndz-WkNDOXliNzU%3D",
    "source_league": "APTA_CHICAGO",
    "Scraped At": "2025-09-16T21:03:28.773592"
  },
  {
    "Player ID": "nndz-WkMrK3dibjdodz09",
    "First Name": "Jay",
    "Last Name": "Schweiger",
    "Team": "Biltmore CC 38",
    "Series": "Series 38",
    "League": "APTA_CHICAGO",
    "Club": "Biltmore CC 38",
    "PTI": "N/A",
    "Wins": "0",
    "Losses": "0",
    "Win %": "0.0%",
    "Captain": "",
    "Source URL": "https://aptachicago.tenniscores.com/?mod=nndz-TjJiOWtORzkwTlJFb0NVU1NzOD0%3D&team=nndz-WkNDOXliNzU%3D",
    "source_league": "APTA_CHICAGO",
    "Scraped At": "2025-09-16T21:03:28.773631"
  },
  {
    "Player ID": "nndz-WkMrK3dibjdoQT09",
    "First Name": "Mike",
    "Last Name": "Seiffer",
    "Team": "Biltmore CC 38",
    "Series": "Series 38",
    "League": "APTA_CHICAGO",
    "Club": "Biltmore CC 38",
    "PTI": "N/A",
    "Wins": "0",
    "Losses": "0",
    "Win %": "0.0%",
    "Captain": "",
    "Source URL": "https://aptachicago.tenniscores.com/?mod=nndz-TjJiOWtORzkwTlJFb0NVU1NzOD0%3D&team=nndz-WkNDOXliNzU%3D",
    "source_league": "APTA_CHICAGO",
    "Scraped At": "2025-09-16T21:03:28.773671"
  },
  {
    "Player ID": "nndz-WkMreHlManhoZz09",
    "First Name": "Mike",
    "Last Name": "Skonie",
    "Team": "Biltmore CC 38",
    "Series": "Series 38",
    "League": "APTA_CHICAGO",
    "Club": "Biltmore CC 38",
    "PTI": "76.2",
    "Wins": "0",
    "Losses": "0",
    "Win %": "0.0%",
    "Captain": "",
    "Source URL": "https://aptachicago.tenniscores.com/?mod=nndz-TjJiOWtORzkwTlJFb0NVU1NzOD0%3D&team=nndz-WkNDOXliNzU%3D",
    "source_league": "APTA_CHICAGO",
    "Scraped At": "2025-09-16T21:03:28.773710"
  },
  {
    "Player ID": "nndz-WkMrK3g3NzVqQT09",
    "First Name": "Ed",
    "Last Name": "Soske",
    "Team": "Biltmore CC 38",
    "Series": "Series 38",
    "League": "APTA_CHICAGO",
    "Club": "Biltmore CC 38",
    "PTI": "N/A",
    "Wins": "0",
    "Losses": "0",
    "Win %": "0.0%",
    "Captain": "",
    "Source URL": "https://aptachicago.tenniscores.com/?mod=nndz-TjJiOWtORzkwTlJFb0NVU1NzOD0%3D&team=nndz-WkNDOXliNzU%3D",
    "source_league": "APTA_CHICAGO",
    "Scraped At": "2025-09-16T21:03:28.773749"
  },
  {
    "Player ID": "nndz-WkMrK3c3NzRoUT09",
    "First Name": "Brett",
    "Last Name": "Stetson",
    "Team": "Biltmore CC 38",
    "Series": "Series 38",
    "League": "APTA_CHICAGO",
    "Club": "Biltmore CC 38",
    "PTI": "N/A",
    "Wins": "0",
    "Losses": "0",
    "Win %": "0.0%",
    "Captain": "",
    "Source URL": "https://aptachicago.tenniscores.com/?mod=nndz-TjJiOWtORzkwTlJFb0NVU1NzOD0%3D&team=nndz-WkNDOXliNzU%3D",
    "source_league": "APTA_CHICAGO",
    "Scraped At": "2025-09-16T21:03:28.773788"
  },
  {
    "Player ID": "nndz-WkMrK3dibjZodz09",
    "First Name": "Mark",
    "Last Name": "Swink",
    "Team": "Biltmore CC 38",
    "Series": "Series 38",
    "League": "APTA_CHICAGO",
    "Club": "Biltmore CC 38",
    "PTI": "71.1",
    "Wins": "0",
    "Losses": "0",
    "Win %": "0.0%",
    "Captain": "",
    "Source URL": "https://aptachicago.tenniscores.com/?mod=nndz-TjJiOWtORzkwTlJFb0NVU1NzOD0%3D&team=nndz-WkNDOXliNzU%3D",
    "source_league": "APTA_CHICAGO",
    "Scraped At": "2025-09-16T21:03:28.773827"
  },
  {
    "Player ID": "nndz-WkMrK3dibjdoZz09",
    "First Name": "Doug",
    "Last Name": "Tomasian",
    "Team": "Biltmore CC 38",
    "Series": "Series 38",
    "League": "APTA_CHICAGO",
    "Club": "Biltmore CC 38",
    "PTI": "N/A",
    "Wins": "0",
    "Losses": "0",
    "Win %": "0.0%",
    "Captain": "",
    "Source URL": "https://aptachicago.tenniscores.com/?mod=nndz-TjJiOWtORzkwTlJFb0NVU1NzOD0%3D&team=nndz-WkNDOXliNzU%3D",
    "source_league": "APTA_CHICAGO",
    "Scraped At": "2025-09-16T21:03:28.773866"
  },
  {
    "Player ID": "nndz-WkMrK3dibjRqQT09",
    "First Name": "John",
    "Last Name": "Yerger",
    "Team": "Biltmore CC 38",
    "Series": "Series 38",
    "League": "APTA_CHICAGO",
    "Club": "Biltmore CC 38",
    "PTI": "78.7",
    "Wins": "0",
    "Losses": "0",
    "Win %": "0.0%",
    "Captain": "",
    "Source URL": "https://aptachicago.tenniscores.com/?mod=nndz-TjJiOWtORzkwTlJFb0NVU1NzOD0%3D&team=nndz-WkNDOXliNzU%3D",
    "source_league": "APTA_CHICAGO",
    "Scraped At": "2025-09-16T21:03:28.773904"
  },
  {
    "Player ID": "nndz-WkMreHhMLzdqQT09",
    "First Name": "David",
    "Last Name": "Zorzy",
    "Team": "Biltmore CC 38",
    "Series": "Series 38",
    "League": "APTA_CHICAGO",
    "Club": "Biltmore CC 38",
    "PTI": "N/A",
    "Wins": "0",
    "Losses": "0",
    "Win %": "0.0%",
    "Captain": "",
    "Source URL": "https://aptachicago.tenniscores.com/?mod=nndz-TjJiOWtORzkwTlJFb0NVU1NzOD0%3D&team=nndz-WkNDOXliNzU%3D",
    "source_league": "APTA_CHICAGO",
    "Scraped At": "2025-09-16T21:03:28.773943"
  },
  {
    "Player ID": "nndz-WkNHeHhyci9nQT09",
    "First Name": "Kenneth",
    "Last Name": "Spero",
    "Team": "Briarwood 38",
    "Series": "Series 38",
    "League": "APTA_CHICAGO",
    "Club": "Briarwood",
    "PTI": "N/A",
    "Wins": "0",
    "Losses": "0",
    "Win %": "0.0%",
    "Captain": "",
    "Source URL": "https://aptachicago.tenniscores.com/?mod=nndz-TjJiOWtORzkwTlJFb0NVU1NzOD0%3D&team=nndz-WkNTNXdiLys%3D",
    "source_league": "APTA_CHICAGO",
    "Scraped At": "2025-09-16T21:03:32.440554"
  },
  {
    "Player ID": "nndz-WlNlNnlMdjVndz09",
    "First Name": "Sam",
    "Last Name": "Block",
    "Team": "Briarwood 38",
    "Series": "Series 38",
    "League": "APTA_CHICAGO",
    "Club": "Briarwood 38",
    "PTI": "65.6",
    "Wins": "0",
    "Losses": "0",
    "Win %": "0.0%",
    "Captain": "",
    "Source URL": "https://aptachicago.tenniscores.com/?mod=nndz-TjJiOWtORzkwTlJFb0NVU1NzOD0%3D&team=nndz-WkNTNXdiLys%3D",
    "source_league": "APTA_CHICAGO",
    "Scraped At": "2025-09-16T21:03:32.440608"
  },
  {
    "Player ID": "nndz-WlNlNndyZitoZz09",
    "First Name": "Jeff",
    "Last Name": "Cohen",
    "Team": "Briarwood 38",
    "Series": "Series 38",
    "League": "APTA_CHICAGO",
    "Club": "Briarwood 38",
    "PTI": "70.2",
    "Wins": "0",
    "Losses": "0",
    "Win %": "0.0%",
    "Captain": "",
    "Source URL": "https://aptachicago.tenniscores.com/?mod=nndz-TjJiOWtORzkwTlJFb0NVU1NzOD0%3D&team=nndz-WkNTNXdiLys%3D",
    "source_league": "APTA_CHICAGO",
    "Scraped At": "2025-09-16T21:03:32.440648"
  },
  {
    "Player ID": "nndz-WlNlNnlMdjVnQT09",
    "First Name": "Max",
    "Last Name": "Fargotstein",
    "Team": "Briarwood 38",
    "Series": "Series 38",
    "League": "APTA_CHICAGO",
    "Club": "Briarwood 38",
    "PTI": "N/A",
    "Wins": "0",
    "Losses": "0",
    "Win %": "0.0%",
    "Captain": "",
    "Source URL": "https://aptachicago.tenniscores.com/?mod=nndz-TjJiOWtORzkwTlJFb0NVU1NzOD0%3D&team=nndz-WkNTNXdiLys%3D",
    "source_league": "APTA_CHICAGO",
    "Scraped At": "2025-09-16T21:03:32.440724"
  },
  {
    "Player ID": "nndz-WkNHeHhyci9qUT09",
    "First Name": "Adam",
    "Last Name": "Goldman",
    "Team": "Briarwood 38",
    "Series": "Series 38",
    "League": "APTA_CHICAGO",
    "Club": "Briarwood 38",
    "PTI": "N/A",
    "Wins": "0",
    "Losses": "0",
    "Win %": "0.0%",
    "Captain": "",
    "Source URL": "https://aptachicago.tenniscores.com/?mod=nndz-TjJiOWtORzkwTlJFb0NVU1NzOD0%3D&team=nndz-WkNTNXdiLys%3D",
    "source_league": "APTA_CHICAGO",
    "Scraped At": "2025-09-16T21:03:32.440765"
  },
  {
    "Player ID": "nndz-WkNHeHhycitoZz09",
    "First Name": "Craig",
    "Last Name": "Goldsmith",
    "Team": "Briarwood 38",
    "Series": "Series 38",
    "League": "APTA_CHICAGO",
    "Club": "Briarwood 38",
    "PTI": "N/A",
    "Wins": "0",
    "Losses": "0",
    "Win %": "0.0%",
    "Captain": "",
    "Source URL": "https://aptachicago.tenniscores.com/?mod=nndz-TjJiOWtORzkwTlJFb0NVU1NzOD0%3D&team=nndz-WkNTNXdiLys%3D",
    "source_league": "APTA_CHICAGO",
    "Scraped At": "2025-09-16T21:03:32.440801"
  },
  {
    "Player ID": "nndz-WlNlNnhiei9qQT09",
    "First Name": "Brett",
    "Last Name": "Leviton",
    "Team": "Briarwood 38",
    "Series": "Series 38",
    "League": "APTA_CHICAGO",
    "Club": "Briarwood 38",
    "PTI": "77.4",
    "Wins": "0",
    "Losses": "0",
    "Win %": "0.0%",
    "Captain": "",
    "Source URL": "https://aptachicago.tenniscores.com/?mod=nndz-TjJiOWtORzkwTlJFb0NVU1NzOD0%3D&team=nndz-WkNTNXdiLys%3D",
    "source_league": "APTA_CHICAGO",
    "Scraped At": "2025-09-16T21:03:32.440847"
  },
  {
    "Player ID": "nndz-WkNPd3libjVqUT09",
    "First Name": "Robert",
    "Last Name": "M. Lehrman",
    "Team": "Briarwood 38",
    "Series": "Series 38",
    "League": "APTA_CHICAGO",
    "Club": "Briarwood 38",
    "PTI": "N/A",
    "Wins": "0",
    "Losses": "0",
    "Win %": "0.0%",
    "Captain": "",
    "Source URL": "https://aptachicago.tenniscores.com/?mod=nndz-TjJiOWtORzkwTlJFb0NVU1NzOD0%3D&team=nndz-WkNTNXdiLys%3D",
    "source_league": "APTA_CHICAGO",
    "Scraped At": "2025-09-16T21:03:32.440888"
  },
  {
    "Player ID": "nndz-WkMrK3hyNzdqQT09",
    "First Name": "Bradley",
    "Last Name": "Mandel",
    "Team": "Briarwood 38",
    "Series": "Series 38",
    "League": "APTA_CHICAGO",
    "Club": "Briarwood 38",
    "PTI": "62.3",
    "Wins": "0",
    "Losses": "0",
    "Win %": "0.0%",
    "Captain": "",
    "Source URL": "https://aptachicago.tenniscores.com/?mod=nndz-TjJiOWtORzkwTlJFb0NVU1NzOD0%3D&team=nndz-WkNTNXdiLys%3D",
    "source_league": "APTA_CHICAGO",
    "Scraped At": "2025-09-16T21:03:32.440924"
  },
  {
    "Player ID": "nndz-WkNDOHhMeitnZz09",
    "First Name": "Greg",
    "Last Name": "Moyer",
    "Team": "Briarwood 38",
    "Series": "Series 38",
    "League": "APTA_CHICAGO",
    "Club": "Briarwood 38",
    "PTI": "N/A",
    "Wins": "0",
    "Losses": "0",
    "Win %": "0.0%",
    "Captain": "",
    "Source URL": "https://aptachicago.tenniscores.com/?mod=nndz-TjJiOWtORzkwTlJFb0NVU1NzOD0%3D&team=nndz-WkNTNXdiLys%3D",
    "source_league": "APTA_CHICAGO",
    "Scraped At": "2025-09-16T21:03:32.440965"
  },
  {
    "Player ID": "nndz-WlNlNndyZitndz09",
    "First Name": "Rob",
    "Last Name": "Nadler",
    "Team": "Briarwood 38",
    "Series": "Series 38",
    "League": "APTA_CHICAGO",
    "Club": "Briarwood 38",
    "PTI": "N/A",
    "Wins": "0",
    "Losses": "0",
    "Win %": "0.0%",
    "Captain": "",
    "Source URL": "https://aptachicago.tenniscores.com/?mod=nndz-TjJiOWtORzkwTlJFb0NVU1NzOD0%3D&team=nndz-WkNTNXdiLys%3D",
    "source_league": "APTA_CHICAGO",
    "Scraped At": "2025-09-16T21:03:32.441010"
  },
  {
    "Player ID": "nndz-WlNlNndyZitodz09",
    "First Name": "Max",
    "Last Name": "Resnick",
    "Team": "Briarwood 38",
    "Series": "Series 38",
    "League": "APTA_CHICAGO",
    "Club": "Briarwood 38",
    "PTI": "69.8",
    "Wins": "0",
    "Losses": "0",
    "Win %": "0.0%",
    "Captain": "",
    "Source URL": "https://aptachicago.tenniscores.com/?mod=nndz-TjJiOWtORzkwTlJFb0NVU1NzOD0%3D&team=nndz-WkNTNXdiLys%3D",
    "source_league": "APTA_CHICAGO",
    "Scraped At": "2025-09-16T21:03:32.441046"
  },
  {
    "Player ID": "nndz-WkM2L3g3andqQT09",
    "First Name": "Brian",
    "Last Name": "Ruben",
    "Team": "Briarwood 38",
    "Series": "Series 38",
    "League": "APTA_CHICAGO",
    "Club": "Briarwood 38",
    "PTI": "73.4",
    "Wins": "0",
    "Losses": "0",
    "Win %": "0.0%",
    "Captain": "",
    "Source URL": "https://aptachicago.tenniscores.com/?mod=nndz-TjJiOWtORzkwTlJFb0NVU1NzOD0%3D&team=nndz-WkNTNXdiLys%3D",
    "source_league": "APTA_CHICAGO",
    "Scraped At": "2025-09-16T21:03:32.441087"
  },
  {
    "Player ID": "nndz-WkMrK3hyNzRoQT09",
    "First Name": "Aaron",
    "Last Name": "Zeid",
    "Team": "Briarwood 38",
    "Series": "Series 38",
    "League": "APTA_CHICAGO",
    "Club": "Briarwood 38",
    "PTI": "79.1",
    "Wins": "0",
    "Losses": "0",
    "Win %": "0.0%",
    "Captain": "",
    "Source URL": "https://aptachicago.tenniscores.com/?mod=nndz-TjJiOWtORzkwTlJFb0NVU1NzOD0%3D&team=nndz-WkNTNXdiLys%3D",
    "source_league": "APTA_CHICAGO",
    "Scraped At": "2025-09-16T21:03:32.441128"
  },
  {
    "Player ID": "nndz-WlNlNng3Ly9odz09",
    "First Name": "John",
    "Last Name": "Zukin",
    "Team": "Briarwood 38",
    "Series": "Series 38",
    "League": "APTA_CHICAGO",
    "Club": "Briarwood 38",
    "PTI": "64.1",
    "Wins": "0",
    "Losses": "0",
    "Win %": "0.0%",
    "Captain": "",
    "Source URL": "https://aptachicago.tenniscores.com/?mod=nndz-TjJiOWtORzkwTlJFb0NVU1NzOD0%3D&team=nndz-WkNTNXdiLys%3D",
    "source_league": "APTA_CHICAGO",
    "Scraped At": "2025-09-16T21:03:32.441180"
  },
  {
    "Player ID": "nndz-WkM2L3dyZjhnQT09",
    "First Name": "Peter",
    "Last Name": "Hulick",
    "Team": "Glen View 38",
    "Series": "Series 38",
    "League": "APTA_CHICAGO",
    "Club": "Glen View",
    "PTI": "77.0",
    "Wins": "0",
    "Losses": "0",
    "Win %": "0.0%",
    "Captain": "",
    "Source URL": "https://aptachicago.tenniscores.com/?mod=nndz-TjJiOWtORzkwTlJFb0NVU1NzOD0%3D&team=nndz-WkNPOHhyYnc%3D",
    "source_league": "APTA_CHICAGO",
    "Scraped At": "2025-09-16T21:03:39.354792"
  },
  {
    "Player ID": "nndz-WkM2L3dyZjhnUT09",
    "First Name": "Greg",
    "Last Name": "Frezados",
    "Team": "Glen View 38",
    "Series": "Series 38",
    "League": "APTA_CHICAGO",
    "Club": "Glen View 38",
    "PTI": "N/A",
    "Wins": "0",
    "Losses": "0",
    "Win %": "0.0%",
    "Captain": "",
    "Source URL": "https://aptachicago.tenniscores.com/?mod=nndz-TjJiOWtORzkwTlJFb0NVU1NzOD0%3D&team=nndz-WkNPOHhyYnc%3D",
    "source_league": "APTA_CHICAGO",
    "Scraped At": "2025-09-16T21:03:39.354848"
  },
  {
    "Player ID": "nndz-WlNlN3hyLzRoUT09",
    "First Name": "Brandon",
    "Last Name": "Barela",
    "Team": "Glen View 38",
    "Series": "Series 38",
    "League": "APTA_CHICAGO",
    "Club": "Glen View 38",
    "PTI": "N/A",
    "Wins": "0",
    "Losses": "0",
    "Win %": "0.0%",
    "Captain": "",
    "Source URL": "https://aptachicago.tenniscores.com/?mod=nndz-TjJiOWtORzkwTlJFb0NVU1NzOD0%3D&team=nndz-WkNPOHhyYnc%3D",
    "source_league": "APTA_CHICAGO",
    "Scraped At": "2025-09-16T21:03:39.354897"
  },
  {
    "Player ID": "nndz-WlNlN3hydi9oUT09",
    "First Name": "Wicks",
    "Last Name": "Barkhausen",
    "Team": "Glen View 38",
    "Series": "Series 38",
    "League": "APTA_CHICAGO",
    "Club": "Glen View 38",
    "PTI": "71.7",
    "Wins": "0",
    "Losses": "0",
    "Win %": "0.0%",
    "Captain": "",
    "Source URL": "https://aptachicago.tenniscores.com/?mod=nndz-TjJiOWtORzkwTlJFb0NVU1NzOD0%3D&team=nndz-WkNPOHhyYnc%3D",
    "source_league": "APTA_CHICAGO",
    "Scraped At": "2025-09-16T21:03:39.354939"
  },
  {
    "Player ID": "nndz-WkM2eHdyNytnUT09",
    "First Name": "Ed",
    "Last Name": "Keller",
    "Team": "Glen View 38",
    "Series": "Series 38",
    "League": "APTA_CHICAGO",
    "Club": "Glen View 38",
    "PTI": "N/A",
    "Wins": "0",
    "Losses": "0",
    "Win %": "0.0%",
    "Captain": "",
    "Source URL": "https://aptachicago.tenniscores.com/?mod=nndz-TjJiOWtORzkwTlJFb0NVU1NzOD0%3D&team=nndz-WkNPOHhyYnc%3D",
    "source_league": "APTA_CHICAGO",
    "Scraped At": "2025-09-16T21:03:39.354980"
  },
  {
    "Player ID": "nndz-WkM2L3dyZi9ndz09",
    "First Name": "John",
    "Last Name": "Kinahan",
    "Team": "Glen View 38",
    "Series": "Series 38",
    "League": "APTA_CHICAGO",
    "Club": "Glen View 38",
    "PTI": "N/A",
    "Wins": "0",
    "Losses": "0",
    "Win %": "0.0%",
    "Captain": "",
    "Source URL": "https://aptachicago.tenniscores.com/?mod=nndz-TjJiOWtORzkwTlJFb0NVU1NzOD0%3D&team=nndz-WkNPOHhyYnc%3D",
    "source_league": "APTA_CHICAGO",
    "Scraped At": "2025-09-16T21:03:39.355020"
  },
  {
    "Player ID": "nndz-WkMrK3hyenhodz09",
    "First Name": "Chris",
    "Last Name": "McKee",
    "Team": "Glen View 38",
    "Series": "Series 38",
    "League": "APTA_CHICAGO",
    "Club": "Glen View 38",
    "PTI": "N/A",
    "Wins": "0",
    "Losses": "0",
    "Win %": "0.0%",
    "Captain": "",
    "Source URL": "https://aptachicago.tenniscores.com/?mod=nndz-TjJiOWtORzkwTlJFb0NVU1NzOD0%3D&team=nndz-WkNPOHhyYnc%3D",
    "source_league": "APTA_CHICAGO",
    "Scraped At": "2025-09-16T21:03:39.355060"
  },
  {
    "Player ID": "nndz-WkNDOHg3M3hoUT09",
    "First Name": "Martin",
    "Last Name": "Podorsky",
    "Team": "Glen View 38",
    "Series": "Series 38",
    "League": "APTA_CHICAGO",
    "Club": "Glen View 38",
    "PTI": "N/A",
    "Wins": "0",
    "Losses": "0",
    "Win %": "0.0%",
    "Captain": "",
    "Source URL": "https://aptachicago.tenniscores.com/?mod=nndz-TjJiOWtORzkwTlJFb0NVU1NzOD0%3D&team=nndz-WkNPOHhyYnc%3D",
    "source_league": "APTA_CHICAGO",
    "Scraped At": "2025-09-16T21:03:39.355099"
  },
  {
    "Player ID": "nndz-WkM2L3hiMzVqQT09",
    "First Name": "Gordon",
    "Last Name": "Rahr",
    "Team": "Glen View 38",
    "Series": "Series 38",
    "League": "APTA_CHICAGO",
    "Club": "Glen View 38",
    "PTI": "N/A",
    "Wins": "0",
    "Losses": "0",
    "Win %": "0.0%",
    "Captain": "",
    "Source URL": "https://aptachicago.tenniscores.com/?mod=nndz-TjJiOWtORzkwTlJFb0NVU1NzOD0%3D&team=nndz-WkNPOHhyYnc%3D",
    "source_league": "APTA_CHICAGO",
    "Scraped At": "2025-09-16T21:03:39.355170"
  },
  {
    "Player ID": "nndz-WlNlN3lMcndqUT09",
    "First Name": "Cooper",
    "Last Name": "Rebhun",
    "Team": "Glen View 38",
    "Series": "Series 38",
    "League": "APTA_CHICAGO",
    "Club": "Glen View 38",
    "PTI": "N/A",
    "Wins": "0",
    "Losses": "0",
    "Win %": "0.0%",
    "Captain": "",
    "Source URL": "https://aptachicago.tenniscores.com/?mod=nndz-TjJiOWtORzkwTlJFb0NVU1NzOD0%3D&team=nndz-WkNPOHhyYnc%3D",
    "source_league": "APTA_CHICAGO",
    "Scraped At": "2025-09-16T21:03:39.355211"
  },
  {
    "Player ID": "nndz-WkM2L3dyZi9oUT09",
    "First Name": "Matt",
    "Last Name": "Schlatter",
    "Team": "Glen View 38",
    "Series": "Series 38",
    "League": "APTA_CHICAGO",
    "Club": "Glen View 38",
    "PTI": "N/A",
    "Wins": "0",
    "Losses": "0",
    "Win %": "0.0%",
    "Captain": "",
    "Source URL": "https://aptachicago.tenniscores.com/?mod=nndz-TjJiOWtORzkwTlJFb0NVU1NzOD0%3D&team=nndz-WkNPOHhyYnc%3D",
    "source_league": "APTA_CHICAGO",
    "Scraped At": "2025-09-16T21:03:39.355252"
  },
  {
    "Player ID": "nndz-WlNlN3liM3hnZz09",
    "First Name": "Chris",
    "Last Name": "Sipe",
    "Team": "Glen View 38",
    "Series": "Series 38",
    "League": "APTA_CHICAGO",
    "Club": "Glen View 38",
    "PTI": "N/A",
    "Wins": "0",
    "Losses": "0",
    "Win %": "0.0%",
    "Captain": "",
    "Source URL": "https://aptachicago.tenniscores.com/?mod=nndz-TjJiOWtORzkwTlJFb0NVU1NzOD0%3D&team=nndz-WkNPOHhyYnc%3D",
    "source_league": "APTA_CHICAGO",
    "Scraped At": "2025-09-16T21:03:39.355298"
  },
  {
    "Player ID": "nndz-WkMreHdyZitnQT09",
    "First Name": "Jamie",
    "Last Name": "Whiteman",
    "Team": "Glen View 38",
    "Series": "Series 38",
    "League": "APTA_CHICAGO",
    "Club": "Glen View 38",
    "PTI": "68.3",
    "Wins": "0",
    "Losses": "0",
    "Win %": "0.0%",
    "Captain": "",
    "Source URL": "https://aptachicago.tenniscores.com/?mod=nndz-TjJiOWtORzkwTlJFb0NVU1NzOD0%3D&team=nndz-WkNPOHhyYnc%3D",
    "source_league": "APTA_CHICAGO",
    "Scraped At": "2025-09-16T21:03:39.355345"
  },
  {
    "Player ID": "nndz-WkM2L3hiMzRqUT09",
    "First Name": "Kees",
    "Last Name": "Woodward",
    "Team": "Glen View 38",
    "Series": "Series 38",
    "League": "APTA_CHICAGO",
    "Club": "Glen View 38",
    "PTI": "N/A",
    "Wins": "0",
    "Losses": "0",
    "Win %": "0.0%",
    "Captain": "",
    "Source URL": "https://aptachicago.tenniscores.com/?mod=nndz-TjJiOWtORzkwTlJFb0NVU1NzOD0%3D&team=nndz-WkNPOHhyYnc%3D",
    "source_league": "APTA_CHICAGO",
    "Scraped At": "2025-09-16T21:03:39.355385"
  },
  {
    "Player ID": "nndz-WkNHeHdMaitoUT09",
    "First Name": "Keith",
    "Last Name": "Harris",
    "Team": "Lake Bluff 38",
    "Series": "Series 38",
    "League": "APTA_CHICAGO",
    "Club": "Lake Bluff",
    "PTI": "75.1",
    "Wins": "0",
    "Losses": "0",
    "Win %": "0.0%",
    "Captain": "",
    "Source URL": "https://aptachicago.tenniscores.com/?mod=nndz-TjJiOWtORzkwTlJFb0NVU1NzOD0%3D&team=nndz-WkNLd3c3MzQ%3D",
    "source_league": "APTA_CHICAGO",
    "Scraped At": "2025-09-16T21:03:42.705070"
  },
  {
    "Player ID": "nndz-WkMrK3dyMy9nUT09",
    "First Name": "Patrick",
    "Last Name": "Sassen",
    "Team": "Lake Bluff 38",
    "Series": "Series 38",
    "League": "APTA_CHICAGO",
    "Club": "Lake Bluff 38",
    "PTI": "N/A",
    "Wins": "0",
    "Losses": "0",
    "Win %": "0.0%",
    "Captain": "",
    "Source URL": "https://aptachicago.tenniscores.com/?mod=nndz-TjJiOWtORzkwTlJFb0NVU1NzOD0%3D&team=nndz-WkNLd3c3MzQ%3D",
    "source_league": "APTA_CHICAGO",
    "Scraped At": "2025-09-16T21:03:42.705128"
  },
  {
    "Player ID": "nndz-WlNlNnhiendqUT09",
    "First Name": "Lance",
    "Last Name": "Cook",
    "Team": "Lake Bluff 38",
    "Series": "Series 38",
    "League": "APTA_CHICAGO",
    "Club": "Lake Bluff 38",
    "PTI": "N/A",
    "Wins": "0",
    "Losses": "0",
    "Win %": "0.0%",
    "Captain": "",
    "Source URL": "https://aptachicago.tenniscores.com/?mod=nndz-TjJiOWtORzkwTlJFb0NVU1NzOD0%3D&team=nndz-WkNLd3c3MzQ%3D",
    "source_league": "APTA_CHICAGO",
    "Scraped At": "2025-09-16T21:03:42.705176"
  },
  {
    "Player ID": "nndz-WlNlNndydndoUT09",
    "First Name": "Michael",
    "Last Name": "Costabile",
    "Team": "Lake Bluff 38",
    "Series": "Series 38",
    "League": "APTA_CHICAGO",
    "Club": "Lake Bluff 38",
    "PTI": "N/A",
    "Wins": "0",
    "Losses": "0",
    "Win %": "0.0%",
    "Captain": "",
    "Source URL": "https://aptachicago.tenniscores.com/?mod=nndz-TjJiOWtORzkwTlJFb0NVU1NzOD0%3D&team=nndz-WkNLd3c3MzQ%3D",
    "source_league": "APTA_CHICAGO",
    "Scraped At": "2025-09-16T21:03:42.705217"
  },
  {
    "Player ID": "nndz-WkMrK3hMbjRoQT09",
    "First Name": "Matt",
    "Last Name": "Gaines",
    "Team": "Lake Bluff 38",
    "Series": "Series 38",
    "League": "APTA_CHICAGO",
    "Club": "Lake Bluff 38",
    "PTI": "N/A",
    "Wins": "0",
    "Losses": "0",
    "Win %": "0.0%",
    "Captain": "",
    "Source URL": "https://aptachicago.tenniscores.com/?mod=nndz-TjJiOWtORzkwTlJFb0NVU1NzOD0%3D&team=nndz-WkNLd3c3MzQ%3D",
    "source_league": "APTA_CHICAGO",
    "Scraped At": "2025-09-16T21:03:42.705259"
  },
  {
    "Player ID": "nndz-WkM2OHhyMzhoZz09",
    "First Name": "Davoud",
    "Last Name": "Khorzad",
    "Team": "Lake Bluff 38",
    "Series": "Series 38",
    "League": "APTA_CHICAGO",
    "Club": "Lake Bluff 38",
    "PTI": "80.6",
    "Wins": "0",
    "Losses": "0",
    "Win %": "0.0%",
    "Captain": "",
    "Source URL": "https://aptachicago.tenniscores.com/?mod=nndz-TjJiOWtORzkwTlJFb0NVU1NzOD0%3D&team=nndz-WkNLd3c3MzQ%3D",
    "source_league": "APTA_CHICAGO",
    "Scraped At": "2025-09-16T21:03:42.705301"
  },
  {
    "Player ID": "nndz-WkM2OHg3djRoQT09",
    "First Name": "Scott",
    "Last Name": "McCallum",
    "Team": "Lake Bluff 38",
    "Series": "Series 38",
    "League": "APTA_CHICAGO",
    "Club": "Lake Bluff 38",
    "PTI": "80.0",
    "Wins": "0",
    "Losses": "0",
    "Win %": "0.0%",
    "Captain": "",
    "Source URL": "https://aptachicago.tenniscores.com/?mod=nndz-TjJiOWtORzkwTlJFb0NVU1NzOD0%3D&team=nndz-WkNLd3c3MzQ%3D",
    "source_league": "APTA_CHICAGO",
    "Scraped At": "2025-09-16T21:03:42.705341"
  },
  {
    "Player ID": "nndz-WlNlNndydnhodz09",
    "First Name": "Mark",
    "Last Name": "Morrison",
    "Team": "Lake Bluff 38",
    "Series": "Series 38",
    "League": "APTA_CHICAGO",
    "Club": "Lake Bluff 38",
    "PTI": "N/A",
    "Wins": "0",
    "Losses": "0",
    "Win %": "0.0%",
    "Captain": "",
    "Source URL": "https://aptachicago.tenniscores.com/?mod=nndz-TjJiOWtORzkwTlJFb0NVU1NzOD0%3D&team=nndz-WkNLd3c3MzQ%3D",
    "source_league": "APTA_CHICAGO",
    "Scraped At": "2025-09-16T21:03:42.705381"
  },
  {
    "Player ID": "nndz-WkNHeHdMaitodz09",
    "First Name": "Stuart",
    "Last Name": "Poulton",
    "Team": "Lake Bluff 38",
    "Series": "Series 38",
    "League": "APTA_CHICAGO",
    "Club": "Lake Bluff 38",
    "PTI": "80.6",
    "Wins": "0",
    "Losses": "0",
    "Win %": "0.0%",
    "Captain": "",
    "Source URL": "https://aptachicago.tenniscores.com/?mod=nndz-TjJiOWtORzkwTlJFb0NVU1NzOD0%3D&team=nndz-WkNLd3c3MzQ%3D",
    "source_league": "APTA_CHICAGO",
    "Scraped At": "2025-09-16T21:03:42.705420"
  },
  {
    "Player ID": "nndz-WkMrK3dyendoQT09",
    "First Name": "Patrick",
    "Last Name": "Regan",
    "Team": "Lake Bluff 38",
    "Series": "Series 38",
    "League": "APTA_CHICAGO",
    "Club": "Lake Bluff 38",
    "PTI": "N/A",
    "Wins": "0",
    "Losses": "0",
    "Win %": "0.0%",
    "Captain": "",
    "Source URL": "https://aptachicago.tenniscores.com/?mod=nndz-TjJiOWtORzkwTlJFb0NVU1NzOD0%3D&team=nndz-WkNLd3c3MzQ%3D",
    "source_league": "APTA_CHICAGO",
    "Scraped At": "2025-09-16T21:03:42.705460"
  },
  {
    "Player ID": "nndz-WkNPd3lMdjdndz09",
    "First Name": "Jeff",
    "Last Name": "Soukup",
    "Team": "Lake Bluff 38",
    "Series": "Series 38",
    "League": "APTA_CHICAGO",
    "Club": "Lake Bluff 38",
    "PTI": "82.5",
    "Wins": "0",
    "Losses": "0",
    "Win %": "0.0%",
    "Captain": "",
    "Source URL": "https://aptachicago.tenniscores.com/?mod=nndz-TjJiOWtORzkwTlJFb0NVU1NzOD0%3D&team=nndz-WkNLd3c3MzQ%3D",
    "source_league": "APTA_CHICAGO",
    "Scraped At": "2025-09-16T21:03:42.705500"
  },
  {
    "Player ID": "nndz-WkMrK3c3bjlqUT09",
    "First Name": "Stephen",
    "Last Name": "Balawajder",
    "Team": "Michigan Shores 38",
    "Series": "Series 38",
    "League": "APTA_CHICAGO",
    "Club": "Michigan Shores",
    "PTI": "60.7",
    "Wins": "0",
    "Losses": "0",
    "Win %": "0.0%",
    "Captain": "",
    "Source URL": "https://aptachicago.tenniscores.com/?mod=nndz-TjJiOWtORzkwTlJFb0NVU1NzOD0%3D&team=nndz-WkNTNXdiMzc%3D",
    "source_league": "APTA_CHICAGO",
    "Scraped At": "2025-09-16T21:03:46.933427"
  },
  {
    "Player ID": "nndz-WkM2L3g3LzloZz09",
    "First Name": "Tom",
    "Last Name": "O'Gara",
    "Team": "Michigan Shores 38",
    "Series": "Series 38",
    "League": "APTA_CHICAGO",
    "Club": "Michigan Shores 38",
    "PTI": "57.5",
    "Wins": "0",
    "Losses": "0",
    "Win %": "0.0%",
    "Captain": "",
    "Source URL": "https://aptachicago.tenniscores.com/?mod=nndz-TjJiOWtORzkwTlJFb0NVU1NzOD0%3D&team=nndz-WkNTNXdiMzc%3D",
    "source_league": "APTA_CHICAGO",
    "Scraped At": "2025-09-16T21:03:46.933492"
  },
  {
    "Player ID": "nndz-WkNDOXc3djRqQT09",
    "First Name": "Aric",
    "Last Name": "Bednar",
    "Team": "Michigan Shores 38",
    "Series": "Series 38",
    "League": "APTA_CHICAGO",
    "Club": "Michigan Shores 38",
    "PTI": "N/A",
    "Wins": "0",
    "Losses": "0",
    "Win %": "0.0%",
    "Captain": "",
    "Source URL": "https://aptachicago.tenniscores.com/?mod=nndz-TjJiOWtORzkwTlJFb0NVU1NzOD0%3D&team=nndz-WkNTNXdiMzc%3D",
    "source_league": "APTA_CHICAGO",
    "Scraped At": "2025-09-16T21:03:46.933631"
  },
  {
    "Player ID": "nndz-WkNPd3lMbjVoQT09",
    "First Name": "Greg",
    "Last Name": "Beitel",
    "Team": "Michigan Shores 38",
    "Series": "Series 38",
    "League": "APTA_CHICAGO",
    "Club": "Michigan Shores 38",
    "PTI": "71.9",
    "Wins": "0",
    "Losses": "0",
    "Win %": "0.0%",
    "Captain": "",
    "Source URL": "https://aptachicago.tenniscores.com/?mod=nndz-TjJiOWtORzkwTlJFb0NVU1NzOD0%3D&team=nndz-WkNTNXdiMzc%3D",
    "source_league": "APTA_CHICAGO",
    "Scraped At": "2025-09-16T21:03:46.933683"
  },
  {
    "Player ID": "nndz-WlNlN3g3LzZoZz09",
    "First Name": "Edwin",
    "Last Name": "Bender",
    "Team": "Michigan Shores 38",
    "Series": "Series 38",
    "League": "APTA_CHICAGO",
    "Club": "Michigan Shores 38",
    "PTI": "64.0",
    "Wins": "0",
    "Losses": "0",
    "Win %": "0.0%",
    "Captain": "",
    "Source URL": "https://aptachicago.tenniscores.com/?mod=nndz-TjJiOWtORzkwTlJFb0NVU1NzOD0%3D&team=nndz-WkNTNXdiMzc%3D",
    "source_league": "APTA_CHICAGO",
    "Scraped At": "2025-09-16T21:03:46.933743"
  },
  {
    "Player ID": "nndz-WkMrK3hyZjVoZz09",
    "First Name": "Drew",
    "Last Name": "Buckley",
    "Team": "Michigan Shores 38",
    "Series": "Series 38",
    "League": "APTA_CHICAGO",
    "Club": "Michigan Shores 38",
    "PTI": "N/A",
    "Wins": "0",
    "Losses": "0",
    "Win %": "0.0%",
    "Captain": "",
    "Source URL": "https://aptachicago.tenniscores.com/?mod=nndz-TjJiOWtORzkwTlJFb0NVU1NzOD0%3D&team=nndz-WkNTNXdiMzc%3D",
    "source_league": "APTA_CHICAGO",
    "Scraped At": "2025-09-16T21:03:46.933788"
  },
  {
    "Player ID": "nndz-WlNlN3g3eitoUT09",
    "First Name": "Scott",
    "Last Name": "Christie",
    "Team": "Michigan Shores 38",
    "Series": "Series 38",
    "League": "APTA_CHICAGO",
    "Club": "Michigan Shores 38",
    "PTI": "66.9",
    "Wins": "0",
    "Losses": "0",
    "Win %": "0.0%",
    "Captain": "",
    "Source URL": "https://aptachicago.tenniscores.com/?mod=nndz-TjJiOWtORzkwTlJFb0NVU1NzOD0%3D&team=nndz-WkNTNXdiMzc%3D",
    "source_league": "APTA_CHICAGO",
    "Scraped At": "2025-09-16T21:03:46.933901"
  },
  {
    "Player ID": "nndz-WlNlN3g3ejZqQT09",
    "First Name": "Tim",
    "Last Name": "Epstein",
    "Team": "Michigan Shores 38",
    "Series": "Series 38",
    "League": "APTA_CHICAGO",
    "Club": "Michigan Shores 38",
    "PTI": "71.2",
    "Wins": "0",
    "Losses": "0",
    "Win %": "0.0%",
    "Captain": "",
    "Source URL": "https://aptachicago.tenniscores.com/?mod=nndz-TjJiOWtORzkwTlJFb0NVU1NzOD0%3D&team=nndz-WkNTNXdiMzc%3D",
    "source_league": "APTA_CHICAGO",
    "Scraped At": "2025-09-16T21:03:46.933954"
  },
  {
    "Player ID": "nndz-WlNlN3c3ajRnQT09",
    "First Name": "Ian",
    "Last Name": "R. Fisher",
    "Team": "Michigan Shores 38",
    "Series": "Series 38",
    "League": "APTA_CHICAGO",
    "Club": "Michigan Shores 38",
    "PTI": "93.3",
    "Wins": "0",
    "Losses": "0",
    "Win %": "0.0%",
    "Captain": "",
    "Source URL": "https://aptachicago.tenniscores.com/?mod=nndz-TjJiOWtORzkwTlJFb0NVU1NzOD0%3D&team=nndz-WkNTNXdiMzc%3D",
    "source_league": "APTA_CHICAGO",
    "Scraped At": "2025-09-16T21:03:46.933994"
  },
  {
    "Player ID": "nndz-WlNlN3hyMzRnQT09",
    "First Name": "Matthew",
    "Last Name": "Fitzpatrick",
    "Team": "Michigan Shores 38",
    "Series": "Series 38",
    "League": "APTA_CHICAGO",
    "Club": "Michigan Shores 38",
    "PTI": "82.7",
    "Wins": "0",
    "Losses": "0",
    "Win %": "0.0%",
    "Captain": "",
    "Source URL": "https://aptachicago.tenniscores.com/?mod=nndz-TjJiOWtORzkwTlJFb0NVU1NzOD0%3D&team=nndz-WkNTNXdiMzc%3D",
    "source_league": "APTA_CHICAGO",
    "Scraped At": "2025-09-16T21:03:46.934036"
  },
  {
    "Player ID": "nndz-WkM2L3dMMzhoUT09",
    "First Name": "Patrick",
    "Last Name": "Hanna",
    "Team": "Michigan Shores 38",
    "Series": "Series 38",
    "League": "APTA_CHICAGO",
    "Club": "Michigan Shores 38",
    "PTI": "N/A",
    "Wins": "0",
    "Losses": "0",
    "Win %": "0.0%",
    "Captain": "",
    "Source URL": "https://aptachicago.tenniscores.com/?mod=nndz-TjJiOWtORzkwTlJFb0NVU1NzOD0%3D&team=nndz-WkNTNXdiMzc%3D",
    "source_league": "APTA_CHICAGO",
    "Scraped At": "2025-09-16T21:03:46.934081"
  },
  {
    "Player ID": "nndz-WkM2L3c3YjVoUT09",
    "First Name": "Dan",
    "Last Name": "Harrison",
    "Team": "Michigan Shores 38",
    "Series": "Series 38",
    "League": "APTA_CHICAGO",
    "Club": "Michigan Shores 38",
    "PTI": "N/A",
    "Wins": "0",
    "Losses": "0",
    "Win %": "0.0%",
    "Captain": "",
    "Source URL": "https://aptachicago.tenniscores.com/?mod=nndz-TjJiOWtORzkwTlJFb0NVU1NzOD0%3D&team=nndz-WkNTNXdiMzc%3D",
    "source_league": "APTA_CHICAGO",
    "Scraped At": "2025-09-16T21:03:46.934128"
  },
  {
    "Player ID": "nndz-WlNlN3hMZjZnUT09",
    "First Name": "Dan",
    "Last Name": "Johnson",
    "Team": "Michigan Shores 38",
    "Series": "Series 38",
    "League": "APTA_CHICAGO",
    "Club": "Michigan Shores 38",
    "PTI": "N/A",
    "Wins": "0",
    "Losses": "0",
    "Win %": "0.0%",
    "Captain": "",
    "Source URL": "https://aptachicago.tenniscores.com/?mod=nndz-TjJiOWtORzkwTlJFb0NVU1NzOD0%3D&team=nndz-WkNTNXdiMzc%3D",
    "source_league": "APTA_CHICAGO",
    "Scraped At": "2025-09-16T21:03:46.934174"
  },
  {
    "Player ID": "nndz-WlNlN3hMZjdoUT09",
    "First Name": "Patrick",
    "Last Name": "McAuliffe",
    "Team": "Michigan Shores 38",
    "Series": "Series 38",
    "League": "APTA_CHICAGO",
    "Club": "Michigan Shores 38",
    "PTI": "71.8",
    "Wins": "0",
    "Losses": "0",
    "Win %": "0.0%",
    "Captain": "",
    "Source URL": "https://aptachicago.tenniscores.com/?mod=nndz-TjJiOWtORzkwTlJFb0NVU1NzOD0%3D&team=nndz-WkNTNXdiMzc%3D",
    "source_league": "APTA_CHICAGO",
    "Scraped At": "2025-09-16T21:03:46.934211"
  },
  {
    "Player ID": "nndz-WlNlN3hMZitnQT09",
    "First Name": "Alec",
    "Last Name": "Miz",
    "Team": "Michigan Shores 38",
    "Series": "Series 38",
    "League": "APTA_CHICAGO",
    "Club": "Michigan Shores 38",
    "PTI": "67.3",
    "Wins": "0",
    "Losses": "0",
    "Win %": "0.0%",
    "Captain": "",
    "Source URL": "https://aptachicago.tenniscores.com/?mod=nndz-TjJiOWtORzkwTlJFb0NVU1NzOD0%3D&team=nndz-WkNTNXdiMzc%3D",
    "source_league": "APTA_CHICAGO",
    "Scraped At": "2025-09-16T21:03:46.934259"
  },
  {
    "Player ID": "nndz-WkNDOXdMNzhnUT09",
    "First Name": "Dan",
    "Last Name": "Neely",
    "Team": "Michigan Shores 38",
    "Series": "Series 38",
    "League": "APTA_CHICAGO",
    "Club": "Michigan Shores 38",
    "PTI": "82.2",
    "Wins": "0",
    "Losses": "0",
    "Win %": "0.0%",
    "Captain": "",
    "Source URL": "https://aptachicago.tenniscores.com/?mod=nndz-TjJiOWtORzkwTlJFb0NVU1NzOD0%3D&team=nndz-WkNTNXdiMzc%3D",
    "source_league": "APTA_CHICAGO",
    "Scraped At": "2025-09-16T21:03:46.934300"
  },
  {
    "Player ID": "nndz-WlNlN3g3NzRqUT09",
    "First Name": "Thomas",
    "Last Name": "Norwood",
    "Team": "Michigan Shores 38",
    "Series": "Series 38",
    "League": "APTA_CHICAGO",
    "Club": "Michigan Shores 38",
    "PTI": "67.4",
    "Wins": "0",
    "Losses": "0",
    "Win %": "0.0%",
    "Captain": "",
    "Source URL": "https://aptachicago.tenniscores.com/?mod=nndz-TjJiOWtORzkwTlJFb0NVU1NzOD0%3D&team=nndz-WkNTNXdiMzc%3D",
    "source_league": "APTA_CHICAGO",
    "Scraped At": "2025-09-16T21:03:46.934350"
  },
  {
    "Player ID": "nndz-WlNlN3hMZi9nZz09",
    "First Name": "Bill",
    "Last Name": "OConnor",
    "Team": "Michigan Shores 38",
    "Series": "Series 38",
    "League": "APTA_CHICAGO",
    "Club": "Michigan Shores 38",
    "PTI": "57.4",
    "Wins": "0",
    "Losses": "0",
    "Win %": "0.0%",
    "Captain": "",
    "Source URL": "https://aptachicago.tenniscores.com/?mod=nndz-TjJiOWtORzkwTlJFb0NVU1NzOD0%3D&team=nndz-WkNTNXdiMzc%3D",
    "source_league": "APTA_CHICAGO",
    "Scraped At": "2025-09-16T21:03:46.934386"
  },
  {
    "Player ID": "nndz-WkNHd3diLzloQT09",
    "First Name": "Chirag",
    "Last Name": "Patel",
    "Team": "Michigan Shores 38",
    "Series": "Series 38",
    "League": "APTA_CHICAGO",
    "Club": "Michigan Shores 38",
    "PTI": "71.8",
    "Wins": "0",
    "Losses": "0",
    "Win %": "0.0%",
    "Captain": "",
    "Source URL": "https://aptachicago.tenniscores.com/?mod=nndz-TjJiOWtORzkwTlJFb0NVU1NzOD0%3D&team=nndz-WkNTNXdiMzc%3D",
    "source_league": "APTA_CHICAGO",
    "Scraped At": "2025-09-16T21:03:46.934421"
  },
  {
    "Player ID": "nndz-WlNlNnhMNzdqUT09",
    "First Name": "Connor",
    "Last Name": "Patterson",
    "Team": "Michigan Shores 38",
    "Series": "Series 38",
    "League": "APTA_CHICAGO",
    "Club": "Michigan Shores 38",
    "PTI": "71.2",
    "Wins": "0",
    "Losses": "0",
    "Win %": "0.0%",
    "Captain": "",
    "Source URL": "https://aptachicago.tenniscores.com/?mod=nndz-TjJiOWtORzkwTlJFb0NVU1NzOD0%3D&team=nndz-WkNTNXdiMzc%3D",
    "source_league": "APTA_CHICAGO",
    "Scraped At": "2025-09-16T21:03:46.934457"
  },
  {
    "Player ID": "nndz-WkMrK3dybitnZz09",
    "First Name": "ROBERT",
    "Last Name": "W PETTI",
    "Team": "Michigan Shores 38",
    "Series": "Series 38",
    "League": "APTA_CHICAGO",
    "Club": "Michigan Shores 38",
    "PTI": "N/A",
    "Wins": "0",
    "Losses": "0",
    "Win %": "0.0%",
    "Captain": "",
    "Source URL": "https://aptachicago.tenniscores.com/?mod=nndz-TjJiOWtORzkwTlJFb0NVU1NzOD0%3D&team=nndz-WkNTNXdiMzc%3D",
    "source_league": "APTA_CHICAGO",
    "Scraped At": "2025-09-16T21:03:46.934501"
  },
  {
    "Player ID": "nndz-WkM2L3g3LzlnQT09",
    "First Name": "Steven",
    "Last Name": "Schwulst",
    "Team": "Michigan Shores 38",
    "Series": "Series 38",
    "League": "APTA_CHICAGO",
    "Club": "Michigan Shores 38",
    "PTI": "N/A",
    "Wins": "0",
    "Losses": "0",
    "Win %": "0.0%",
    "Captain": "",
    "Source URL": "https://aptachicago.tenniscores.com/?mod=nndz-TjJiOWtORzkwTlJFb0NVU1NzOD0%3D&team=nndz-WkNTNXdiMzc%3D",
    "source_league": "APTA_CHICAGO",
    "Scraped At": "2025-09-16T21:03:46.934554"
  },
  {
    "Player ID": "nndz-WlNhNndMdjhqQT09",
    "First Name": "Reid",
    "Last Name": "Snellenbarger",
    "Team": "Michigan Shores 38",
    "Series": "Series 38",
    "League": "APTA_CHICAGO",
    "Club": "Michigan Shores 38",
    "PTI": "N/A",
    "Wins": "0",
    "Losses": "0",
    "Win %": "0.0%",
    "Captain": "",
    "Source URL": "https://aptachicago.tenniscores.com/?mod=nndz-TjJiOWtORzkwTlJFb0NVU1NzOD0%3D&team=nndz-WkNTNXdiMzc%3D",
    "source_league": "APTA_CHICAGO",
    "Scraped At": "2025-09-16T21:03:46.934590"
  },
  {
    "Player ID": "nndz-WkNHd3diejZodz09",
    "First Name": "Craig",
    "Last Name": "Tagliamonte",
    "Team": "Michigan Shores 38",
    "Series": "Series 38",
    "League": "APTA_CHICAGO",
    "Club": "Michigan Shores 38",
    "PTI": "N/A",
    "Wins": "0",
    "Losses": "0",
    "Win %": "0.0%",
    "Captain": "",
    "Source URL": "https://aptachicago.tenniscores.com/?mod=nndz-TjJiOWtORzkwTlJFb0NVU1NzOD0%3D&team=nndz-WkNTNXdiMzc%3D",
    "source_league": "APTA_CHICAGO",
    "Scraped At": "2025-09-16T21:03:46.934626"
  },
  {
    "Player ID": "nndz-WlNlNnhMLzhnUT09",
    "First Name": "Michael",
    "Last Name": "Welch",
    "Team": "Michigan Shores 38",
    "Series": "Series 38",
    "League": "APTA_CHICAGO",
    "Club": "Michigan Shores 38",
    "PTI": "N/A",
    "Wins": "0",
    "Losses": "0",
    "Win %": "0.0%",
    "Captain": "",
    "Source URL": "https://aptachicago.tenniscores.com/?mod=nndz-TjJiOWtORzkwTlJFb0NVU1NzOD0%3D&team=nndz-WkNTNXdiMzc%3D",
    "source_league": "APTA_CHICAGO",
    "Scraped At": "2025-09-16T21:03:46.934662"
  },
  {
    "Player ID": "nndz-WlNlN3dyMzZoUT09",
    "First Name": "Zach",
    "Last Name": "Mulcrone",
    "Team": "Park RIdge CC 38",
    "Series": "Series 38",
    "League": "APTA_CHICAGO",
    "Club": "Park RIdge CC",
    "PTI": "80.0",
    "Wins": "0",
    "Losses": "0",
    "Win %": "0.0%",
    "Captain": "",
    "Source URL": "https://aptachicago.tenniscores.com/?mod=nndz-TjJiOWtORzkwTlJFb0NVU1NzOD0%3D&team=nndz-WkNDOXliNzY%3D",
    "source_league": "APTA_CHICAGO",
    "Scraped At": "2025-09-16T21:03:50.584849"
  },
  {
    "Player ID": "nndz-WlNlN3dyei9oQT09",
    "First Name": "Brett",
    "Last Name": "Mazurek",
    "Team": "Park RIdge CC 38",
    "Series": "Series 38",
    "League": "APTA_CHICAGO",
    "Club": "Park RIdge CC 38",
    "PTI": "88.9",
    "Wins": "0",
    "Losses": "0",
    "Win %": "0.0%",
    "Captain": "",
    "Source URL": "https://aptachicago.tenniscores.com/?mod=nndz-TjJiOWtORzkwTlJFb0NVU1NzOD0%3D&team=nndz-WkNDOXliNzY%3D",
    "source_league": "APTA_CHICAGO",
    "Scraped At": "2025-09-16T21:03:50.584906"
  },
  {
    "Player ID": "nndz-WlNlN3hMZjhoZz09",
    "First Name": "Kevin",
    "Last Name": "Bogner",
    "Team": "Park RIdge CC 38",
    "Series": "Series 38",
    "League": "APTA_CHICAGO",
    "Club": "Park RIdge CC 38",
    "PTI": "84.1",
    "Wins": "0",
    "Losses": "0",
    "Win %": "0.0%",
    "Captain": "",
    "Source URL": "https://aptachicago.tenniscores.com/?mod=nndz-TjJiOWtORzkwTlJFb0NVU1NzOD0%3D&team=nndz-WkNDOXliNzY%3D",
    "source_league": "APTA_CHICAGO",
    "Scraped At": "2025-09-16T21:03:50.584958"
  },
  {
    "Player ID": "nndz-WlNTN3hybndndz09",
    "First Name": "Mike",
    "Last Name": "Boychuck",
    "Team": "Park RIdge CC 38",
    "Series": "Series 38",
    "League": "APTA_CHICAGO",
    "Club": "Park RIdge CC 38",
    "PTI": "N/A",
    "Wins": "0",
    "Losses": "0",
    "Win %": "0.0%",
    "Captain": "",
    "Source URL": "https://aptachicago.tenniscores.com/?mod=nndz-TjJiOWtORzkwTlJFb0NVU1NzOD0%3D&team=nndz-WkNDOXliNzY%3D",
    "source_league": "APTA_CHICAGO",
    "Scraped At": "2025-09-16T21:03:50.585009"
  },
  {
    "Player ID": "nndz-WkMrK3dybndnZz09",
    "First Name": "Ryan",
    "Last Name": "Braun",
    "Team": "Park RIdge CC 38",
    "Series": "Series 38",
    "League": "APTA_CHICAGO",
    "Club": "Park RIdge CC 38",
    "PTI": "80.2",
    "Wins": "0",
    "Losses": "0",
    "Win %": "0.0%",
    "Captain": "",
    "Source URL": "https://aptachicago.tenniscores.com/?mod=nndz-TjJiOWtORzkwTlJFb0NVU1NzOD0%3D&team=nndz-WkNDOXliNzY%3D",
    "source_league": "APTA_CHICAGO",
    "Scraped At": "2025-09-16T21:03:50.585051"
  },
  {
    "Player ID": "nndz-WlNTN3hyajloUT09",
    "First Name": "Josh",
    "Last Name": "Brown",
    "Team": "Park RIdge CC 38",
    "Series": "Series 38",
    "League": "APTA_CHICAGO",
    "Club": "Park RIdge CC 38",
    "PTI": "N/A",
    "Wins": "0",
    "Losses": "0",
    "Win %": "0.0%",
    "Captain": "",
    "Source URL": "https://aptachicago.tenniscores.com/?mod=nndz-TjJiOWtORzkwTlJFb0NVU1NzOD0%3D&team=nndz-WkNDOXliNzY%3D",
    "source_league": "APTA_CHICAGO",
    "Scraped At": "2025-09-16T21:03:50.585092"
  },
  {
    "Player ID": "nndz-WlNhOXhMNzdnQT09",
    "First Name": "Rick",
    "Last Name": "Cosgrove",
    "Team": "Park RIdge CC 38",
    "Series": "Series 38",
    "League": "APTA_CHICAGO",
    "Club": "Park RIdge CC 38",
    "PTI": "86.7",
    "Wins": "0",
    "Losses": "0",
    "Win %": "0.0%",
    "Captain": "",
    "Source URL": "https://aptachicago.tenniscores.com/?mod=nndz-TjJiOWtORzkwTlJFb0NVU1NzOD0%3D&team=nndz-WkNDOXliNzY%3D",
    "source_league": "APTA_CHICAGO",
    "Scraped At": "2025-09-16T21:03:50.585132"
  },
  {
    "Player ID": "nndz-WlNTN3hyajZqQT09",
    "First Name": "Christopher",
    "Last Name": "DiFranco",
    "Team": "Park RIdge CC 38",
    "Series": "Series 38",
    "League": "APTA_CHICAGO",
    "Club": "Park RIdge CC 38",
    "PTI": "N/A",
    "Wins": "0",
    "Losses": "0",
    "Win %": "0.0%",
    "Captain": "",
    "Source URL": "https://aptachicago.tenniscores.com/?mod=nndz-TjJiOWtORzkwTlJFb0NVU1NzOD0%3D&team=nndz-WkNDOXliNzY%3D",
    "source_league": "APTA_CHICAGO",
    "Scraped At": "2025-09-16T21:03:50.585172"
  },
  {
    "Player ID": "nndz-WlNTN3hybjVnZz09",
    "First Name": "Michael",
    "Last Name": "Goldstein",
    "Team": "Park RIdge CC 38",
    "Series": "Series 38",
    "League": "APTA_CHICAGO",
    "Club": "Park RIdge CC 38",
    "PTI": "N/A",
    "Wins": "0",
    "Losses": "0",
    "Win %": "0.0%",
    "Captain": "",
    "Source URL": "https://aptachicago.tenniscores.com/?mod=nndz-TjJiOWtORzkwTlJFb0NVU1NzOD0%3D&team=nndz-WkNDOXliNzY%3D",
    "source_league": "APTA_CHICAGO",
    "Scraped At": "2025-09-16T21:03:50.585212"
  },
  {
    "Player ID": "nndz-WkMrK3diZjdqQT09",
    "First Name": "Johnathan",
    "Last Name": "Hirsh",
    "Team": "Park RIdge CC 38",
    "Series": "Series 38",
    "League": "APTA_CHICAGO",
    "Club": "Park RIdge CC 38",
    "PTI": "83.6",
    "Wins": "0",
    "Losses": "0",
    "Win %": "0.0%",
    "Captain": "",
    "Source URL": "https://aptachicago.tenniscores.com/?mod=nndz-TjJiOWtORzkwTlJFb0NVU1NzOD0%3D&team=nndz-WkNDOXliNzY%3D",
    "source_league": "APTA_CHICAGO",
    "Scraped At": "2025-09-16T21:03:50.585254"
  },
  {
    "Player ID": "nndz-WkM2L3dMai9nZz09",
    "First Name": "Mark",
    "Last Name": "Hoetling",
    "Team": "Park RIdge CC 38",
    "Series": "Series 38",
    "League": "APTA_CHICAGO",
    "Club": "Park RIdge CC 38",
    "PTI": "80.4",
    "Wins": "0",
    "Losses": "0",
    "Win %": "0.0%",
    "Captain": "",
    "Source URL": "https://aptachicago.tenniscores.com/?mod=nndz-TjJiOWtORzkwTlJFb0NVU1NzOD0%3D&team=nndz-WkNDOXliNzY%3D",
    "source_league": "APTA_CHICAGO",
    "Scraped At": "2025-09-16T21:03:50.585298"
  },
  {
    "Player ID": "nndz-WkNHeHdyMzRnQT09",
    "First Name": "Jay",
    "Last Name": "Munce",
    "Team": "Park RIdge CC 38",
    "Series": "Series 38",
    "League": "APTA_CHICAGO",
    "Club": "Park RIdge CC 38",
    "PTI": "80.9",
    "Wins": "0",
    "Losses": "0",
    "Win %": "0.0%",
    "Captain": "",
    "Source URL": "https://aptachicago.tenniscores.com/?mod=nndz-TjJiOWtORzkwTlJFb0NVU1NzOD0%3D&team=nndz-WkNDOXliNzY%3D",
    "source_league": "APTA_CHICAGO",
    "Scraped At": "2025-09-16T21:03:50.585340"
  },
  {
    "Player ID": "nndz-WlNTN3hybjRoUT09",
    "First Name": "Richard",
    "Last Name": "Pedi",
    "Team": "Park RIdge CC 38",
    "Series": "Series 38",
    "League": "APTA_CHICAGO",
    "Club": "Park RIdge CC 38",
    "PTI": "N/A",
    "Wins": "0",
    "Losses": "0",
    "Win %": "0.0%",
    "Captain": "",
    "Source URL": "https://aptachicago.tenniscores.com/?mod=nndz-TjJiOWtORzkwTlJFb0NVU1NzOD0%3D&team=nndz-WkNDOXliNzY%3D",
    "source_league": "APTA_CHICAGO",
    "Scraped At": "2025-09-16T21:03:50.585380"
  },
  {
    "Player ID": "nndz-WlNlNnhMandoUT09",
    "First Name": "Bryan",
    "Last Name": "Rutherford",
    "Team": "Park RIdge CC 38",
    "Series": "Series 38",
    "League": "APTA_CHICAGO",
    "Club": "Park RIdge CC 38",
    "PTI": "85.2",
    "Wins": "0",
    "Losses": "0",
    "Win %": "0.0%",
    "Captain": "",
    "Source URL": "https://aptachicago.tenniscores.com/?mod=nndz-TjJiOWtORzkwTlJFb0NVU1NzOD0%3D&team=nndz-WkNDOXliNzY%3D",
    "source_league": "APTA_CHICAGO",
    "Scraped At": "2025-09-16T21:03:50.585419"
  },
  {
    "Player ID": "nndz-WkNDd3lMejRqQT09",
    "First Name": "Jim",
    "Last Name": "Stinson",
    "Team": "Park RIdge CC 38",
    "Series": "Series 38",
    "League": "APTA_CHICAGO",
    "Club": "Park RIdge CC 38",
    "PTI": "90.3",
    "Wins": "0",
    "Losses": "0",
    "Win %": "0.0%",
    "Captain": "",
    "Source URL": "https://aptachicago.tenniscores.com/?mod=nndz-TjJiOWtORzkwTlJFb0NVU1NzOD0%3D&team=nndz-WkNDOXliNzY%3D",
    "source_league": "APTA_CHICAGO",
    "Scraped At": "2025-09-16T21:03:50.585459"
  },
  {
    "Player ID": "nndz-WkNDd3lMejRndz09",
    "First Name": "Raman",
    "Last Name": "Yousefi",
    "Team": "Park RIdge CC 38",
    "Series": "Series 38",
    "League": "APTA_CHICAGO",
    "Club": "Park RIdge CC 38",
    "PTI": "80.2",
    "Wins": "0",
    "Losses": "0",
    "Win %": "0.0%",
    "Captain": "",
    "Source URL": "https://aptachicago.tenniscores.com/?mod=nndz-TjJiOWtORzkwTlJFb0NVU1NzOD0%3D&team=nndz-WkNDOXliNzY%3D",
    "source_league": "APTA_CHICAGO",
    "Scraped At": "2025-09-16T21:03:50.585499"
  },
  {
    "Player ID": "nndz-WkM2L3c3ejRoZz09",
    "First Name": "Patrick",
    "Last Name": "Osborne",
    "Team": "Skokie 38",
    "Series": "Series 38",
    "League": "APTA_CHICAGO",
    "Club": "Skokie",
    "PTI": "70.2",
    "Wins": "0",
    "Losses": "0",
    "Win %": "0.0%",
    "Captain": "",
    "Source URL": "https://aptachicago.tenniscores.com/?mod=nndz-TjJiOWtORzkwTlJFb0NVU1NzOD0%3D&team=nndz-WkM2L3dMejk%3D",
    "source_league": "APTA_CHICAGO",
    "Scraped At": "2025-09-16T21:03:54.588556"
  },
  {
    "Player ID": "nndz-WkM2L3g3bjloUT09",
    "First Name": "Dave",
    "Last Name": "Eagleton",
    "Team": "Skokie 38",
    "Series": "Series 38",
    "League": "APTA_CHICAGO",
    "Club": "Skokie 38",
    "PTI": "65.0",
    "Wins": "0",
    "Losses": "0",
    "Win %": "0.0%",
    "Captain": "",
    "Source URL": "https://aptachicago.tenniscores.com/?mod=nndz-TjJiOWtORzkwTlJFb0NVU1NzOD0%3D&team=nndz-WkM2L3dMejk%3D",
    "source_league": "APTA_CHICAGO",
    "Scraped At": "2025-09-16T21:03:54.588891"
  },
  {
    "Player ID": "nndz-WlNlN3hiL3hqUT09",
    "First Name": "Adam",
    "Last Name": "Crandall",
    "Team": "Skokie 38",
    "Series": "Series 38",
    "League": "APTA_CHICAGO",
    "Club": "Skokie 38",
    "PTI": "73.9",
    "Wins": "0",
    "Losses": "0",
    "Win %": "0.0%",
    "Captain": "",
    "Source URL": "https://aptachicago.tenniscores.com/?mod=nndz-TjJiOWtORzkwTlJFb0NVU1NzOD0%3D&team=nndz-WkM2L3dMejk%3D",
    "source_league": "APTA_CHICAGO",
    "Scraped At": "2025-09-16T21:03:54.589215"
  },
  {
    "Player ID": "nndz-WkNHd3hMMy9nQT09",
    "First Name": "John",
    "Last Name": "Frank",
    "Team": "Skokie 38",
    "Series": "Series 38",
    "League": "APTA_CHICAGO",
    "Club": "Skokie 38",
    "PTI": "76.0",
    "Wins": "0",
    "Losses": "0",
    "Win %": "0.0%",
    "Captain": "",
    "Source URL": "https://aptachicago.tenniscores.com/?mod=nndz-TjJiOWtORzkwTlJFb0NVU1NzOD0%3D&team=nndz-WkM2L3dMejk%3D",
    "source_league": "APTA_CHICAGO",
    "Scraped At": "2025-09-16T21:03:54.589373"
  },
  {
    "Player ID": "nndz-WlNlNnhibjRnQT09",
    "First Name": "Connor",
    "Last Name": "Goggin",
    "Team": "Skokie 38",
    "Series": "Series 38",
    "League": "APTA_CHICAGO",
    "Club": "Skokie 38",
    "PTI": "N/A",
    "Wins": "0",
    "Losses": "0",
    "Win %": "0.0%",
    "Captain": "",
    "Source URL": "https://aptachicago.tenniscores.com/?mod=nndz-TjJiOWtORzkwTlJFb0NVU1NzOD0%3D&team=nndz-WkM2L3dMejk%3D",
    "source_league": "APTA_CHICAGO",
    "Scraped At": "2025-09-16T21:03:54.589641"
  },
  {
    "Player ID": "nndz-WkM2L3c3ejRnQT09",
    "First Name": "Chris",
    "Last Name": "Harlin",
    "Team": "Skokie 38",
    "Series": "Series 38",
    "League": "APTA_CHICAGO",
    "Club": "Skokie 38",
    "PTI": "81.4",
    "Wins": "0",
    "Losses": "0",
    "Win %": "0.0%",
    "Captain": "",
    "Source URL": "https://aptachicago.tenniscores.com/?mod=nndz-TjJiOWtORzkwTlJFb0NVU1NzOD0%3D&team=nndz-WkM2L3dMejk%3D",
    "source_league": "APTA_CHICAGO",
    "Scraped At": "2025-09-16T21:03:54.590155"
  },
  {
    "Player ID": "nndz-WkNHeHhyejZoUT09",
    "First Name": "Scott",
    "Last Name": "Mackey",
    "Team": "Skokie 38",
    "Series": "Series 38",
    "League": "APTA_CHICAGO",
    "Club": "Skokie 38",
    "PTI": "N/A",
    "Wins": "0",
    "Losses": "0",
    "Win %": "0.0%",
    "Captain": "",
    "Source URL": "https://aptachicago.tenniscores.com/?mod=nndz-TjJiOWtORzkwTlJFb0NVU1NzOD0%3D&team=nndz-WkM2L3dMejk%3D",
    "source_league": "APTA_CHICAGO",
    "Scraped At": "2025-09-16T21:03:54.590587"
  },
  {
    "Player ID": "nndz-WlNlN3c3bi9oUT09",
    "First Name": "Ben",
    "Last Name": "Odle",
    "Team": "Skokie 38",
    "Series": "Series 38",
    "League": "APTA_CHICAGO",
    "Club": "Skokie 38",
    "PTI": "N/A",
    "Wins": "0",
    "Losses": "0",
    "Win %": "0.0%",
    "Captain": "",
    "Source URL": "https://aptachicago.tenniscores.com/?mod=nndz-TjJiOWtORzkwTlJFb0NVU1NzOD0%3D&team=nndz-WkM2L3dMejk%3D",
    "source_league": "APTA_CHICAGO",
    "Scraped At": "2025-09-16T21:03:54.590984"
  },
  {
    "Player ID": "nndz-WkNDd3lMcitqQT09",
    "First Name": "Mike",
    "Last Name": "paleczny",
    "Team": "Skokie 38",
    "Series": "Series 38",
    "League": "APTA_CHICAGO",
    "Club": "Skokie 38",
    "PTI": "N/A",
    "Wins": "0",
    "Losses": "0",
    "Win %": "0.0%",
    "Captain": "",
    "Source URL": "https://aptachicago.tenniscores.com/?mod=nndz-TjJiOWtORzkwTlJFb0NVU1NzOD0%3D&team=nndz-WkM2L3dMejk%3D",
    "source_league": "APTA_CHICAGO",
    "Scraped At": "2025-09-16T21:03:54.591559"
  },
  {
    "Player ID": "nndz-WlNlN3lidnhnQT09",
    "First Name": "Quinn",
    "Last Name": "Roddy",
    "Team": "Skokie 38",
    "Series": "Series 38",
    "League": "APTA_CHICAGO",
    "Club": "Skokie 38",
    "PTI": "N/A",
    "Wins": "0",
    "Losses": "0",
    "Win %": "0.0%",
    "Captain": "",
    "Source URL": "https://aptachicago.tenniscores.com/?mod=nndz-TjJiOWtORzkwTlJFb0NVU1NzOD0%3D&team=nndz-WkM2L3dMejk%3D",
    "source_league": "APTA_CHICAGO",
    "Scraped At": "2025-09-16T21:03:54.592041"
  },
  {
    "Player ID": "nndz-WkM2K3libitnUT09",
    "First Name": "Peter",
    "Last Name": "Wilson",
    "Team": "Skokie 38",
    "Series": "Series 38",
    "League": "APTA_CHICAGO",
    "Club": "Skokie 38",
    "PTI": "69.2",
    "Wins": "0",
    "Losses": "0",
    "Win %": "0.0%",
    "Captain": "",
    "Source URL": "https://aptachicago.tenniscores.com/?mod=nndz-TjJiOWtORzkwTlJFb0NVU1NzOD0%3D&team=nndz-WkM2L3dMejk%3D",
    "source_league": "APTA_CHICAGO",
    "Scraped At": "2025-09-16T21:03:54.592204"
  },
  {
    "Player ID": "nndz-WlNlN3lidjVodz09",
    "First Name": "Jack",
    "Last Name": "Winkler",
    "Team": "Skokie 38",
    "Series": "Series 38",
    "League": "APTA_CHICAGO",
    "Club": "Skokie 38",
    "PTI": "N/A",
    "Wins": "0",
    "Losses": "0",
    "Win %": "0.0%",
    "Captain": "",
    "Source URL": "https://aptachicago.tenniscores.com/?mod=nndz-TjJiOWtORzkwTlJFb0NVU1NzOD0%3D&team=nndz-WkM2L3dMejk%3D",
    "source_league": "APTA_CHICAGO",
    "Scraped At": "2025-09-16T21:03:54.592560"
  },
  {
    "Player ID": "nndz-WlNlN3liZjhoZz09",
    "First Name": "Scott",
    "Last Name": "Wojteczko",
    "Team": "Skokie 38",
    "Series": "Series 38",
    "League": "APTA_CHICAGO",
    "Club": "Skokie 38",
    "PTI": "77.3",
    "Wins": "0",
    "Losses": "0",
    "Win %": "0.0%",
    "Captain": "",
    "Source URL": "https://aptachicago.tenniscores.com/?mod=nndz-TjJiOWtORzkwTlJFb0NVU1NzOD0%3D&team=nndz-WkM2L3dMejk%3D",
    "source_league": "APTA_CHICAGO",
    "Scraped At": "2025-09-16T21:03:54.592828"
  },
  {
    "Player ID": "nndz-WkM2L3c3Lzdodz09",
    "First Name": "John",
    "Last Name": "Wysockey",
    "Team": "Skokie 38",
    "Series": "Series 38",
    "League": "APTA_CHICAGO",
    "Club": "Skokie 38",
    "PTI": "74.0",
    "Wins": "0",
    "Losses": "0",
    "Win %": "0.0%",
    "Captain": "",
    "Source URL": "https://aptachicago.tenniscores.com/?mod=nndz-TjJiOWtORzkwTlJFb0NVU1NzOD0%3D&team=nndz-WkM2L3dMejk%3D",
    "source_league": "APTA_CHICAGO",
    "Scraped At": "2025-09-16T21:03:54.593358"
  },
  {
    "Player ID": "nndz-WlNlN3lMaitodz09",
    "First Name": "Jeremy",
    "Last Name": "Zeman",
    "Team": "Skokie 38",
    "Series": "Series 38",
    "League": "APTA_CHICAGO",
    "Club": "Skokie 38",
    "PTI": "86.4",
    "Wins": "0",
    "Losses": "0",
    "Win %": "0.0%",
    "Captain": "",
    "Source URL": "https://aptachicago.tenniscores.com/?mod=nndz-TjJiOWtORzkwTlJFb0NVU1NzOD0%3D&team=nndz-WkM2L3dMejk%3D",
    "source_league": "APTA_CHICAGO",
    "Scraped At": "2025-09-16T21:03:54.593587"
  },
  {
    "Player ID": "nndz-WkNHeHdiZjZoUT09",
    "First Name": "Marc",
    "Last Name": "Sher",
    "Team": "Tennaqua 38",
    "Series": "Series 38",
    "League": "APTA_CHICAGO",
    "Club": "Tennaqua",
    "PTI": "72.7",
    "Wins": "0",
    "Losses": "0",
    "Win %": "0.0%",
    "Captain": "",
    "Source URL": "https://aptachicago.tenniscores.com/?mod=nndz-TjJiOWtORzkwTlJFb0NVU1NzOD0%3D&team=nndz-WkNPOHhybis%3D",
    "source_league": "APTA_CHICAGO",
    "Scraped At": "2025-09-16T21:03:58.280519"
  },
  {
    "Player ID": "nndz-WkM2eHdydndnZz09",
    "First Name": "Brad",
    "Last Name": "Auerbach",
    "Team": "Tennaqua 38",
    "Series": "Series 38",
    "League": "APTA_CHICAGO",
    "Club": "Tennaqua 38",
    "PTI": "73.2",
    "Wins": "0",
    "Losses": "0",
    "Win %": "0.0%",
    "Captain": "",
    "Source URL": "https://aptachicago.tenniscores.com/?mod=nndz-TjJiOWtORzkwTlJFb0NVU1NzOD0%3D&team=nndz-WkNPOHhybis%3D",
    "source_league": "APTA_CHICAGO",
    "Scraped At": "2025-09-16T21:03:58.280573"
  },
  {
    "Player ID": "nndz-WlNTN3c3cnhnUT09",
    "First Name": "Ryan",
    "Last Name": "Beattie",
    "Team": "Tennaqua 38",
    "Series": "Series 38",
    "League": "APTA_CHICAGO",
    "Club": "Tennaqua 38",
    "PTI": "N/A",
    "Wins": "0",
    "Losses": "0",
    "Win %": "0.0%",
    "Captain": "",
    "Source URL": "https://aptachicago.tenniscores.com/?mod=nndz-TjJiOWtORzkwTlJFb0NVU1NzOD0%3D&team=nndz-WkNPOHhybis%3D",
    "source_league": "APTA_CHICAGO",
    "Scraped At": "2025-09-16T21:03:58.280614"
  },
  {
    "Player ID": "nndz-WlNTN3liYjZnZz09",
    "First Name": "Attila",
    "Last Name": "Farkas",
    "Team": "Tennaqua 38",
    "Series": "Series 38",
    "League": "APTA_CHICAGO",
    "Club": "Tennaqua 38",
    "PTI": "N/A",
    "Wins": "0",
    "Losses": "0",
    "Win %": "0.0%",
    "Captain": "",
    "Source URL": "https://aptachicago.tenniscores.com/?mod=nndz-TjJiOWtORzkwTlJFb0NVU1NzOD0%3D&team=nndz-WkNPOHhybis%3D",
    "source_league": "APTA_CHICAGO",
    "Scraped At": "2025-09-16T21:03:58.280652"
  },
  {
    "Player ID": "nndz-WlNTN3dMcjlnQT09",
    "First Name": "Adan",
    "Last Name": "Galvan",
    "Team": "Tennaqua 38",
    "Series": "Series 38",
    "League": "APTA_CHICAGO",
    "Club": "Tennaqua 38",
    "PTI": "N/A",
    "Wins": "0",
    "Losses": "0",
    "Win %": "0.0%",
    "Captain": "",
    "Source URL": "https://aptachicago.tenniscores.com/?mod=nndz-TjJiOWtORzkwTlJFb0NVU1NzOD0%3D&team=nndz-WkNPOHhybis%3D",
    "source_league": "APTA_CHICAGO",
    "Scraped At": "2025-09-16T21:03:58.280725"
  },
  {
    "Player ID": "nndz-WkM2L3c3bi9oUT09",
    "First Name": "Steve",
    "Last Name": "Harfield",
    "Team": "Tennaqua 38",
    "Series": "Series 38",
    "League": "APTA_CHICAGO",
    "Club": "Tennaqua 38",
    "PTI": "75.4",
    "Wins": "0",
    "Losses": "0",
    "Win %": "0.0%",
    "Captain": "",
    "Source URL": "https://aptachicago.tenniscores.com/?mod=nndz-TjJiOWtORzkwTlJFb0NVU1NzOD0%3D&team=nndz-WkNPOHhybis%3D",
    "source_league": "APTA_CHICAGO",
    "Scraped At": "2025-09-16T21:03:58.280768"
  },
  {
    "Player ID": "nndz-WlNTN3dybjZqQT09",
    "First Name": "Frank",
    "Last Name": "Hilvers",
    "Team": "Tennaqua 38",
    "Series": "Series 38",
    "League": "APTA_CHICAGO",
    "Club": "Tennaqua 38",
    "PTI": "N/A",
    "Wins": "0",
    "Losses": "0",
    "Win %": "0.0%",
    "Captain": "",
    "Source URL": "https://aptachicago.tenniscores.com/?mod=nndz-TjJiOWtORzkwTlJFb0NVU1NzOD0%3D&team=nndz-WkNPOHhybis%3D",
    "source_league": "APTA_CHICAGO",
    "Scraped At": "2025-09-16T21:03:58.280805"
  },
  {
    "Player ID": "nndz-WkNDNnhyYjZnZz09",
    "First Name": "Jon",
    "Last Name": "Kochmit",
    "Team": "Tennaqua 38",
    "Series": "Series 38",
    "League": "APTA_CHICAGO",
    "Club": "Tennaqua 38",
    "PTI": "75.3",
    "Wins": "0",
    "Losses": "0",
    "Win %": "0.0%",
    "Captain": "",
    "Source URL": "https://aptachicago.tenniscores.com/?mod=nndz-TjJiOWtORzkwTlJFb0NVU1NzOD0%3D&team=nndz-WkNPOHhybis%3D",
    "source_league": "APTA_CHICAGO",
    "Scraped At": "2025-09-16T21:03:58.280847"
  },
  {
    "Player ID": "nndz-WkNHeHdiZjlnZz09",
    "First Name": "Craig",
    "Last Name": "Laufer",
    "Team": "Tennaqua 38",
    "Series": "Series 38",
    "League": "APTA_CHICAGO",
    "Club": "Tennaqua 38",
    "PTI": "73.3",
    "Wins": "0",
    "Losses": "0",
    "Win %": "0.0%",
    "Captain": "",
    "Source URL": "https://aptachicago.tenniscores.com/?mod=nndz-TjJiOWtORzkwTlJFb0NVU1NzOD0%3D&team=nndz-WkNPOHhybis%3D",
    "source_league": "APTA_CHICAGO",
    "Scraped At": "2025-09-16T21:03:58.280894"
  },
  {
    "Player ID": "nndz-WkM2L3c3bjZoQT09",
    "First Name": "Dan",
    "Last Name": "Ware",
    "Team": "Tennaqua 38",
    "Series": "Series 38",
    "League": "APTA_CHICAGO",
    "Club": "Tennaqua 38",
    "PTI": "76.7",
    "Wins": "0",
    "Losses": "0",
    "Win %": "0.0%",
    "Captain": "",
    "Source URL": "https://aptachicago.tenniscores.com/?mod=nndz-TjJiOWtORzkwTlJFb0NVU1NzOD0%3D&team=nndz-WkNPOHhybis%3D",
    "source_league": "APTA_CHICAGO",
    "Scraped At": "2025-09-16T21:03:58.280930"
  },
  {
    "Player ID": "nndz-WlNTN3liYjVnQT09",
    "First Name": "Brian",
    "Last Name": "Zambie",
    "Team": "Tennaqua 38",
    "Series": "Series 38",
    "League": "APTA_CHICAGO",
    "Club": "Tennaqua 38",
    "PTI": "N/A",
    "Wins": "0",
    "Losses": "0",
    "Win %": "0.0%",
    "Captain": "",
    "Source URL": "https://aptachicago.tenniscores.com/?mod=nndz-TjJiOWtORzkwTlJFb0NVU1NzOD0%3D&team=nndz-WkNPOHhybis%3D",
    "source_league": "APTA_CHICAGO",
    "Scraped At": "2025-09-16T21:03:58.280966"
  },
  {
    "Player ID": "nndz-WlNTN3hicjlodz09",
    "First Name": "Andrew",
    "Last Name": "Keaschall",
    "Team": "Valley Lo 38",
    "Series": "Series 38",
    "League": "APTA_CHICAGO",
    "Club": "Valley Lo",
    "PTI": "N/A",
    "Wins": "0",
    "Losses": "0",
    "Win %": "0.0%",
    "Captain": "",
    "Source URL": "https://aptachicago.tenniscores.com/?mod=nndz-TjJiOWtORzkwTlJFb0NVU1NzOD0%3D&team=nndz-WkNDOXhyZis%3D",
    "source_league": "APTA_CHICAGO",
    "Scraped At": "2025-09-16T21:04:02.084120"
  },
  {
    "Player ID": "nndz-WlNTN3hiMy9oZz09",
    "First Name": "Jack",
    "Last Name": "Gavin",
    "Team": "Valley Lo 38",
    "Series": "Series 38",
    "League": "APTA_CHICAGO",
    "Club": "Valley Lo 38",
    "PTI": "N/A",
    "Wins": "0",
    "Losses": "0",
    "Win %": "0.0%",
    "Captain": "",
    "Source URL": "https://aptachicago.tenniscores.com/?mod=nndz-TjJiOWtORzkwTlJFb0NVU1NzOD0%3D&team=nndz-WkNDOXhyZis%3D",
    "source_league": "APTA_CHICAGO",
    "Scraped At": "2025-09-16T21:04:02.084179"
  },
  {
    "Player ID": "nndz-WlNTN3hydndnQT09",
    "First Name": "John",
    "Last Name": "Baker",
    "Team": "Valley Lo 38",
    "Series": "Series 38",
    "League": "APTA_CHICAGO",
    "Club": "Valley Lo 38",
    "PTI": "N/A",
    "Wins": "0",
    "Losses": "0",
    "Win %": "0.0%",
    "Captain": "",
    "Source URL": "https://aptachicago.tenniscores.com/?mod=nndz-TjJiOWtORzkwTlJFb0NVU1NzOD0%3D&team=nndz-WkNDOXhyZis%3D",
    "source_league": "APTA_CHICAGO",
    "Scraped At": "2025-09-16T21:04:02.084233"
  },
  {
    "Player ID": "nndz-WlNTN3hiN3hnZz09",
    "First Name": "Justin",
    "Last Name": "Frosolone",
    "Team": "Valley Lo 38",
    "Series": "Series 38",
    "League": "APTA_CHICAGO",
    "Club": "Valley Lo 38",
    "PTI": "N/A",
    "Wins": "0",
    "Losses": "0",
    "Win %": "0.0%",
    "Captain": "",
    "Source URL": "https://aptachicago.tenniscores.com/?mod=nndz-TjJiOWtORzkwTlJFb0NVU1NzOD0%3D&team=nndz-WkNDOXhyZis%3D",
    "source_league": "APTA_CHICAGO",
    "Scraped At": "2025-09-16T21:04:02.084274"
  },
  {
    "Player ID": "nndz-WlNTN3hiMzdndz09",
    "First Name": "Chase",
    "Last Name": "Ignelzi",
    "Team": "Valley Lo 38",
    "Series": "Series 38",
    "League": "APTA_CHICAGO",
    "Club": "Valley Lo 38",
    "PTI": "N/A",
    "Wins": "0",
    "Losses": "0",
    "Win %": "0.0%",
    "Captain": "",
    "Source URL": "https://aptachicago.tenniscores.com/?mod=nndz-TjJiOWtORzkwTlJFb0NVU1NzOD0%3D&team=nndz-WkNDOXhyZis%3D",
    "source_league": "APTA_CHICAGO",
    "Scraped At": "2025-09-16T21:04:02.084322"
  },
  {
    "Player ID": "nndz-WkNHeHdMZi9nZz09",
    "First Name": "Ralph",
    "Last Name": "Lynch",
    "Team": "Valley Lo 38",
    "Series": "Series 38",
    "League": "APTA_CHICAGO",
    "Club": "Valley Lo 38",
    "PTI": "74.8",
    "Wins": "0",
    "Losses": "0",
    "Win %": "0.0%",
    "Captain": "",
    "Source URL": "https://aptachicago.tenniscores.com/?mod=nndz-TjJiOWtORzkwTlJFb0NVU1NzOD0%3D&team=nndz-WkNDOXhyZis%3D",
    "source_league": "APTA_CHICAGO",
    "Scraped At": "2025-09-16T21:04:02.084364"
  },
  {
    "Player ID": "nndz-WlNTN3hyajVoUT09",
    "First Name": "Bryant",
    "Last Name": "Merryman",
    "Team": "Valley Lo 38",
    "Series": "Series 38",
    "League": "APTA_CHICAGO",
    "Club": "Valley Lo 38",
    "PTI": "N/A",
    "Wins": "0",
    "Losses": "0",
    "Win %": "0.0%",
    "Captain": "",
    "Source URL": "https://aptachicago.tenniscores.com/?mod=nndz-TjJiOWtORzkwTlJFb0NVU1NzOD0%3D&team=nndz-WkNDOXhyZis%3D",
    "source_league": "APTA_CHICAGO",
    "Scraped At": "2025-09-16T21:04:02.084405"
  },
  {
    "Player ID": "nndz-WlNTN3hyandoZz09",
    "First Name": "Matt",
    "Last Name": "Panzica",
    "Team": "Valley Lo 38",
    "Series": "Series 38",
    "League": "APTA_CHICAGO",
    "Club": "Valley Lo 38",
    "PTI": "N/A",
    "Wins": "0",
    "Losses": "0",
    "Win %": "0.0%",
    "Captain": "",
    "Source URL": "https://aptachicago.tenniscores.com/?mod=nndz-TjJiOWtORzkwTlJFb0NVU1NzOD0%3D&team=nndz-WkNDOXhyZis%3D",
    "source_league": "APTA_CHICAGO",
    "Scraped At": "2025-09-16T21:04:02.084446"
  },
  {
    "Player ID": "nndz-WlNTN3hiejhqQT09",
    "First Name": "Tony",
    "Last Name": "Saracco",
    "Team": "Valley Lo 38",
    "Series": "Series 38",
    "League": "APTA_CHICAGO",
    "Club": "Valley Lo 38",
    "PTI": "N/A",
    "Wins": "0",
    "Losses": "0",
    "Win %": "0.0%",
    "Captain": "",
    "Source URL": "https://aptachicago.tenniscores.com/?mod=nndz-TjJiOWtORzkwTlJFb0NVU1NzOD0%3D&team=nndz-WkNDOXhyZis%3D",
    "source_league": "APTA_CHICAGO",
    "Scraped At": "2025-09-16T21:04:02.084486"
  },
  {
    "Player ID": "nndz-WlNTN3hiL3dqQT09",
    "First Name": "Kevin",
    "Last Name": "Schmidt",
    "Team": "Valley Lo 38",
    "Series": "Series 38",
    "League": "APTA_CHICAGO",
    "Club": "Valley Lo 38",
    "PTI": "N/A",
    "Wins": "0",
    "Losses": "0",
    "Win %": "0.0%",
    "Captain": "",
    "Source URL": "https://aptachicago.tenniscores.com/?mod=nndz-TjJiOWtORzkwTlJFb0NVU1NzOD0%3D&team=nndz-WkNDOXhyZis%3D",
    "source_league": "APTA_CHICAGO",
    "Scraped At": "2025-09-16T21:04:02.084531"
  },
  {
    "Player ID": "nndz-WkM2L3hibjloUT09",
    "First Name": "Jim",
    "Last Name": "Tausche",
    "Team": "Valley Lo 38",
    "Series": "Series 38",
    "League": "APTA_CHICAGO",
    "Club": "Valley Lo 38",
    "PTI": "74.1",
    "Wins": "0",
    "Losses": "0",
    "Win %": "0.0%",
    "Captain": "",
    "Source URL": "https://aptachicago.tenniscores.com/?mod=nndz-TjJiOWtORzkwTlJFb0NVU1NzOD0%3D&team=nndz-WkNDOXhyZis%3D",
    "source_league": "APTA_CHICAGO",
    "Scraped At": "2025-09-16T21:04:02.084575"
  },
  {
    "Player ID": "nndz-WlNTN3liNzRqQT09",
    "First Name": "Tyler",
    "Last Name": "Ventura",
    "Team": "Valley Lo 38",
    "Series": "Series 38",
    "League": "APTA_CHICAGO",
    "Club": "Valley Lo 38",
    "PTI": "N/A",
    "Wins": "0",
    "Losses": "0",
    "Win %": "0.0%",
    "Captain": "",
    "Source URL": "https://aptachicago.tenniscores.com/?mod=nndz-TjJiOWtORzkwTlJFb0NVU1NzOD0%3D&team=nndz-WkNDOXhyZis%3D",
    "source_league": "APTA_CHICAGO",
    "Scraped At": "2025-09-16T21:04:02.084616"
  },
  {
    "Player ID": "nndz-WlNTN3hyajRoQT09",
    "First Name": "Taylor",
    "Last Name": "Wood",
    "Team": "Valley Lo 38",
    "Series": "Series 38",
    "League": "APTA_CHICAGO",
    "Club": "Valley Lo 38",
    "PTI": "N/A",
    "Wins": "0",
    "Losses": "0",
    "Win %": "0.0%",
    "Captain": "",
    "Source URL": "https://aptachicago.tenniscores.com/?mod=nndz-TjJiOWtORzkwTlJFb0NVU1NzOD0%3D&team=nndz-WkNDOXhyZis%3D",
    "source_league": "APTA_CHICAGO",
    "Scraped At": "2025-09-16T21:04:02.084656"
  }
]